Workbook

Sheet Results
A1: manual cat | B1: correct | C1: extent | D1: category | E1: titles | F1: NER | G1: NER_label | H1: desc | I1: method | J1: main_graph | K1: second_graph | L1: third_graph | M1: file_id
A2: PER | B2: 1 | C2: 1 | D2: 1 | E2: Faster than fear | F2: Haffner | G2: PER | H2: e s'adresser à... elle. En garde à vue, Haffner n'avoue toujours pas où se trouve Marce | I2: spaCy | M2: 0
A3: PER | B3: 1 | C3: 1 | D3: 1 | E3: Faster than fear | F3: Haffner | G3: PER | H3: lle n'a plus rien à voir avec l'affaire Haffner, mais celui-ci demande à ne parler qu'à | I3: spaCy_Stanza | M3: 0
A4: PER | B4: 1 | C4: 1 | D4: 1 | E4: Faster than fear | F4: Marcel | G4: PER | H4: , haffner n ' avoue toujours pas où se trouve marcel . | I4: casEN_spaCy_Stanza | J4: grfpersGenerique | M4: 0
A5: PER | B5: 0 | C5: 1 | D5: PER | E5: Faster than fear | F5: Sunny | G5: MISC | H5: ralf a pu prouver son innocence et sunny a été suspendue de ses fonctions . elle n ' | I5: Stanza | M5: 0
A6: PER | B6: 0 | C6: 1 | D6: PER | E6: Faster than fear | F6: Sunny | G6: LOC | H6: mais celui-ci demande à ne parler qu'à Sunny. D'ailleurs, elle est persuadée que Nor | I6: spaCy_Stanza | M6: 0
E7: Faster than fear | F7: affaire Haffner | G7: MISC | H7: n ' a plus rien à voir avec l ' affaire haffner , mais celui - ci demande à ne parler qu | I7: Stanza | M7: 0
A8: PER | B8: 1 | C8: 1 | D8: 1 | E8: Faster than fear | F8: Nora | G8: PER | H8: sunny . d ' ailleurs , elle est persuadée que nora a divulgué des informations à son agresseur et décide donc | I8: casEN_Stanza_priority | J8: grfpersGenerique | M8: 0
E9: Faster than fear | F9: Sunny | G9: PER | H9: Ralf a pu prouver son innocence et Sunny a été suspendue de ses fonctions. Elle | I9: spaCy | M9: 0
E10: Faster than fear | F10: Nora | G10: LOC | H10: nny. D'ailleurs, elle est persuadée que Nora a divulgué des informations à son agres | I10: spaCy | M10: 0
A11: PER | B11: 1 | C11: 1 | D11: 1 | E11: Commissaire Magellan (S1-E30) | F11: Delandin | G11: PER | H11: 'apprête à être exposée dans la galerie Delandin. Mais la directrice et fondatrice du li | I11: spaCy_Stanza_priority | M11: 1
A12: PER | B12: 1 | C12: 1 | D12: 1 | E12: Commissaire Magellan (S1-E30) | F12: Tristan Garil | G12: PER | H12: l ' oeuvre du talentueux photographe tristan garil s ' apprête à être exposée dans la galerie delandin | I12: casEN_Stanza | J12: grfpersPrenomNom | K12: grftagPrenom | L12: grftagNomFamille | M12: 1
A13: PER | B13: 1 | C13: 1 | D13: 1 | E13: Commissaire Magellan (S1-E30) | F13: Estelle Delandin | G13: PER | H13: delandin . mais la directrice et fondatrice du lieu , estelle delandin , est assassinée . le commissaire magellan et le lieutenant | I13: casEN_spaCy_Stanza | J13: grfpersPrenomNom | K13: grftagPrenom | L13: grftagNomFamille | M13: 1
E14: Commissaire Magellan (S1-E30) | F14: galerie | G14: ORG | H14: tristan garil s ' apprête à être exposée dans la galerie delandin . mais la directrice et fondatrice du lieu , | I14: casEN | J14: grforgProximite | M14: 1
E15: Commissaire Magellan (S1-E30) | F15: commissaire Magellan | G15: PER | H15: u, Estelle Delandin, est assassinée. Le commissaire Magellan et le lieutenant Selma Berrayah se char | I15: spaCy | M15: 1
E16: Commissaire Magellan (S1-E30) | F16: Delandin | G16: ORG | H16: garil s ' apprête à être exposée dans la galerie delandin . mais la directrice et fondatrice du lieu , estelle | I16: casEN | J16: grforgSeule | M16: 1
E17: Commissaire Magellan (S1-E30) | F17: Tristan | G17: MISC | H17: L'oeuvre du talentueux photographe Tristan Garil s'apprête à être exposée dans la | I17: spaCy | M17: 1
A18: PER | B18: 1 | C18: 1 | D18: 1 | E18: Commissaire Magellan (S1-E30) | F18: Selma Berrayah | G18: PER | H18: , est assassinée . le commissaire magellan et le lieutenant selma berrayah se chargent de l ' enquête . au fil de | I18: casEN_spaCy_Stanza | J18: grfpersPrenomNom | K18: grftagPrenom | L18: grftagNomFamille | M18: 1
A19: PER | B19: 1 | C19: 1 | D19: 1 | E19: Commissaire Magellan (S1-E30) | F19: Magellan | G19: PER | H19: lieu , estelle delandin , est assassinée . le commissaire magellan et le lieutenant selma berrayah se chargent de l ' | I19: casEN_Stanza | J19: grfpersContextePersonne | K19: grftagNomFamille | M19: 1
A20: PER | B20: 0 | C20: 0 | D20: PER | E20: La mort du Père Noël | F20: Le Père Noël | G20: MISC | H20: Le Père Noël est mort. Qui l'a tué ? | I20: spaCy | M20: 3
E21: La mort du Père Noël | F21: Père Noël | G21: MISC | H21: le père noël est mort . qui l ' a tué ? | I21: Stanza | M21: 3
A22: PER | B22: 1 | C22: 1 | D22: 1 | E22: La mort du Père Noël | F22: Père Noël | G22: PER | H22: le père noël est mort . qui l ' a tué ? | I22: casEN_opti | J22: grfpersAmbigus | M22: 3
A23: PER | B23: 1 | C23: 1 | D23: 1 | E23: Commissaire Magellan (S1-E30) | F23: Christophe Diaz | G23: PER | H23: jour de la fête de la bière à saignac , christophe diaz est retrouvé mort à la brasserie des trois amis . | I23: casEN_spaCy_Stanza | J23: grfpersPrenomNom | K23: grftagPrenom | L23: grftagNomFamille | M23: 7
A24: PER | B24: 1 | C24: 1 | D24: 1 | E24: Commissaire Magellan (S1-E30) | F24: Magellan | G24: PER | H24: meilleure bière artisanale . au cours de son enquête , magellan découvre . . . la rivalité qui opposait la victime | I24: casEN_spaCy_Stanza | J24: grfpersGenerique | M24: 7
A25: LOC | B25: 1 | C25: 1 | D25: 1 | E25: Commissaire Magellan (S1-E30) | F25: Saignac | G25: LOC | H25: Le jour de la fête de la Bière à Saignac, Christophe Diaz est retrouvé mort à la | I25: spaCy_Stanza | M25: 7
E26: Commissaire Magellan (S1-E30) | F26: fête de la | G26: MISC | H26: Le jour de la fête de la Bière à Saignac, Christophe Diaz est re | I26: spaCy | M26: 7
E27: Commissaire Magellan (S1-E30) | F27: Bière | G27: LOC | H27: Le jour de la fête de la Bière à Saignac, Christophe Diaz est retrouvé | I27: spaCy | M27: 7
E28: Commissaire Magellan (S1-E30) | F28: Trois Amis | G28: ORG | H28: az est retrouvé mort à la brasserie des Trois Amis. Le jeune brasseur avait un avenir des | I28: spaCy_Stanza | M28: 7
E29: Commissaire Magellan (S1-E30) | F29: brasserie | G29: ORG | H29: à saignac , christophe diaz est retrouvé mort à la brasserie des trois amis . le jeune brasseur avait un avenir | I29: casEN | J29: grforgProximite | M29: 7
A30: PER | B30: 1 | C30: 1 | D30: 1 | E30: Commissaire Magellan (S1-E30) | F30: Claude Verague | G30: PER | H30: qui opposait la victime à son beau - père , claude verague , également brasseur . mais le commissaire n ' est | I30: casEN_spaCy_Stanza | J30: grfpersPrenomNom | K30: grftagPrenom | L30: grftagNomFamille | M30: 7
A31: MISC | B31: 1 | C31: 1 | D31: 1 | E31: Commissaire Magellan (S1-E30) | F31: fête de la Bière | G31: MISC | H31: le jour de la fête de la bière à saignac , christophe diaz est retrouvé mort à la | I31: Stanza | M31: 7
E32: Commissaire Magellan (S1-E34) | F32: commissaire Magellan | G32: PER | H32: Le commissaire Magellan et la lieutenante Berrayah mènent des i | I32: spaCy | M32: 8
A33: PER | B33: 1 | C33: 1 | D33: 1 | E33: Commissaire Magellan (S1-E34) | F33: Audrey Galvi | G33: PER | H33: berrayah mènent des investigations sur l ' assassinat d ' audrey galvi , une championne olympique devenue entraîneuse . réputée pour son | I33: casEN_spaCy_Stanza | J33: grfpersPrenomNom | K33: grftagPrenom | L33: grftagNomFamille | M33: 8
A34: PER | B34: 1 | C34: 1 | D34: 1 | E34: Commissaire Magellan (S1-E34) | F34: Berrayah | G34: PER | H34: le commissaire magellan et la lieutenante berrayah mènent des investigations sur l ' assassinat d ' audrey | I34: casEN_Stanza_priority | J34: grfpersContextePersonne | K34: grftagNomFamille | M34: 8
A35: PER | B35: 1 | C35: 1 | D35: 1 | E35: Commissaire Magellan (S1-E34) | F35: Lucie Mauricourt | G35: PER | H35: avait entrepris de mener deux prodiges de la glace , lucie mauricourt et lorena bardin , jusqu ' aux . . . | I35: casEN_spaCy_Stanza | J35: grfpersPrenomNom | K35: grftagPrenom | L35: grftagNomFamille | M35: 8
A36: PER | B36: 1 | C36: 1 | D36: 1 | E36: Commissaire Magellan (S1-E34) | F36: Lorena Bardin | G36: PER | H36: mener deux prodiges de la glace , lucie mauricourt et lorena bardin , jusqu ' aux . . . marches du podium | I36: casEN_spaCy_Stanza | J36: grfpersPrenomNom | K36: grftagPrenom | L36: grftagNomFamille | M36: 8
A37: PER | B37: 1 | C37: 1 | D37: 1 | E37: Commissaire Magellan (S1-E34) | F37: Magellan | G37: PER | H37: le commissaire magellan et la lieutenante berrayah mènent des investigations sur l ' | I37: casEN_spaCy_Stanza | J37: grfpersContextePersonne | K37: grftagNomFamille | M37: 8
A38: PER | B38: 1 | C38: 1 | D38: 1 | E38: Commissaire Magellan (S1-E34) | F38: Magellan | G38: PER | H38: le commissaire magellan et la lieutenante berrayah mènent des investigations sur l ' | I38: casEN_Stanza | J38: grfpersGenerique | M38: 8
E39: Commissaire Magellan (S1-E34) | F39: Berrayah | G39: MISC | H39: commissaire Magellan et la lieutenante Berrayah mènent des investigations sur l'assassi | I39: spaCy | M39: 8
A40: LOC | B40: 1 | C40: 1 | D40: 1 | E40: Einstein : équations criminelles (S3-E1) | F40: Bochum | G40: LOC | H40: poignardé lors d ' une fête , les enquêteurs de bochum sont sur le qui - vive : le meurtrier se | I40: casEN_spaCy_Stanza | J40: grfgeogPlaceDico | M40: 9
A41: PER | B41: 1 | C41: 1 | D41: 1 | E41: Einstein : équations criminelles (S3-E1) | F41: Albert Einstein | G41: PER | H41: aurait hérité des aptitudes mentales de son aïeul supposé : albert einstein . arrêté pour consommation de stupéfiants , felix passe , | I41: casEN_spaCy_Stanza | J41: grfpersPrenomNom | K41: grftagPrenom | L41: grftagNomFamille | M41: 9
E42: Einstein : équations criminelles (S3-E1) | F42: police | G42: ORG | H42: passe , contre son gré , un accord avec la police afin d ' éviter la prison : il va devoir | I42: casEN | J42: grforgPolice | M42: 9
A43: PER | B43: 1 | C43: 1 | D43: 1 | E43: Einstein : équations criminelles (S3-E1) | F43: Felix | G43: PER | H43: brillant physicien , felix winterberg aurait hérité des aptitudes mentales de son aïeul supposé | I43: casEN_spaCy_Stanza | J43: grfpersGenerique | M43: 9
A44: PER | B44: 1 | C44: 1 | D44: 1 | E44: Einstein : équations criminelles (S3-E1) | F44: Felix Winterberg | G44: PER | H44: brillant physicien , felix winterberg aurait hérité des aptitudes mentales de son aïeul supposé : | I44: casEN_spaCy_Stanza | J44: grfpersPrenomNom | K44: grftagPrenom | L44: grftagNomFamille | M44: 9
E45: Einstein : équations criminelles (S3-E1) | F45: Arrêté | G45: LOC | H45: aptitudes mentales de son aïeul supposé : albert einstein . arrêté pour consommation de stupéfiants , felix passe , contre son | I45: Stanza | M45: 9
A46: PER | B46: 1 | C46: 1 | D46: 1 | E46: Einstein : équations criminelles (S3-E1) | F46: Elena Lange | G46: PER | H46: éviter la prison : il va devoir aider la commissaire elena lange à résoudre . . . des affaires criminelles épineuses . | I46: casEN_spaCy_Stanza | J46: grfpersPrenomNom | K46: grftagPrenom | L46: grftagNomFamille | M46: 9
A47: PER | B47: 1 | C47: 1 | D47: 1 | E47: Chicago Fire (S2-E11) | F47: Casey | G47: PER | H47: la situation ne tarde pas à dégénérer. Casey a toujours de gros problèmes de mémoire | I47: spaCy_Stanza | M47: 10
E48: Chicago Fire (S2-E11) | F48: Dawson | G48: PER | H48: es de mémoire mais refuse d'en parler à Dawson. | I48: spaCy_Stanza | M48: 10
E49: Chicago Police Department (S2-E10) | F49: Burgess | G49: PER | H49: sont à déplorer . toutes étaient des avocats brillants . burgess est à la fois inquiète et excitée car c ' | I49: Stanza | M49: 11
A50: PER | B50: 1 | C50: 1 | D50: 1 | E50: Chicago Police Department (S2-E10) | F50: Erin | G50: PER | H50: tente de le faire parler . de son côté , erin a du mal à reprendre le dessus et doit faire | I50: casEN_spaCy_Stanza | J50: grfpersGenerique | M50: 11
A51: PER | B51: 0 | C51: 1 | D51: PER | E51: Chicago Police Department (S2-E10) | F51: Burgess | G51: LOC | H51: . Toutes étaient des avocats brillants. Burgess est à la fois inquiète et excitée car c | I51: spaCy | M51: 11
E52: Chicago Police Department (S2-E10) | F52: équipe | G52: ORG | H52: l ' équipe est appelée dans un club de sport où des coups | I52: casEN | J52: grforgProximite | M52: 11
A53: PER | B53: 1 | C53: 1 | D53: 1 | E53: Chicago Police Department (S2-E10) | F53: Voight | G53: PER | H53: e affaire sur laquelle elle intervient. Voight parvient à neutraliser l'un... des malf | I53: spaCy_Stanza | M53: 11
A54: PER | B54: 0 | C54: 1 | D54: PER | E54: Family Law (S1-E1) | F54: Abby | G54: MISC | H54: eu. Cela met en lumière la dépendance d'Abby, qui continue de nier ce fait. C'est un | I54: spaCy | M54: 12
E55: Family Law (S1-E1) | F55: Abby | G55: PER | H55: jeu . cela met en lumière la dépendance d ' abby , qui continue de nier ce fait . c ' | I55: casEN_Stanza_priority | J55: grfpersGenerique | M55: 12
A56: PER | B56: 1 | C56: 1 | D56: 1 | E56: Family Law (S1-E1) | F56: Daniel | G56: PER | H56: daniel et abigail défendent une mère qui risque de perdre la | I56: casEN_Stanza | J56: grfpersGenerique | M56: 12
A57: PER | B57: 1 | C57: 1 | D57: 1 | E57: Family Law (S1-E1) | F57: Abigail | G57: PER | H57: daniel et abigail défendent une mère qui risque de perdre la garde de | I57: casEN_Stanza | J57: grfpersGenerique | M57: 12
E58: Family Law (S1-E1) | F58: Daniel et Abigail | G58: PER | H58: Daniel et Abigail défendent une mère qui risque de perdre | I58: spaCy | M58: 12
A59: PER | B59: 1 | C59: 1 | D59: 1 | E59: Family Law (S1-E1) | F59: Daniel | G59: PER | H59: daniel et abigail défendent une mère qui risque de perdre la | I59: casEN_spaCy_Stanza | J59: grfpersGenerique | M59: 12
A60: PER | B60: 0 | C60: 1 | D60: PER | E60: Family Law (S1-E1) | F60: Danielle | G60: LOC | H60: e prix. Daniel décide de se marier avec Danielle et Lucy exprime... son avis à ce sujet. | I60: spaCy | M60: 12
E61: Family Law (S1-E1) | F61: Danielle | G61: PER | H61: payer le prix . daniel décide de se marier avec danielle et lucy exprime . . . son avis à ce | I61: Stanza | M61: 12
A62: PER | B62: 0 | C62: 1 | D62: PER | E62: Family Law (S1-E1) | F62: Lucy | G62: LOC | H62: el décide de se marier avec Danielle et Lucy exprime... son avis à ce sujet. | I62: spaCy | M62: 12
E63: Family Law (S1-E1) | F63: Lucy | G63: PER | H63: prix . daniel décide de se marier avec danielle et lucy exprime . . . son avis à ce sujet . | I63: casEN_Stanza_priority | J63: grfpersGenerique | M63: 12
A64: PER | B64: 1 | C64: 1 | D64: 1 | E64: Commissaire Magellan (S1-E34) | F64: Magellan | G64: PER | H64: ' il s ' apprêtait à dévoiler ? le commissaire magellan et le lieutenant selma berrayah vont devoir apprendre à lire | I64: casEN_Stanza | J64: grfpersContextePersonne | K64: grftagNomFamille | M64: 13
A65: PER | B65: 1 | C65: 1 | D65: 1 | E65: Commissaire Magellan (S1-E34) | F65: Selma Berrayah | G65: PER | H65: apprêtait à dévoiler ? le commissaire magellan et le lieutenant selma berrayah vont devoir apprendre à lire entre les lignes du roman | I65: casEN_spaCy_Stanza | J65: grfpersPrenomNom | K65: grftagPrenom | L65: grftagNomFamille | M65: 13
A66: LOC | B66: 1 | C66: 1 | D66: 1 | E66: Commissaire Magellan (S1-E34) | F66: Saignac | G66: LOC | H66: Adrien Beauval est de retour à Saignac pour la signature de son dernier roman | I66: spaCy_Stanza | M66: 13
E67: Commissaire Magellan (S1-E34) | F67: commissaire Magellan | G67: PER | H67: me et qu'il s'apprêtait à dévoiler ? Le commissaire Magellan et le lieutenant Selma Berrayah vont de | I67: spaCy | M67: 13
A68: PER | B68: 1 | C68: 1 | D68: 1 | E68: Commissaire Magellan (S1-E34) | F68: Adrien Beauval | G68: PER | H68: adrien beauval est de retour à saignac pour la signature de son | I68: casEN_spaCy_Stanza | J68: grfpersPrenomNom | K68: grftagPrenom | L68: grftagNomFamille | M68: 13
E69: Einstein : équations criminelles (S3-E1) | F69: université | G69: ORG | H69: d ' avoir fait chanter des hommes de l ' université faisant secrètement appel à des escort girls , pour leur | I69: casEN | J69: grforgProximite | M69: 14
A70: PER | B70: 0 | C70: 1 | D70: PER | E70: Family Law (S1-E1) | F70: Abigail | G70: LOC | H70: Abigail et Daniel représentent un adolescent ga | I70: spaCy | M70: 15
E71: Family Law (S1-E1) | F71: Abigail | G71: PER | H71: abigail et daniel représentent un adolescent gai , fier de son | I71: casEN_Stanza_priority | J71: grfpersGenerique | M71: 15
E72: Family Law (S1-E1) | F72: Abigail | G72: MISC | H72: abigail et daniel représentent un adolescent gai , fier de son | I72: Stanza | M72: 15
A73: PER | B73: 0 | C73: 1 | D73: PER | E73: Family Law (S1-E1) | F73: Abigail | G73: LOC | H73: té, Harry donne une... seconde chance à Abigail. | I73: spaCy | M73: 15
E74: Family Law (S1-E1) | F74: Abigail | G74: PER | H74: abigail et daniel représentent un adolescent gai , fier de son | I74: casEN | J74: grfpersGenerique | M74: 15
A75: PER | B75: 1 | C75: 1 | D75: 1 | E75: Family Law (S1-E1) | F75: Daniel | G75: PER | H75: abigail et daniel représentent un adolescent gai , fier de son identité sexuelle | I75: casEN_spaCy_Stanza | J75: grfpersGenerique | M75: 15
A76: PER | B76: 1 | C76: 1 | D76: 1 | E76: Family Law (S1-E1) | F76: Harry | G76: PER | H76: lorsque le jeune homme disparaît . de son côté , harry donne une . . . seconde chance à abigail . | I76: casEN_spaCy_Stanza | J76: grfpersGenerique | M76: 15
A77: PER | B77: 1 | C77: 1 | D77: 1 | E77: Chicago Fire (S1-E12) | F77: Brent Seabrook | G77: PER | H77: l ' académie . deux joueurs professionnels de hockey , brent seabrook et duncan keith , se confient à leslie shay . | I77: casEN_Stanza_priority | J77: grfpersPrenomNom | K77: grftagPrenom | L77: grftagNomFamille | M77: 16
E78: Chicago Fire (S1-E12) | F78: Brent Seabrook | G78: ORG | H78: Deux joueurs professionnels de hockey, Brent Seabrook et Duncan Keith, se confient à Leslie S | I78: spaCy | M78: 16
A79: PER | B79: 1 | C79: 1 | D79: 1 | E79: Chicago Fire (S1-E12) | F79: Duncan Keith | G79: PER | H79: . deux joueurs professionnels de hockey , brent seabrook et duncan keith , se confient à leslie shay . . . | I79: casEN_spaCy_Stanza | J79: grfpersPrenomNom | K79: grftagPrenom | L79: grftagNomFamille | M79: 16
A80: PER | B80: 1 | C80: 1 | D80: 1 | E80: Chicago Fire (S1-E12) | F80: Dawson | G80: PER | H80: re d'un traumatisme crânien.... Quant à Dawson, il a les plus grandes difficultés à pa | I80: spaCy_Stanza | M80: 16
A81: PER | B81: 1 | C81: 1 | D81: 1 | E81: Chicago Fire (S1-E12) | F81: Casey | G81: PER | H81: à se venger de Kelly. Pendant ce temps, Casey consulte un médecin au sujet de ses pro | I81: spaCy_Stanza | M81: 16
A82: PER | B82: 1 | C82: 1 | D82: 1 | E82: Chicago Fire (S1-E12) | F82: Vince Keeler | G82: PER | H82: sœur katie qui a été enlevée . la police soupçonne vince keeler , un voyou qui cherche à se venger de kelly | I82: casEN_spaCy_Stanza | J82: grfpersPrenomNom | K82: grftagPrenom | L82: grftagNomFamille | M82: 16
A83: PER | B83: 1 | C83: 1 | D83: 1 | E83: Chicago Fire (S1-E12) | F83: Leslie Shay | G83: PER | H83: , brent seabrook et duncan keith , se confient à leslie shay . . . | I83: casEN_spaCy_Stanza | J83: grfpersPrenomNom | K83: grftagPrenom | L83: grftagNomFamille | M83: 16
A84: PER | B84: 1 | C84: 1 | D84: 1 | E84: Chicago Fire (S1-E12) | F84: Kelly | G84: PER | H84: kelly est fou d ' inquiétude pour sa sœur katie qui | I84: casEN_spaCy_Stanza | J84: grfpersGenerique | M84: 16
A85: PER | B85: 1 | C85: 1 | D85: 1 | E85: Chicago Fire (S1-E12) | F85: Kelly | G85: PER | H85: kelly est fou d ' inquiétude pour sa sœur katie qui | I85: casEN_spaCy_Stanza | J85: grfpersGenerique | M85: 16
A86: PER | B86: 1 | C86: 1 | D86: 1 | E86: Chicago Fire (S1-E12) | F86: Katie | G86: PER | H86: kelly est fou d ' inquiétude pour sa sœur katie qui a été enlevée . la police soupçonne vince keeler | I86: casEN_spaCy_Stanza | J86: grfpersContextePersonne | K86: grftagNomFamille | M86: 16
E87: Chicago Fire (S1-E12) | F87: académie | G87: ORG | H87: à oxygène en vue de son entrée à l ' académie . deux joueurs professionnels de hockey , brent seabrook et | I87: casEN | J87: grforgProximite | M87: 16
E88: Chicago Fire (S1-E12) | F88: police | G88: ORG | H88: pour sa sœur katie qui a été enlevée . la police soupçonne vince keeler , un voyou qui cherche à se | I88: casEN | J88: grforgPolice | M88: 16
A89: PER | B89: 0 | C89: 1 | D89: PER | E89: Chicago Fire (S2-E11) | F89: Severide | G89: ORG | H89: stagiaire aux côtés de l ' équipe de casey . severide enrage à l ' idée que keeler puisse être libéré | I89: casEN | J89: grforgGenerique | M89: 17
E90: Chicago Fire (S2-E11) | F90: équipe Casey | G90: ORG | H90: En attendant de repasser ses examens, Dawson est de retour à la brigade en tant qu'ambulancière. Jones, quant à elle, s'apprête à faire ses premiers pas de stagiaire aux côtés de l'équipe de Casey. Severide enrage à l'idée que Keeler puisse être libéré après ce qu'il a fait subir à sa... sœur. Il compte bien prendre les choses en main. En proie à de nouveaux problèmes conjugaux, Benny, le père de Kelly, refait surface. Il propose son aide à Severide, mais celui-ci ne veut rien entendre. Entre temps, l'équipe doit intervenir pour un incendie dans un immeuble de dix-huit étages en centre-ville... | I90: casEN | J90: grforgSeule | M90: 17
E91: Chicago Fire (S2-E11) | F91: brigade | G91: ORG | H91: repasser ses examens , dawson est de retour à la brigade en tant qu ' ambulancière . jones , quant à | I91: casEN | J91: grforgPolice | M91: 17
E92: Chicago Fire (S2-E11) | F92: Severide | G92: LOC | H92: , refait surface. Il propose son aide à Severide, mais celui-ci ne veut rien entendre. E | I92: spaCy | M92: 17
E93: Chicago Fire (S2-E11) | F93: Casey | G93: LOC | H93: s de stagiaire aux côtés de l'équipe de Casey. Severide enrage à l'idée que Keeler pu | I93: spaCy | M93: 17
E94: Chicago Fire (S2-E11) | F94: Casey | G94: PER | H94: pas de stagiaire aux côtés de l ' équipe de casey . severide enrage à l ' idée que keeler puisse | I94: Stanza | M94: 17
A95: PER | B95: 1 | C95: 1 | D95: 1 | E95: Chicago Fire (S2-E11) | F95: Benny | G95: PER | H95: roie à de nouveaux problèmes conjugaux, Benny, le père de Kelly, refait surface. Il p | I95: spaCy_Stanza | M95: 17
A96: PER | B96: 1 | C96: 1 | D96: 1 | E96: Chicago Fire (S2-E11) | F96: Kelly | G96: PER | H96: de nouveaux problèmes conjugaux , benny , le père de kelly , refait surface . il propose son aide à severide | I96: casEN_spaCy_Stanza | J96: grfpersGenerique | M96: 17
A97: PER | B97: 1 | C97: 1 | D97: 1 | E97: Chicago Fire (S2-E11) | F97: Keeler | G97: PER | H97: de casey . severide enrage à l ' idée que keeler puisse être libéré après ce qu ' il a fait | I97: casEN_spaCy_Stanza | J97: grfpersGenerique | M97: 17
A98: PER | B98: 1 | C98: 1 | D98: 1 | E98: Chicago Fire (S2-E11) | F98: Jones | G98: PER | H98: retour à la brigade en tant qu ' ambulancière . jones , quant à elle , s ' apprête à faire | I98: casEN_spaCy_Stanza | J98: grfpersGenerique | M98: 17
A99: PER | B99: 1 | C99: 1 | D99: 1 | E99: Chicago Fire (S2-E11) | F99: Dawson | G99: PER | H99: En attendant de repasser ses examens, Dawson est de retour à la brigade en tant qu'a | I99: spaCy_Stanza | M99: 17
A100: PER | B100: 0 | C100: 1 | D100: PER | E100: Chicago Fire (S2-E11) | F100: Severide | G100: ORG | H100: stagiaire aux côtés de l ' équipe de casey . severide enrage à l ' idée que keeler puisse être libéré | I100: casEN | J100: grfroleName | M100: 17
...

Sheet Analyses
A1: {=_xlfn.UNIQUE(_xlfn._xlws.FILTER(Results!I:I, Results!I:I <>""))} -> method | B1: Total Founds | C1: Corrected | D1: Correct | E1: Accuracy | F1: Time | G1: Choose
A2: spaCy | B2: =COUNTIF(Results!I:I, A2) -> 9424 | C2: =COUNTIFS(Results!I:I, A2, Results!B:B, 1) + COUNTIFS(Results!I:I, A2, Results!B:B, 0) -> 4970 | D2: =COUNTIFS(Results!I:I, A2,Results!B:B, 1) -> 711 | E2: =D2/C2 -> 0.14305835 | F2: 70.65s | G2: 0 | K2: Total | L2: Accuracy | M2: Data Gains | N2: Accuracy Loss
A3: spaCy_Stanza | B3: =COUNTIF(Results!I:I, A3) -> 5397 | C3: =COUNTIFS(Results!I:I, A3, Results!B:B, 1) + COUNTIFS(Results!I:I, A3, Results!B:B, 0) -> 4441 | D3: =COUNTIFS(Results!I:I, A3,Results!B:B, 1) -> 3111 | E3: =D3/C3 -> 0.7005179 | G3: 0 | J3: old intersection (spaCy + CasEN) | K3: 5970 | L3: 0.977 | M3: =IFERROR((K3-K3)/K3, 0) -> 0 | N3: =L3-L3 -> 0
A4: casEN_spaCy_Stanza | B4: =COUNTIF(Results!I:I, A4) -> 5345 | C4: =COUNTIFS(Results!I:I, A4, Results!B:B, 1) + COUNTIFS(Results!I:I, A4, Results!B:B, 0) -> 5157 | D4: =COUNTIFS(Results!I:I, A4,Results!B:B, 1) -> 5116 | E4: =D4/C4 -> 0.99204964 | G4: 1 | J4: spaCy + CasEN + opti + priority | K4: 7990 | L4: 0.95181187 | M4: 0.33835846 | N4: 0.025165797 | O4: (cartesian product)
A5: Stanza | B5: =COUNTIF(Results!I:I, A5) -> 7428 | C5: =COUNTIFS(Results!I:I, A5, Results!B:B, 1) + COUNTIFS(Results!I:I, A5, Results!B:B, 0) -> 1386 | D5: =COUNTIFS(Results!I:I, A5,Results!B:B, 1) -> 1011 | E5: =D5/C5 -> 0.72943723 | F5: 367.36s CPU vs 104.43s GPU (rtx3070 FE) | G5: 0 | J5: spaCy_casEN_Stanza | K5: =B4 -> 5345 | L5: =E4 -> 0.99204964 | M5: =IFERROR((K5-K3)/K3, 0) -> -0.10469012 | N5: =L3-L5 -> -0.015049641
A6: casEN_Stanza_priority | B6: =COUNTIF(Results!I:I, A6) -> 1094 | C6: =COUNTIFS(Results!I:I, A6, Results!B:B, 1) + COUNTIFS(Results!I:I, A6, Results!B:B, 0) -> 645 | D6: =COUNTIFS(Results!I:I, A6,Results!B:B, 1) -> 586 | E6: =D6/C6 -> 0.90852713 | G6: 1
A7: spaCy_Stanza_priority | B7: =COUNTIF(Results!I:I, A7) -> 277 | C7: =COUNTIFS(Results!I:I, A7, Results!B:B, 1) + COUNTIFS(Results!I:I, A7, Results!B:B, 0) -> 219 | D7: =COUNTIFS(Results!I:I, A7,Results!B:B, 1) -> 213 | E7: =D7/C7 -> 0.97260274 | G7: 1
A8: casEN_Stanza | B8: =COUNTIF(Results!I:I, A8) -> 718 | C8: =COUNTIFS(Results!I:I, A8, Results!B:B, 1) + COUNTIFS(Results!I:I, A8, Results!B:B, 0) -> 532 | D8: =COUNTIFS(Results!I:I, A8,Results!B:B, 1) -> 490 | E8: =D8/C8 -> 0.92105263 | G8: 1
A9: casEN | B9: =COUNTIF(Results!I:I, A9) -> 4317 | C9: =COUNTIFS(Results!I:I, A9, Results!B:B, 1) + COUNTIFS(Results!I:I, A9, Results!B:B, 0) -> 938 | D9: =COUNTIFS(Results!I:I, A9,Results!B:B, 1) -> 320 | E9: =D9/C9 -> 0.34115139 | G9: 0
A10: casEN_opti | B10: =COUNTIF(Results!I:I, A10) -> 494 | C10: =COUNTIFS(Results!I:I, A10, Results!B:B, 1) + COUNTIFS(Results!I:I, A10, Results!B:B, 0) -> 270 | D10: =COUNTIFS(Results!I:I, A10,Results!B:B, 1) -> 242 | E10: =D10/C10 -> 0.8962963 | G10: 1 | J10: Total Founds | K10: Corrected | L10: Correct | M10: Accuracy | N10: Data Gains | O10: Accuracy Loss
A11: casEN_spaCy | B11: =COUNTIF(Results!I:I, A11) -> 213 | C11: =COUNTIFS(Results!I:I, A11, Results!B:B, 1) + COUNTIFS(Results!I:I, A11, Results!B:B, 0) -> 197 | D11: =COUNTIFS(Results!I:I, A11,Results!B:B, 1) -> 140 | E11: =D11/C11 -> 0.7106599 | G11: 0 | I11: VS OLD inter | J11: =SUMIF(G2:G13, 1, B2:B13) -> 8184 | K11: =SUMIF(G2:G13, 1, C2:C13) -> 7058 | L11: =SUMIF(G2:G13, 1, D2:D13) -> 6854 | M11: =L11/K11 -> 0.97109663 | N11: =(J11-K3)/K3 -> 0.37085427 | O11: =L3-M11 -> 0.0059033721
A12: casEN_spaCy_Stanza_priority | B12: =COUNTIF(Results!I:I, A12) -> 102 | C12: =COUNTIFS(Results!I:I, A12, Results!B:B, 1) + COUNTIFS(Results!I:I, A12, Results!B:B, 0) -> 91 | D12: =COUNTIFS(Results!I:I, A12,Results!B:B, 1) -> 91 | E12: =D12/C12 -> 1 | G12: 1 | I12: VS spaCy casEN opti priority | J12: =SUMIF(G2:G13, 1, B2:B13) -> 8184 | K12: =SUMIF(G2:G13, 1, C2:C13) -> 7058 | L12: =SUMIF(G3:G14, 1, D3:D14) -> 6854 | M12: =L12/K12 -> 0.97109663 | N12: =(J12-K4)/K4 -> 0.02428035 | O12: =L4-M12 -> -0.019284754
A13: casEN_spaCy_priority | B13: =COUNTIF(Results!I:I, A13) -> 154 | C13: =COUNTIFS(Results!I:I, A13, Results!B:B, 1) + COUNTIFS(Results!I:I, A13, Results!B:B, 0) -> 144 | D13: =COUNTIFS(Results!I:I, A13,Results!B:B, 1) -> 116 | E13: =D13/C13 -> 0.80555556 | G13: 1 | I13: PER | J13: =SUMIF(R22:R33, 1, B22:B33) -> 6661 | K13: =SUMIF(R22:R33, 1, C22:C33) -> 5688 | L13: =SUMIF(R22:R33, 1, D22:D33) -> 5530 | M13: =L13/K13 -> 0.97222222
I14: LOC | J14: =SUMIF(R22:R33, 1, F22:F33) -> 1367 | K14: =SUMIF(R22:R33, 1, G22:G33) -> 1236 | L14: =SUMIF(R22:R33, 1, H22:H33) -> 1218 | M14: =L14/K14 -> 0.98543689
A15: Total CasEN | B15: =B4+B6+B8+B9+B10+B11+B12+B13 -> 12437 | C15: =C4+C6+C8+C9+C10+C11+C12+C13 -> 7974 | D15: =D4+D6+D8+D9+D10+D11+D12+D13 -> 7101 | E15: =D15/C15 -> 0.89051919 | F15: without MISC ! | I15: ORG | J15: =SUMIF(R22:R33, 1, J22:J33) -> 154 | K15: =SUMIF(R22:R33, 1, K22:K33) -> 133 | L15: =SUMIF(R22:R33, 1, L22:L33) -> 106 | M15: =L15/K15 -> 0.79699248
A16: Total Stanza | B16: =B3+B4+B5+B6+B7+B8+B12 -> 20361 | C16: =C3+C4+C5+C6+C7+C8+C12 -> 12471 | D16: =D3+D4+D5+D6+D7+D8+D12 -> 10618 | E16: =D16/C16 -> 0.85141528 | I16: MISC | J16: =SUMIF(R22:R33, 1, N22:N33) -> 2 | K16: =SUMIF(R22:R33, 1, O22:O33) -> 1 | L16: =SUMIF(R22:R33, 1, P22:P33) -> 0 | M16: =L16/K16 -> 0
A17: Total SpaCy | B17: =B2+B3+B4+B7+B11+B12+B13 -> 20912 | C17: =C2+C3+C4+C7+C11+C12+C13 -> 15219 | D17: =D2+D3+D4+D7+D11+D12+D13 -> 9498 | E17: =D17/C17 -> 0.62408831
A21: method | B21: PER | C21: Corrected | D21: Correct | E21: Accuracy | F21: LOC | G21: Corrected | H21: Correct | I21: Accuracy | J21: ORG | K21: Corrected | L21: Correct | M21: Accuracy | N21: MISC | O21: Corrected | P21: Correct | Q21: Accuracy | R21: Choose
A22: spaCy | B22: =COUNTIFS(Results!$I:$I, A22, Results!$G:$G, $B$21) -> 1773 | C22: =COUNTIFS(Results!$I:$I, A22, Results!$G:$G, $B$21, Results!B:B, 1) + COUNTIFS(Results!$I:$I, A22, Results!$G:$G, $B$21, Results!B:B, 0) -> 948 | D22: =COUNTIFS(Results!$I:$I, A22, Results!$G:$G, $B$21, Results!B:B, 1) -> 449 | E22: =IFERROR(D22/C22, 0) -> 0.47362869 | F22: =COUNTIFS(Results!$I:$I, $A22, Results!$G:$G, $F$21) -> 4095 | G22: =COUNTIFS(Results!$I:$I, $A22, Results!$G:$G, $F$21, Results!B:B, 1) + COUNTIFS(Results!$I:$I, $A22, Results!$G:$G, $F$21, Results!B:B, 0) -> 2344 | H22: =COUNTIFS(Results!$I:$I, $A22, Results!$G:$G, $F$21, Results!B:B, 1) -> 198 | I22: =IFERROR(H22/G22, 0) -> 0.08447099 | J22: =COUNTIFS(Results!$I:$I, $A22,Results!$G:$G, $J$21) -> 654 | K22: =COUNTIFS(Results!$I:$I, $A22,Results!$G:$G, $J$21, Results!B:B, 1) + COUNTIFS(Results!$I:$I, $A22,Results!$G:$G, $J$21, Results!B:B, 0) -> 264 | L22: =COUNTIFS(Results!$I:$I, $A22,Results!$G:$G, $J$21, Results!B:B, 1) -> 49 | M22: =IFERROR(L22/K22, 0) -> 0.18560606 | N22: =COUNTIFS(Results!$I:$I, $A22, Results!$G:$G, $N$21) -> 2902 | O22: =COUNTIFS(Results!$I:$I, $A22, Results!$G:$G, $N$21, Results!B:B, 1) + COUNTIFS(Results!$I:$I, $A22, Results!$G:$G, $N$21, Results!B:B, 0) -> 1414 | P22: =COUNTIFS(Results!$I:$I, $A22, Results!$G:$G, $N$21, Results!B:B, 1) -> 15 | Q22: =IFERROR(P22/O22, 0) -> 0.010608204 | R22: =G2 -> 0
A23: spaCy_Stanza | B23: =COUNTIFS(Results!$I:$I, A23, Results!$G:$G, $B$21) -> 2330 | C23: =COUNTIFS(Results!$I:$I, A23, Results!$G:$G, $B$21, Results!B:B, 1) + COUNTIFS(Results!$I:$I, A23, Results!$G:$G, $B$21, Results!B:B, 0) -> 1947 | D23: =COUNTIFS(Results!$I:$I, A23, Results!$G:$G, $B$21, Results!B:B, 1) -> 1875 | E23: =IFERROR(D23/C23, 0) -> 0.96302003 | F23: =COUNTIFS(Results!$I:$I, $A23, Results!$G:$G, $F$21) -> 1277 | G23: =COUNTIFS(Results!$I:$I, $A23, Results!$G:$G, $F$21, Results!B:B, 1) + COUNTIFS(Results!$I:$I, $A23, Results!$G:$G, $F$21, Results!B:B, 0) -> 1131 | H23: =COUNTIFS(Results!$I:$I, $A23, Results!$G:$G, $F$21, Results!B:B, 1) -> 957 | I23: =IFERROR(H23/G23, 0) -> 0.84615385 | J23: =COUNTIFS(Results!$I:$I, $A23,Results!$G:$G, $J$21) -> 257 | K23: =COUNTIFS(Results!$I:$I, $A23,Results!$G:$G, $J$21, Results!B:B, 1) + COUNTIFS(Results!$I:$I, $A23,Results!$G:$G, $J$21, Results!B:B, 0) -> 194 | L23: =COUNTIFS(Results!$I:$I, $A23,Results!$G:$G, $J$21, Results!B:B, 1) -> 162 | M23: =IFERROR(L23/K23, 0) -> 0.83505155 | N23: =COUNTIFS(Results!$I:$I, $A23, Results!$G:$G, $N$21) -> 1533 | O23: =COUNTIFS(Results!$I:$I, $A23, Results!$G:$G, $N$21, Results!B:B, 1) + COUNTIFS(Results!$I:$I, $A23, Results!$G:$G, $N$21, Results!B:B, 0) -> 1169 | P23: =COUNTIFS(Results!$I:$I, $A23, Results!$G:$G, $N$21, Results!B:B, 1) -> 117 | Q23: =IFERROR(P23/O23, 0) -> 0.10008554 | R23: =G3 -> 0
A24: casEN_spaCy_Stanza | B24: =COUNTIFS(Results!$I:$I, A24, Results!$G:$G, $B$21) -> 4367 | C24: =COUNTIFS(Results!$I:$I, A24, Results!$G:$G, $B$21, Results!B:B, 1) + COUNTIFS(Results!$I:$I, A24, Results!$G:$G, $B$21, Results!B:B, 0) -> 4182 | D24: =COUNTIFS(Results!$I:$I, A24, Results!$G:$G, $B$21, Results!B:B, 1) -> 4148 | E24: =IFERROR(D24/C24, 0) -> 0.99186992 | F24: =COUNTIFS(Results!$I:$I, $A24, Results!$G:$G, $F$21) -> 906 | G24: =COUNTIFS(Results!$I:$I, $A24, Results!$G:$G, $F$21, Results!B:B, 1) + COUNTIFS(Results!$I:$I, $A24, Results!$G:$G, $F$21, Results!B:B, 0) -> 904 | H24: =COUNTIFS(Results!$I:$I, $A24, Results!$G:$G, $F$21, Results!B:B, 1) -> 902 | I24: =IFERROR(H24/G24, 0) -> 0.99778761 | J24: =COUNTIFS(Results!$I:$I, $A24,Results!$G:$G, $J$21) -> 72 | K24: =COUNTIFS(Results!$I:$I, $A24,Results!$G:$G, $J$21, Results!B:B, 1) + COUNTIFS(Results!$I:$I, $A24,Results!$G:$G, $J$21, Results!B:B, 0) -> 71 | L24: =COUNTIFS(Results!$I:$I, $A24,Results!$G:$G, $J$21, Results!B:B, 1) -> 66 | M24: =IFERROR(L24/K24, 0) -> 0.92957746 | N24: =COUNTIFS(Results!$I:$I, $A24, Results!$G:$G, $N$21) -> 0 | O24: =COUNTIFS(Results!$I:$I, $A24, Results!$G:$G, $N$21, Results!B:B, 1) + COUNTIFS(Results!$I:$I, $A24, Results!$G:$G, $N$21, Results!B:B, 0) -> 0 | P24: =COUNTIFS(Results!$I:$I, $A24, Results!$G:$G, $N$21, Results!B:B, 1) -> 0 | Q24: =IFERROR(P24/O24, 0) -> 0 | R24: =G4 -> 1
A25: Stanza | B25: =COUNTIFS(Results!$I:$I, A25, Results!$G:$G, $B$21) -> 3036 | C25: =COUNTIFS(Results!$I:$I, A25, Results!$G:$G, $B$21, Results!B:B, 1) + COUNTIFS(Results!$I:$I, A25, Results!$G:$G, $B$21, Results!B:B, 0) -> 749 | D25: =COUNTIFS(Results!$I:$I, A25, Results!$G:$G, $B$21, Results!B:B, 1) -> 731 | E25: =IFERROR(D25/C25, 0) -> 0.97596796 | F25: =COUNTIFS(Results!$I:$I, $A25, Results!$G:$G, $F$21) -> 833 | G25: =COUNTIFS(Results!$I:$I, $A25, Results!$G:$G, $F$21, Results!B:B, 1) + COUNTIFS(Results!$I:$I, $A25, Results!$G:$G, $F$21, Results!B:B, 0) -> 262 | H25: =COUNTIFS(Results!$I:$I, $A25, Results!$G:$G, $F$21, Results!B:B, 1) -> 219 | I25: =IFERROR(H25/G25, 0) -> 0.83587786 | J25: =COUNTIFS(Results!$I:$I, $A25,Results!$G:$G, $J$21) -> 920 | K25: =COUNTIFS(Results!$I:$I, $A25,Results!$G:$G, $J$21, Results!B:B, 1) + COUNTIFS(Results!$I:$I, $A25,Results!$G:$G, $J$21, Results!B:B, 0) -> 91 | L25: =COUNTIFS(Results!$I:$I, $A25,Results!$G:$G, $J$21, Results!B:B, 1) -> 52 | M25: =IFERROR(L25/K25, 0) -> 0.57142857 | N25: =COUNTIFS(Results!$I:$I, $A25, Results!$G:$G, $N$21) -> 2639 | O25: =COUNTIFS(Results!$I:$I, $A25, Results!$G:$G, $N$21, Results!B:B, 1) + COUNTIFS(Results!$I:$I, $A25, Results!$G:$G, $N$21, Results!B:B, 0) -> 284 | P25: =COUNTIFS(Results!$I:$I, $A25, Results!$G:$G, $N$21, Results!B:B, 1) -> 9 | Q25: =IFERROR(P25/O25, 0) -> 0.031690141 | R25: =G5 -> 0
A26: casEN_Stanza_priority | B26: =COUNTIFS(Results!$I:$I, A26, Results!$G:$G, $B$21) -> 1094 | C26: =COUNTIFS(Results!$I:$I, A26, Results!$G:$G, $B$21, Results!B:B, 1) + COUNTIFS(Results!$I:$I, A26, Results!$G:$G, $B$21, Results!B:B, 0) -> 645 | D26: =COUNTIFS(Results!$I:$I, A26, Results!$G:$G, $B$21, Results!B:B, 1) -> 586 | E26: =IFERROR(D26/C26, 0) -> 0.90852713 | F26: =COUNTIFS(Results!$I:$I, $A26, Results!$G:$G, $F$21) -> 0 | G26: =COUNTIFS(Results!$I:$I, $A26, Results!$G:$G, $F$21, Results!B:B, 1) + COUNTIFS(Results!$I:$I, $A26, Results!$G:$G, $F$21, Results!B:B, 0) -> 0 | H26: =COUNTIFS(Results!$I:$I, $A26, Results!$G:$G, $F$21, Results!B:B, 1) -> 0 | I26: =IFERROR(H26/G26, 0) -> 0 | J26: =COUNTIFS(Results!$I:$I, $A26,Results!$G:$G, $J$21) -> 0 | K26: =COUNTIFS(Results!$I:$I, $A26,Results!$G:$G, $J$21, Results!B:B, 1) + COUNTIFS(Results!$I:$I, $A26,Results!$G:$G, $J$21, Results!B:B, 0) -> 0 | L26: =COUNTIFS(Results!$I:$I, $A26,Results!$G:$G, $J$21, Results!B:B, 1) -> 0 | M26: =IFERROR(L26/K26, 0) -> 0 | N26: =COUNTIFS(Results!$I:$I, $A26, Results!$G:$G, $N$21) -> 0 | O26: =COUNTIFS(Results!$I:$I, $A26, Results!$G:$G, $N$21, Results!B:B, 1) + COUNTIFS(Results!$I:$I, $A26, Results!$G:$G, $N$21, Results!B:B, 0) -> 0 | P26: =COUNTIFS(Results!$I:$I, $A26, Results!$G:$G, $N$21, Results!B:B, 1) -> 0 | Q26: =IFERROR(P26/O26, 0) -> 0 | R26: =G6 -> 1
A27: spaCy_Stanza_priority | B27: =COUNTIFS(Results!$I:$I, A27, Results!$G:$G, $B$21) -> 268 | C27: =COUNTIFS(Results!$I:$I, A27, Results!$G:$G, $B$21, Results!B:B, 1) + COUNTIFS(Results!$I:$I, A27, Results!$G:$G, $B$21, Results!B:B, 0) -> 218 | D27: =COUNTIFS(Results!$I:$I, A27, Results!$G:$G, $B$21, Results!B:B, 1) -> 213 | E27: =IFERROR(D27/C27, 0) -> 0.97706422 | F27: =COUNTIFS(Results!$I:$I, $A27, Results!$G:$G, $F$21) -> 7 | G27: =COUNTIFS(Results!$I:$I, $A27, Results!$G:$G, $F$21, Results!B:B, 1) + COUNTIFS(Results!$I:$I, $A27, Results!$G:$G, $F$21, Results!B:B, 0) -> 0 | H27: =COUNTIFS(Results!$I:$I, $A27, Results!$G:$G, $F$21, Results!B:B, 1) -> 0 | I27: =IFERROR(H27/G27, 0) -> 0 | J27: =COUNTIFS(Results!$I:$I, $A27,Results!$G:$G, $J$21) -> 0 | K27: =COUNTIFS(Results!$I:$I, $A27,Results!$G:$G, $J$21, Results!B:B, 1) + COUNTIFS(Results!$I:$I, $A27,Results!$G:$G, $J$21, Results!B:B, 0) -> 0 | L27: =COUNTIFS(Results!$I:$I, $A27,Results!$G:$G, $J$21, Results!B:B, 1) -> 0 | M27: =IFERROR(L27/K27, 0) -> 0 | N27: =COUNTIFS(Results!$I:$I, $A27, Results!$G:$G, $N$21) -> 2 | O27: =COUNTIFS(Results!$I:$I, $A27, Results!$G:$G, $N$21, Results!B:B, 1) + COUNTIFS(Results!$I:$I, $A27, Results!$G:$G, $N$21, Results!B:B, 0) -> 1 | P27: =COUNTIFS(Results!$I:$I, $A27, Results!$G:$G, $N$21, Results!B:B, 1) -> 0 | Q27: =IFERROR(P27/O27, 0) -> 0 | R27: =G7 -> 1
A28: casEN_Stanza | B28: =COUNTIFS(Results!$I:$I, A28, Results!$G:$G, $B$21) -> 526 | C28: =COUNTIFS(Results!$I:$I, A28, Results!$G:$G, $B$21, Results!B:B, 1) + COUNTIFS(Results!$I:$I, A28, Results!$G:$G, $B$21, Results!B:B, 0) -> 348 | D28: =COUNTIFS(Results!$I:$I, A28, Results!$G:$G, $B$21, Results!B:B, 1) -> 328 | E28: =IFERROR(D28/C28, 0) -> 0.94252874 | F28: =COUNTIFS(Results!$I:$I, $A28, Results!$G:$G, $F$21) -> 139 | G28: =COUNTIFS(Results!$I:$I, $A28, Results!$G:$G, $F$21, Results!B:B, 1) + COUNTIFS(Results!$I:$I, $A28, Results!$G:$G, $F$21, Results!B:B, 0) -> 135 | H28: =COUNTIFS(Results!$I:$I, $A28, Results!$G:$G, $F$21, Results!B:B, 1) -> 135 | I28: =IFERROR(H28/G28, 0) -> 1 | J28: =COUNTIFS(Results!$I:$I, $A28,Results!$G:$G, $J$21) -> 53 | K28: =COUNTIFS(Results!$I:$I, $A28,Results!$G:$G, $J$21, Results!B:B, 1) + COUNTIFS(Results!$I:$I, $A28,Results!$G:$G, $J$21, Results!B:B, 0) -> 49 | L28: =COUNTIFS(Results!$I:$I, $A28,Results!$G:$G, $J$21, Results!B:B, 1) -> 27 | M28: =IFERROR(L28/K28, 0) -> 0.55102041 | N28: =COUNTIFS(Results!$I:$I, $A28, Results!$G:$G, $N$21) -> 0 | O28: =COUNTIFS(Results!$I:$I, $A28, Results!$G:$G, $N$21, Results!B:B, 1) + COUNTIFS(Results!$I:$I, $A28, Results!$G:$G, $N$21, Results!B:B, 0) -> 0 | P28: =COUNTIFS(Results!$I:$I, $A28, Results!$G:$G, $N$21, Results!B:B, 1) -> 0 | Q28: =IFERROR(P28/O28, 0) -> 0 | R28: =G8 -> 1
A29: casEN | B29: =COUNTIFS(Results!$I:$I, A29, Results!$G:$G, $B$21) -> 1816 | C29: =COUNTIFS(Results!$I:$I, A29, Results!$G:$G, $B$21, Results!B:B, 1) + COUNTIFS(Results!$I:$I, A29, Results!$G:$G, $B$21, Results!B:B, 0) -> 457 | D29: =COUNTIFS(Results!$I:$I, A29, Results!$G:$G, $B$21, Results!B:B, 1) -> 218 | E29: =IFERROR(D29/C29, 0) -> 0.47702407 | F29: =COUNTIFS(Results!$I:$I, $A29, Results!$G:$G, $F$21) -> 289 | G29: =COUNTIFS(Results!$I:$I, $A29, Results!$G:$G, $F$21, Results!B:B, 1) + COUNTIFS(Results!$I:$I, $A29, Results!$G:$G, $F$21, Results!B:B, 0) -> 35 | H29: =COUNTIFS(Results!$I:$I, $A29, Results!$G:$G, $F$21, Results!B:B, 1) -> 15 | I29: =IFERROR(H29/G29, 0) -> 0.42857143 | J29: =COUNTIFS(Results!$I:$I, $A29,Results!$G:$G, $J$21) -> 2212 | K29: =COUNTIFS(Results!$I:$I, $A29,Results!$G:$G, $J$21, Results!B:B, 1) + COUNTIFS(Results!$I:$I, $A29,Results!$G:$G, $J$21, Results!B:B, 0) -> 446 | L29: =COUNTIFS(Results!$I:$I, $A29,Results!$G:$G, $J$21, Results!B:B, 1) -> 87 | M29: =IFERROR(L29/K29, 0) -> 0.19506726 | N29: =COUNTIFS(Results!$I:$I, $A29, Results!$G:$G, $N$21) -> 0 | O29: =COUNTIFS(Results!$I:$I, $A29, Results!$G:$G, $N$21, Results!B:B, 1) + COUNTIFS(Results!$I:$I, $A29, Results!$G:$G, $N$21, Results!B:B, 0) -> 0 | P29: =COUNTIFS(Results!$I:$I, $A29, Results!$G:$G, $N$21, Results!B:B, 1) -> 0 | Q29: =IFERROR(P29/O29, 0) -> 0 | R29: =G9 -> 0
A30: casEN_opti | B30: =COUNTIFS(Results!$I:$I, A30, Results!$G:$G, $B$21) -> 150 | C30: =COUNTIFS(Results!$I:$I, A30, Results!$G:$G, $B$21, Results!B:B, 1) + COUNTIFS(Results!$I:$I, A30, Results!$G:$G, $B$21, Results!B:B, 0) -> 60 | D30: =COUNTIFS(Results!$I:$I, A30, Results!$G:$G, $B$21, Results!B:B, 1) -> 48 | E30: =IFERROR(D30/C30, 0) -> 0.8 | F30: =COUNTIFS(Results!$I:$I, $A30, Results!$G:$G, $F$21) -> 315 | G30: =COUNTIFS(Results!$I:$I, $A30, Results!$G:$G, $F$21, Results!B:B, 1) + COUNTIFS(Results!$I:$I, $A30, Results!$G:$G, $F$21, Results!B:B, 0) -> 197 | H30: =COUNTIFS(Results!$I:$I, $A30, Results!$G:$G, $F$21, Results!B:B, 1) -> 181 | I30: =IFERROR(H30/G30, 0) -> 0.91878173 | J30: =COUNTIFS(Results!$I:$I, $A30,Results!$G:$G, $J$21) -> 29 | K30: =COUNTIFS(Results!$I:$I, $A30,Results!$G:$G, $J$21, Results!B:B, 1) + COUNTIFS(Results!$I:$I, $A30,Results!$G:$G, $J$21, Results!B:B, 0) -> 13 | L30: =COUNTIFS(Results!$I:$I, $A30,Results!$G:$G, $J$21, Results!B:B, 1) -> 13 | M30: =IFERROR(L30/K30, 0) -> 1 | N30: =COUNTIFS(Results!$I:$I, $A30, Results!$G:$G, $N$21) -> 0 | O30: =COUNTIFS(Results!$I:$I, $A30, Results!$G:$G, $N$21, Results!B:B, 1) + COUNTIFS(Results!$I:$I, $A30, Results!$G:$G, $N$21, Results!B:B, 0) -> 0 | P30: =COUNTIFS(Results!$I:$I, $A30, Results!$G:$G, $N$21, Results!B:B, 1) -> 0 | Q30: =IFERROR(P30/O30, 0) -> 0 | R30: =G10 -> 1
A31: casEN_spaCy | B31: =COUNTIFS(Results!$I:$I, A31, Results!$G:$G, $B$21) -> 116 | C31: =COUNTIFS(Results!$I:$I, A31, Results!$G:$G, $B$21, Results!B:B, 1) + COUNTIFS(Results!$I:$I, A31, Results!$G:$G, $B$21, Results!B:B, 0) -> 109 | D31: =COUNTIFS(Results!$I:$I, A31, Results!$G:$G, $B$21, Results!B:B, 1) -> 97 | E31: =IFERROR(D31/C31, 0) -> 0.88990826 | F31: =COUNTIFS(Results!$I:$I, $A31, Results!$G:$G, $F$21) -> 43 | G31: =COUNTIFS(Results!$I:$I, $A31, Results!$G:$G, $F$21, Results!B:B, 1) + COUNTIFS(Results!$I:$I, $A31, Results!$G:$G, $F$21, Results!B:B, 0) -> 42 | H31: =COUNTIFS(Results!$I:$I, $A31, Results!$G:$G, $F$21, Results!B:B, 1) -> 36 | I31: =IFERROR(H31/G31, 0) -> 0.85714286 | J31: =COUNTIFS(Results!$I:$I, $A31,Results!$G:$G, $J$21) -> 54 | K31: =COUNTIFS(Results!$I:$I, $A31,Results!$G:$G, $J$21, Results!B:B, 1) + COUNTIFS(Results!$I:$I, $A31,Results!$G:$G, $J$21, Results!B:B, 0) -> 46 | L31: =COUNTIFS(Results!$I:$I, $A31,Results!$G:$G, $J$21, Results!B:B, 1) -> 7 | M31: =IFERROR(L31/K31, 0) -> 0.15217391 | N31: =COUNTIFS(Results!$I:$I, $A31, Results!$G:$G, $N$21) -> 0 | O31: =COUNTIFS(Results!$I:$I, $A31, Results!$G:$G, $N$21, Results!B:B, 1) + COUNTIFS(Results!$I:$I, $A31, Results!$G:$G, $N$21, Results!B:B, 0) -> 0 | P31: =COUNTIFS(Results!$I:$I, $A31, Results!$G:$G, $N$21, Results!B:B, 1) -> 0 | Q31: =IFERROR(P31/O31, 0) -> 0 | R31: =G11 -> 0
A32: casEN_spaCy_Stanza_priority | B32: =COUNTIFS(Results!$I:$I, A32, Results!$G:$G, $B$21) -> 102 | C32: =COUNTIFS(Results!$I:$I, A32, Results!$G:$G, $B$21, Results!B:B, 1) + COUNTIFS(Results!$I:$I, A32, Results!$G:$G, $B$21, Results!B:B, 0) -> 91 | D32: =COUNTIFS(Results!$I:$I, A32, Results!$G:$G, $B$21, Results!B:B, 1) -> 91 | E32: =IFERROR(D32/C32, 0) -> 1 | F32: =COUNTIFS(Results!$I:$I, $A32, Results!$G:$G, $F$21) -> 0 | G32: =COUNTIFS(Results!$I:$I, $A32, Results!$G:$G, $F$21, Results!B:B, 1) + COUNTIFS(Results!$I:$I, $A32, Results!$G:$G, $F$21, Results!B:B, 0) -> 0 | H32: =COUNTIFS(Results!$I:$I, $A32, Results!$G:$G, $F$21, Results!B:B, 1) -> 0 | I32: =IFERROR(H32/G32, 0) -> 0 | J32: =COUNTIFS(Results!$I:$I, $A32,Results!$G:$G, $J$21) -> 0 | K32: =COUNTIFS(Results!$I:$I, $A32,Results!$G:$G, $J$21, Results!B:B, 1) + COUNTIFS(Results!$I:$I, $A32,Results!$G:$G, $J$21, Results!B:B, 0) -> 0 | L32: =COUNTIFS(Results!$I:$I, $A32,Results!$G:$G, $J$21, Results!B:B, 1) -> 0 | M32: =IFERROR(L32/K32, 0) -> 0 | N32: =COUNTIFS(Results!$I:$I, $A32, Results!$G:$G, $N$21) -> 0 | O32: =COUNTIFS(Results!$I:$I, $A32, Results!$G:$G, $N$21, Results!B:B, 1) + COUNTIFS(Results!$I:$I, $A32, Results!$G:$G, $N$21, Results!B:B, 0) -> 0 | P32: =COUNTIFS(Results!$I:$I, $A32, Results!$G:$G, $N$21, Results!B:B, 1) -> 0 | Q32: =IFERROR(P32/O32, 0) -> 0 | R32: =G12 -> 1
A33: casEN_spaCy_priority | B33: =COUNTIFS(Results!$I:$I, A33, Results!$G:$G, $B$21) -> 154 | C33: =COUNTIFS(Results!$I:$I, A33, Results!$G:$G, $B$21, Results!B:B, 1) + COUNTIFS(Results!$I:$I, A33, Results!$G:$G, $B$21, Results!B:B, 0) -> 144 | D33: =COUNTIFS(Results!$I:$I, A33, Results!$G:$G, $B$21, Results!B:B, 1) -> 116 | E33: =IFERROR(D33/C33, 0) -> 0.80555556 | F33: =COUNTIFS(Results!$I:$I, $A33, Results!$G:$G, $F$21) -> 0 | G33: =COUNTIFS(Results!$I:$I, $A33, Results!$G:$G, $F$21, Results!B:B, 1) + COUNTIFS(Results!$I:$I, $A33, Results!$G:$G, $F$21, Results!B:B, 0) -> 0 | H33: =COUNTIFS(Results!$I:$I, $A33, Results!$G:$G, $F$21, Results!B:B, 1) -> 0 | I33: =IFERROR(H33/G33, 0) -> 0 | J33: =COUNTIFS(Results!$I:$I, $A33,Results!$G:$G, $J$21) -> 0 | K33: =COUNTIFS(Results!$I:$I, $A33,Results!$G:$G, $J$21, Results!B:B, 1) + COUNTIFS(Results!$I:$I, $A33,Results!$G:$G, $J$21, Results!B:B, 0) -> 0 | L33: =COUNTIFS(Results!$I:$I, $A33,Results!$G:$G, $J$21, Results!B:B, 1) -> 0 | M33: =IFERROR(L33/K33, 0) -> 0 | N33: =COUNTIFS(Results!$I:$I, $A33, Results!$G:$G, $N$21) -> 0 | O33: =COUNTIFS(Results!$I:$I, $A33, Results!$G:$G, $N$21, Results!B:B, 1) + COUNTIFS(Results!$I:$I, $A33, Results!$G:$G, $N$21, Results!B:B, 0) -> 0 | P33: =COUNTIFS(Results!$I:$I, $A33, Results!$G:$G, $N$21, Results!B:B, 1) -> 0 | Q33: =IFERROR(P33/O33, 0) -> 0 | R33: =G13 -> 1
A35: Total | B35: =SUM(B22:B33) -> 15732 | F35: =SUM(F22:F33) -> 7904 | J35: =SUM(J22:J33) -> 4251 | N35: =SUM(N22:N33) -> 7076
A36: pourcentage | B36: =B35/(B35+F35+J35+N35) -> 0.44996139 | F36: =F35/(F35+B35+J35+N35) -> 0.22606756 | J36: =J35/(B35+F35+J35+N35) -> 0.12158568 | N36: =N35/(N35+J35+F35+B35) -> 0.20238538
A40: Corrected | B40: =C2+C3+C4+C5+C6+C7+C8+C9+C10+C11+C12+C13 -> 18990
A41: Missing correction | B41: =COUNTA(Results!M:M) - B40 -> 15974
