Workbook

Sheet Results
A1: manual cat | B1: correct | C1: extent | D1: NER_category | E1: titles | F1: NER | G1: NER_label | H1: desc | I1: method | J1: main_graph | K1: second_graph | L1: third_graph | M1: file_id | N1: entity_start | O1: entity_end
A2: PER | B2: 1 | C2: 1 | D2: 1 | E2: Faster than fear | F2: Ralf | G2: PER | H2: Ralf a pu prouver son innocence et | I2: stanza | M2: 0 | N2: 0 | O2: 4
A3: PER | B3: 0 | C3: 1 | D3: PER | E3: Faster than fear | F3: Sunny | G3: MISC | H3: a pu prouver son innocence et Sunny a été suspendue de ses foncti | I3: stanza | M3: 0 | N3: 35 | O3: 40
E4: Faster than fear | F4: Sunny | G4: PER | H4: a pu prouver son innocence et Sunny a été suspendue de ses foncti | I4: spaCy | M4: 0 | N4: 35 | O4: 40
E5: Faster than fear | F5: affaire Haffner | G5: MISC | H5: e n'a plus rien à voir avec l'affaire Haffner, mais celui-ci demande à ne p | I5: stanza | M5: 0 | N5: 108 | O5: 123
A6: PER | B6: 1 | C6: 1 | D6: 1 | E6: Faster than fear | F6: Haffner | G6: PER | H6: us rien à voir avec l'affaire Haffner, mais celui-ci demande à ne p | I6: spaCy | M6: 0 | N6: 116 | O6: 123
A7: PER | B7: 0 | C7: 1 | D7: PER | E7: Faster than fear | F7: Sunny | G7: LOC | H7: i-ci demande à ne parler qu'à Sunny. D'ailleurs, elle est persuad | I7: spaCy_stanza | M7: 0 | N7: 164 | O7: 169
E8: Faster than fear | F8: Nora | G8: LOC | H8: leurs, elle est persuadée que Nora a divulgué des informations à | I8: spaCy | M8: 0 | N8: 206 | O8: 210
A9: PER | B9: 1 | C9: 1 | D9: 1 | E9: Faster than fear | F9: Nora | G9: PER | H9: leurs, elle est persuadée que Nora a divulgué des informations à | I9: casEN_stanza_priority | J9: grfpersGenerique | M9: 0 | N9: 206 | O9: 210
A10: PER | B10: 1 | C10: 1 | D10: 1 | E10: Faster than fear | F10: Haffner | G10: PER | H10: er à... elle. En garde à vue, Haffner n'avoue toujours pas où se tr | I10: spaCy_stanza | M10: 0 | N10: 311 | O10: 318
A11: PER | B11: 1 | C11: 1 | D11: 1 | E11: Faster than fear | F11: Marcel | G11: PER | H11: oue toujours pas où se trouve Marcel. | I11: casEN_spaCy_stanza | J11: grfpersGenerique | M11: 0 | N11: 353 | O11: 359
A12: PER | B12: 1 | C12: 1 | D12: 1 | E12: Commissaire Magellan (S1-E30) | F12: Tristan Garil | G12: PER | H12: vre du talentueux photographe Tristan Garil s'apprête à être exposée dans | I12: casEN_stanza | J12: grfpersPrenomNom | K12: grftagPrenom | L12: grftagNomFamille | M12: 1 | N12: 35 | O12: 48
E13: Commissaire Magellan (S1-E30) | F13: Tristan | G13: MISC | H13: vre du talentueux photographe Tristan Garil s'apprête à être exposé | I13: spaCy | M13: 1 | N13: 35 | O13: 42
E14: Commissaire Magellan (S1-E30) | F14: galerie | G14: ORG | H14: pprête à être exposée dans la galerie Delandin. Mais la directrice | I14: casEN | J14: grforgProximite | M14: 1 | N14: 82 | O14: 89
A15: PER | B15: 1 | C15: 1 | D15: 1 | E15: Commissaire Magellan (S1-E30) | F15: Delandin | G15: PER | H15: être exposée dans la galerie Delandin. Mais la directrice et fondat | I15: spaCy_stanza_priority | M15: 1 | N15: 90 | O15: 98
E16: Commissaire Magellan (S1-E30) | F16: Delandin | G16: ORG | H16: être exposée dans la galerie Delandin. Mais la directrice et fondat | I16: casEN | J16: grforgSeule | K16: grfpersGenerique | M16: 1 | N16: 90 | O16: 98
A17: PER | B17: 1 | C17: 1 | D17: 1 | E17: Commissaire Magellan (S1-E30) | F17: Estelle Delandin | G17: PER | H17: ctrice et fondatrice du lieu, Estelle Delandin, est assassinée. Le commissai | I17: casEN_spaCy_stanza | J17: grfpersPrenomNom | K17: grftagPrenom | L17: grftagNomFamille | M17: 1 | N17: 142 | O17: 158
E18: Commissaire Magellan (S1-E30) | F18: commissaire Magellan | G18: PER | H18: Delandin, est assassinée. Le commissaire Magellan et le lieutenant Selma Berray | I18: spaCy | M18: 1 | N18: 179 | O18: 199
A19: PER | B19: 1 | C19: 1 | D19: 1 | E19: Commissaire Magellan (S1-E30) | F19: Magellan | G19: PER | H19: st assassinée. Le commissaire Magellan et le lieutenant Selma Berray | I19: casEN_stanza | J19: grfpersContextePersonne | K19: grftagNomFamille | M19: 1 | N19: 191 | O19: 199
A20: PER | B20: 1 | C20: 1 | D20: 1 | E20: Commissaire Magellan (S1-E30) | F20: Selma Berrayah | G20: PER | H20: ire Magellan et le lieutenant Selma Berrayah se chargent de l'enquête. Au | I20: casEN_spaCy_stanza | J20: grfpersPrenomNom | K20: grftagPrenom | L20: grftagNomFamille | M20: 1 | N20: 217 | O20: 231
A21: PER | B21: 0 | C21: 0 | D21: PER | E21: La mort du Père Noël | F21: Le Père Noël | G21: MISC | H21: Le Père Noël est mort. Qui l'a tué ? | I21: spaCy | M21: 3 | N21: 0 | O21: 12
A22: PER | B22: 1 | C22: 1 | D22: 1 | E22: La mort du Père Noël | F22: Père Noël | G22: PER | H22: Le Père Noël est mort. Qui l'a tué ? | I22: casEN_opti | J22: grfpersAmbigus | M22: 3 | N22: 3 | O22: 12
E23: La mort du Père Noël | F23: Père Noël | G23: MISC | H23: Le Père Noël est mort. Qui l'a tué ? | I23: stanza | M23: 3 | N23: 3 | O23: 12
A24: MISC | B24: 1 | C24: 1 | D24: 1 | E24: Commissaire Magellan (S1-E30) | F24: fête de la Bière | G24: MISC | H24: Le jour de la fête de la Bière à Saignac, Christophe Diaz es | I24: stanza | M24: 7 | N24: 14 | O24: 30
E25: Commissaire Magellan (S1-E30) | F25: fête de la | G25: MISC | H25: Le jour de la fête de la Bière à Saignac, Christophe D | I25: spaCy | M25: 7 | N25: 14 | O25: 24
E26: Commissaire Magellan (S1-E30) | F26: Bière | G26: LOC | H26: Le jour de la fête de la Bière à Saignac, Christophe Diaz es | I26: spaCy | M26: 7 | N26: 25 | O26: 30
A27: LOC | B27: 1 | C27: 1 | D27: 1 | E27: Commissaire Magellan (S1-E30) | F27: Saignac | G27: LOC | H27: jour de la fête de la Bière à Saignac, Christophe Diaz est retrouvé | I27: spaCy_stanza | M27: 7 | N27: 33 | O27: 40
A28: PER | B28: 1 | C28: 1 | D28: 1 | E28: Commissaire Magellan (S1-E30) | F28: Christophe Diaz | G28: PER | H28: a fête de la Bière à Saignac, Christophe Diaz est retrouvé mort à la brasse | I28: casEN_spaCy_stanza | J28: grfpersPrenomNom | K28: grftagPrenom | L28: grftagNomFamille | M28: 7 | N28: 42 | O28: 57
E29: Commissaire Magellan (S1-E30) | F29: brasserie | G29: ORG | H29: e Diaz est retrouvé mort à la brasserie des Trois Amis. Le jeune bras | I29: casEN | J29: grforgProximite | M29: 7 | N29: 81 | O29: 90
E30: Commissaire Magellan (S1-E30) | F30: Trois Amis | G30: ORG | H30: rouvé mort à la brasserie des Trois Amis. Le jeune brasseur avait un a | I30: spaCy_stanza | M30: 7 | N30: 95 | O30: 105
A31: PER | B31: 1 | C31: 1 | D31: 1 | E31: Commissaire Magellan (S1-E30) | F31: Magellan | G31: PER | H31: ale. Au cours de son enquête, Magellan découvre... la rivalité qui o | I31: casEN_spaCy_stanza | J31: grfpersGenerique | M31: 7 | N31: 267 | O31: 275
A32: PER | B32: 1 | C32: 1 | D32: 1 | E32: Commissaire Magellan (S1-E30) | F32: Claude Verague | G32: PER | H32: t la victime à son beau-père, Claude Verague, également brasseur. Mais le | I32: casEN_spaCy_stanza | J32: grfpersPrenomNom | K32: grftagPrenom | L32: grftagNomFamille | M32: 7 | N32: 341 | O32: 355
E33: Commissaire Magellan (S1-E34) | F33: commissaire Magellan | G33: PER | H33: Le commissaire Magellan et la lieutenante Berrayah mè | I33: spaCy | M33: 8 | N33: 3 | O33: 23
A34: PER | B34: 1 | C34: 1 | D34: 1 | E34: Commissaire Magellan (S1-E34) | F34: Magellan | G34: PER | H34: Le commissaire Magellan et la lieutenante Berrayah mè | I34: casEN_stanza | J34: grfpersContextePersonne | K34: grftagNomFamille | M34: 8 | N34: 15 | O34: 23
E35: Commissaire Magellan (S1-E34) | F35: Berrayah | G35: MISC | H35: re Magellan et la lieutenante Berrayah mènent des investigations sur | I35: spaCy | M35: 8 | N35: 42 | O35: 50
A36: PER | B36: 1 | C36: 1 | D36: 1 | E36: Commissaire Magellan (S1-E34) | F36: Berrayah | G36: PER | H36: re Magellan et la lieutenante Berrayah mènent des investigations sur | I36: casEN_stanza_priority | J36: grfpersContextePersonne | K36: grftagNomFamille | M36: 8 | N36: 42 | O36: 50
A37: PER | B37: 1 | C37: 1 | D37: 1 | E37: Commissaire Magellan (S1-E34) | F37: Audrey Galvi | G37: PER | H37: stigations sur l'assassinat d'Audrey Galvi, une championne olympique dev | I37: casEN_spaCy_stanza | J37: grfpersPrenomNom | K37: grftagPrenom | L37: grftagNomFamille | M37: 8 | N37: 96 | O37: 108
A38: PER | B38: 1 | C38: 1 | D38: 1 | E38: Commissaire Magellan (S1-E34) | F38: Lucie Mauricourt | G38: PER | H38: er deux prodiges de la glace, Lucie Mauricourt et Lorena Bardin, jusqu'aux.. | I38: casEN_spaCy_stanza | J38: grfpersPrenomNom | K38: grftagPrenom | L38: grftagNomFamille | M38: 8 | N38: 246 | O38: 262
A39: PER | B39: 1 | C39: 1 | D39: 1 | E39: Commissaire Magellan (S1-E34) | F39: Lorena Bardin | G39: PER | H39: la glace, Lucie Mauricourt et Lorena Bardin, jusqu'aux... marches du podi | I39: casEN_spaCy_stanza | J39: grfpersPrenomNom | K39: grftagPrenom | L39: grftagNomFamille | M39: 8 | N39: 266 | O39: 279
A40: PER | B40: 1 | C40: 1 | D40: 1 | E40: Commissaire Magellan (S1-E34) | F40: Magellan | G40: PER | H40: squ'aux... marches du podium. Magellan s'intéresse de près à ces deu | I40: casEN_spaCy_stanza | J40: grfpersGenerique | M40: 8 | N40: 313 | O40: 321
A41: PER | B41: 1 | C41: 1 | D41: 1 | E41: Einstein : équations criminelles (S3-E1) | F41: Felix Winterberg | G41: PER | H41: Brillant physicien, Felix Winterberg aurait hérité des aptitudes m | I41: casEN_spaCy_stanza | J41: grfpersPrenomNom | K41: grftagPrenom | L41: grftagNomFamille | M41: 9 | N41: 20 | O41: 36
A42: PER | B42: 1 | C42: 1 | D42: 1 | E42: Einstein : équations criminelles (S3-E1) | F42: Albert Einstein | G42: PER | H42: ntales de son aïeul supposé : Albert Einstein. Arrêté pour consommation de | I42: casEN_spaCy_stanza | J42: grfpersPrenomNom | K42: grftagPrenom | L42: grftagNomFamille | M42: 9 | N42: 97 | O42: 112
E43: Einstein : équations criminelles (S3-E1) | F43: Arrêté | G43: LOC | H43: ul supposé : Albert Einstein. Arrêté pour consommation de stupéfia | I43: stanza | M43: 9 | N43: 114 | O43: 120
A44: PER | B44: 1 | C44: 1 | D44: 1 | E44: Einstein : équations criminelles (S3-E1) | F44: Felix | G44: PER | H44: consommation de stupéfiants, Felix passe, contre son gré, un acc | I44: casEN_spaCy_stanza | J44: grfpersGenerique | M44: 9 | N44: 155 | O44: 160
E45: Einstein : équations criminelles (S3-E1) | F45: police | G45: ORG | H45: re son gré, un accord avec la police afin d'éviter la prison : il | I45: casEN | J45: grforgPolice | M45: 9 | N45: 202 | O45: 208
E46: Einstein : équations criminelles (S3-E1) | F46: prison | G46: LOC | H46: ec la police afin d'éviter la prison : il va devoir aider la commi | I46: casEN | J46: grfplaceBatiment | M46: 9 | N46: 226 | O46: 232
A47: PER | B47: 1 | C47: 1 | D47: 1 | E47: Einstein : équations criminelles (S3-E1) | F47: Elena Lange | G47: PER | H47: a devoir aider la commissaire Elena Lange à résoudre... des affaires cr | I47: casEN_spaCy_stanza | J47: grfpersPrenomNom | K47: grftagPrenom | L47: grftagNomFamille | M47: 9 | N47: 269 | O47: 280
A48: LOC | B48: 1 | C48: 1 | D48: 1 | E48: Einstein : équations criminelles (S3-E1) | F48: Bochum | G48: LOC | H48: d'une fête, les enquêteurs de Bochum sont sur le qui-vive : le meu | I48: casEN_spaCy_stanza | J48: grfgeog | M48: 9 | N48: 442 | O48: 448
E49: Chicago Fire (S2-E11) | F49: quartier | G49: LOC | H49: la nuit est glaciale, tout le quartier est bientôt plongé dans l'obs | I49: casEN | J49: grfplaceQuartier | M49: 10 | N49: 118 | O49: 126
E50: Chicago Fire (S2-E11) | F50: caserne | G50: LOC | H50: es habitants à se rendre à la caserne. Mais... la situation ne tard | I50: casEN | J50: grfplaceBatiment | M50: 10 | N50: 271 | O50: 278
A51: PER | B51: 1 | C51: 1 | D51: 1 | E51: Chicago Fire (S2-E11) | F51: Casey | G51: PER | H51: ion ne tarde pas à dégénérer. Casey a toujours de gros problèmes | I51: spaCy_stanza | M51: 10 | N51: 327 | O51: 332
E52: Chicago Fire (S2-E11) | F52: Dawson | G52: PER | H52: ire mais refuse d'en parler à Dawson. | I52: spaCy_stanza | M52: 10 | N52: 399 | O52: 405
E53: Chicago Police Department (S2-E10) | F53: équipe | G53: ORG | H53: L'équipe est appelée dans un club de s | I53: casEN | J53: grforgProximite | M53: 11 | N53: 2 | O53: 8
E54: Chicago Police Department (S2-E10) | F54: Burgess | G54: PER | H54: taient des avocats brillants. Burgess est à la fois inquiète et exc | I54: stanza | M54: 11 | N54: 149 | O54: 156
A55: PER | B55: 0 | C55: 1 | D55: PER | E55: Chicago Police Department (S2-E10) | F55: Burgess | G55: LOC | H55: taient des avocats brillants. Burgess est à la fois inquiète et exc | I55: spaCy | M55: 11 | N55: 149 | O55: 156
A56: PER | B56: 1 | C56: 1 | D56: 1 | E56: Chicago Police Department (S2-E10) | F56: Voight | G56: PER | H56: sur laquelle elle intervient. Voight parvient à neutraliser l'un.. | I56: spaCy_stanza | M56: 11 | N56: 251 | O56: 257
A57: PER | B57: 1 | C57: 1 | D57: 1 | E57: Chicago Police Department (S2-E10) | F57: Erin | G57: PER | H57: le faire parler. De son côté, Erin a du mal à reprendre le dessu | I57: casEN_spaCy_stanza | J57: grfpersGenerique | M57: 11 | N57: 347 | O57: 351
E58: Family Law (S1-E1) | F58: Daniel et Abigail | G58: PER | H58: Daniel et Abigail défendent une mère qui risque | I58: spaCy | M58: 12 | N58: 0 | O58: 17
A59: PER | B59: 1 | C59: 1 | D59: 1 | E59: Family Law (S1-E1) | F59: Daniel | G59: PER | H59: Daniel et Abigail défendent une mère | I59: casEN_stanza | J59: grfpersGenerique | M59: 12 | N59: 0 | O59: 6
A60: PER | B60: 1 | C60: 1 | D60: 1 | E60: Family Law (S1-E1) | F60: Abigail | G60: PER | H60: Daniel et Abigail défendent une mère qui risque | I60: casEN_stanza | J60: grfpersGenerique | M60: 12 | N60: 10 | O60: 17
E61: Family Law (S1-E1) | F61: Abby | G61: PER | H61: et en lumière la dépendance d'Abby, qui continue de nier ce fait | I61: casEN_stanza_priority | J61: grfpersGenerique | M61: 12 | N61: 151 | O61: 155
A62: PER | B62: 0 | C62: 1 | D62: PER | E62: Family Law (S1-E1) | F62: Abby | G62: MISC | H62: et en lumière la dépendance d'Abby, qui continue de nier ce fait | I62: spaCy | M62: 12 | N62: 151 | O62: 155
A63: PER | B63: 1 | C63: 1 | D63: 1 | E63: Family Law (S1-E1) | F63: Daniel | G63: PER | H63: ont elle devra payer le prix. Daniel décide de se marier avec Dani | I63: casEN_spaCy_stanza | J63: grfpersGenerique | M63: 12 | N63: 232 | O63: 238
E64: Family Law (S1-E1) | F64: Danielle | G64: PER | H64: niel décide de se marier avec Danielle et Lucy exprime... son avis à | I64: stanza | M64: 12 | N64: 264 | O64: 272
A65: PER | B65: 0 | C65: 1 | D65: PER | E65: Family Law (S1-E1) | F65: Danielle | G65: LOC | H65: niel décide de se marier avec Danielle et Lucy exprime... son avis à | I65: spaCy | M65: 12 | N65: 264 | O65: 272
E66: Family Law (S1-E1) | F66: Lucy | G66: PER | H66: de se marier avec Danielle et Lucy exprime... son avis à ce suje | I66: casEN_stanza_priority | J66: grfpersGenerique | M66: 12 | N66: 276 | O66: 280
A67: PER | B67: 0 | C67: 1 | D67: PER | E67: Family Law (S1-E1) | F67: Lucy | G67: LOC | H67: de se marier avec Danielle et Lucy exprime... son avis à ce suje | I67: spaCy | M67: 12 | N67: 276 | O67: 280
A68: PER | B68: 1 | C68: 1 | D68: 1 | E68: Commissaire Magellan (S1-E34) | F68: Adrien Beauval | G68: PER | H68: Adrien Beauval est de retour à Saignac pour | I68: casEN_spaCy_stanza | J68: grfpersPrenomNom | K68: grftagPrenom | L68: grftagNomFamille | M68: 13 | N68: 0 | O68: 14
A69: LOC | B69: 1 | C69: 1 | D69: 1 | E69: Commissaire Magellan (S1-E34) | F69: Saignac | G69: LOC | H69: drien Beauval est de retour à Saignac pour la signature de son dern | I69: spaCy_stanza | M69: 13 | N69: 31 | O69: 38
E70: Commissaire Magellan (S1-E34) | F70: commissaire Magellan | G70: PER | H70: l s'apprêtait à dévoiler ? Le commissaire Magellan et le lieutenant Selma Berray | I70: spaCy | M70: 13 | N70: 422 | O70: 442
A71: PER | B71: 1 | C71: 1 | D71: 1 | E71: Commissaire Magellan (S1-E34) | F71: Magellan | G71: PER | H71: t à dévoiler ? Le commissaire Magellan et le lieutenant Selma Berray | I71: casEN_stanza | J71: grfpersContextePersonne | K71: grftagNomFamille | M71: 13 | N71: 434 | O71: 442
A72: PER | B72: 1 | C72: 1 | D72: 1 | E72: Commissaire Magellan (S1-E34) | F72: Selma Berrayah | G72: PER | H72: ire Magellan et le lieutenant Selma Berrayah vont devoir apprendre à lire | I72: casEN_spaCy_stanza | J72: grfpersPrenomNom | K72: grftagPrenom | L72: grftagNomFamille | M72: 13 | N72: 460 | O72: 474
E73: Einstein : équations criminelles (S3-E1) | F73: université | G73: ORG | H73: fait chanter des hommes de l'université faisant secrètement appel à d | I73: casEN | J73: grforgProximite | M73: 14 | N73: 133 | O73: 143
E74: Family Law (S1-E1) | F74: Abigail | G74: PER | H74: Abigail et Daniel représentent un ado | I74: casEN_stanza_priority | J74: grfpersGenerique | M74: 15 | N74: 0 | O74: 7
A75: PER | B75: 0 | C75: 1 | D75: PER | E75: Family Law (S1-E1) | F75: Abigail | G75: LOC | H75: Abigail et Daniel représentent un ado | I75: spaCy | M75: 15 | N75: 0 | O75: 7
A76: PER | B76: 1 | C76: 1 | D76: 1 | E76: Family Law (S1-E1) | F76: Daniel | G76: PER | H76: Abigail et Daniel représentent un adolescent ga | I76: casEN_spaCy_stanza | J76: grfpersGenerique | M76: 15 | N76: 11 | O76: 17
A77: PER | B77: 1 | C77: 1 | D77: 1 | E77: Family Law (S1-E1) | F77: Harry | G77: PER | H77: homme disparaît. De son côté, Harry donne une... seconde chance à | I77: casEN_spaCy_stanza | J77: grfpersGenerique | M77: 15 | N77: 272 | O77: 277
A78: PER | B78: 0 | C78: 1 | D78: PER | E78: Family Law (S1-E1) | F78: Abigail | G78: LOC | H78: donne une... seconde chance à Abigail. | I78: spaCy | M78: 15 | N78: 308 | O78: 315
E79: Family Law (S1-E1) | F79: Abigail | G79: MISC | H79: donne une... seconde chance à Abigail. | I79: stanza | M79: 15 | N79: 308 | O79: 315
E80: Family Law (S1-E1) | F80: Abigail | G80: PER | H80: donne une... seconde chance à Abigail. | I80: casEN | J80: grfpersGenerique | M80: 15 | N80: 308 | O80: 315
A81: PER | B81: 1 | C81: 1 | D81: 1 | E81: Chicago Fire (S1-E12) | F81: Kelly | G81: PER | H81: Kelly est fou d'inquiétude pour sa | I81: casEN_spaCy_stanza | J81: grfpersGenerique | M81: 16 | N81: 0 | O81: 5
A82: PER | B82: 1 | C82: 1 | D82: 1 | E82: Chicago Fire (S1-E12) | F82: Katie | G82: PER | H82: fou d'inquiétude pour sa sœur Katie qui a été enlevée. La police | I82: casEN_spaCy_stanza | J82: grfpersContextePersonne | K82: grftagNomFamille | M82: 16 | N82: 40 | O82: 45
E83: Chicago Fire (S1-E12) | F83: police | G83: ORG | H83: r Katie qui a été enlevée. La police soupçonne Vince Keeler, un vo | I83: casEN | J83: grforgPolice | M83: 16 | N83: 68 | O83: 74
A84: PER | B84: 1 | C84: 1 | D84: 1 | E84: Chicago Fire (S1-E12) | F84: Vince Keeler | G84: PER | H84: enlevée. La police soupçonne Vince Keeler, un voyou qui cherche à se ve | I84: casEN_spaCy_stanza | J84: grfpersPrenomNom | K84: grftagPrenom | L84: grftagNomFamille | M84: 16 | N84: 85 | O84: 97
A85: PER | B85: 1 | C85: 1 | D85: 1 | E85: Chicago Fire (S1-E12) | F85: Kelly | G85: PER | H85: ou qui cherche à se venger de Kelly. Pendant ce temps, Casey cons | I85: casEN_spaCy_stanza | J85: grfpersGenerique | M85: 16 | N85: 135 | O85: 140
A86: PER | B86: 1 | C86: 1 | D86: 1 | E86: Chicago Fire (S1-E12) | F86: Casey | G86: PER | H86: r de Kelly. Pendant ce temps, Casey consulte un médecin au sujet | I86: spaCy_stanza | M86: 16 | N86: 160 | O86: 165
A87: PER | B87: 1 | C87: 1 | D87: 1 | E87: Chicago Fire (S1-E12) | F87: Dawson | G87: PER | H87: aumatisme crânien.... Quant à Dawson, il a les plus grandes diffic | I87: spaCy_stanza | M87: 16 | N87: 296 | O87: 302
E88: Chicago Fire (S1-E12) | F88: académie | G88: ORG | H88: gène en vue de son entrée à l'académie. Deux joueurs professionnels | I88: casEN | J88: grforgProximite | M88: 16 | N88: 409 | O88: 417
E89: Chicago Fire (S1-E12) | F89: Brent Seabrook | G89: ORG | H89: urs professionnels de hockey, Brent Seabrook et Duncan Keith, se confient | I89: spaCy | M89: 16 | N89: 458 | O89: 472
A90: PER | B90: 1 | C90: 1 | D90: 1 | E90: Chicago Fire (S1-E12) | F90: Brent Seabrook | G90: PER | H90: urs professionnels de hockey, Brent Seabrook et Duncan Keith, se confient | I90: casEN_stanza_priority | J90: grfpersPrenomNom | K90: grftagPrenom | L90: grftagNomFamille | M90: 16 | N90: 458 | O90: 472
A91: PER | B91: 1 | C91: 1 | D91: 1 | E91: Chicago Fire (S1-E12) | F91: Duncan Keith | G91: PER | H91: de hockey, Brent Seabrook et Duncan Keith, se confient à Leslie Shay... | I91: casEN_spaCy_stanza | J91: grfpersPrenomNom | K91: grftagPrenom | L91: grftagNomFamille | M91: 16 | N91: 476 | O91: 488
A92: PER | B92: 1 | C92: 1 | D92: 1 | E92: Chicago Fire (S1-E12) | F92: Leslie Shay | G92: PER | H92: t Duncan Keith, se confient à Leslie Shay... | I92: casEN_spaCy_stanza | J92: grfpersPrenomNom | K92: grftagPrenom | L92: grftagNomFamille | M92: 16 | N92: 504 | O92: 515
A93: PER | B93: 1 | C93: 1 | D93: 1 | E93: Chicago Fire (S2-E11) | F93: Dawson | G93: PER | H93: dant de repasser ses examens, Dawson est de retour à la brigade en | I93: spaCy_stanza | M93: 17 | N93: 38 | O93: 44
E94: Chicago Fire (S2-E11) | F94: brigade | G94: ORG | H94: ns, Dawson est de retour à la brigade en tant qu'ambulancière. Jone | I94: casEN | J94: grforgPolice | M94: 17 | N94: 64 | O94: 71
A95: PER | B95: 1 | C95: 1 | D95: 1 | E95: Chicago Fire (S2-E11) | F95: Jones | G95: PER | H95: gade en tant qu'ambulancière. Jones, quant à elle, s'apprête à fa | I95: casEN_spaCy_stanza | J95: grfpersGenerique | M95: 17 | N95: 97 | O95: 102
A96: PER | B96: 0 | C96: 0 | D96: PER | E96: Chicago Fire (S2-E11) | F96: équipe de Casey | G96: ORG | H96: s de stagiaire aux côtés de l'équipe de Casey. Severide enrage à l'idée que | I96: casEN | J96: grforgSeule | K96: grforgProximite | M96: 17 | N96: 181 | O96: 196
E97: Chicago Fire (S2-E11) | F97: Casey | G97: LOC | H97: aire aux côtés de l'équipe de Casey. Severide enrage à l'idée que | I97: spaCy | M97: 17 | N97: 191 | O97: 196
E98: Chicago Fire (S2-E11) | F98: Casey | G98: PER | H98: aire aux côtés de l'équipe de Casey. Severide enrage à l'idée que | I98: stanza | M98: 17 | N98: 191 | O98: 196
A99: PER | B99: 0 | C99: 1 | D99: PER | E99: Chicago Fire (S2-E11) | F99: Severide | G99: ORG | H99: x côtés de l'équipe de Casey. Severide enrage à l'idée que Keeler pu | I99: casEN | J99: grforgGenerique | M99: 17 | N99: 198 | O99: 206
A100: PER | B100: 1 | C100: 1 | D100: 1 | E100: Chicago Fire (S2-E11) | F100: Severide | G100: PER | H100: x côtés de l'équipe de Casey. Severide enrage à l'idée que Keeler pu | I100: stanza | M100: 17 | N100: 198 | O100: 206
...

Sheet NER
A1: methods | B1: Total Founds | C1: Corrected | D1: Correct | E1: Accuracy | F1: Time | G1: Choose
A2: stanza | B2: =COUNTIF(Results!I:I, A2) -> 7391 | C2: =COUNTIFS(Results!I:I, A2, Results!B:B, 1) + COUNTIFS(Results!I:I, A2, Results!B:B, 0) -> 1458 | D2: =COUNTIFS(Results!I:I, A2,Results!B:B, 1) -> 1105 | E2: =D2/C2 -> 0.75788752 | F2: 367.36s CPU vs 104.43s GPU (rtx3070 FE) | G2: 0 | J2: Total | K2: Accuracy | L2: Data Gains | M2: Accuracy Loss
A3: spaCy | B3: =COUNTIF(Results!I:I, A3) -> 9476 | C3: =COUNTIFS(Results!I:I, A3, Results!B:B, 1) + COUNTIFS(Results!I:I, A3, Results!B:B, 0) -> 4965 | D3: =COUNTIFS(Results!I:I, A3,Results!B:B, 1) -> 673 | E3: =D3/C3 -> 0.13554884 | F3: 70.65s | G3: 0 | I3: old intersection (spaCy + CasEN) | J3: 5970 | K3: 0.977 | L3: =IFERROR((J3-J3)/J3, 0) -> 0 | M3: =K3-K3 -> 0
A4: spaCy_stanza | B4: =COUNTIF(Results!I:I, A4) -> 5472 | C4: =COUNTIFS(Results!I:I, A4, Results!B:B, 1) + COUNTIFS(Results!I:I, A4, Results!B:B, 0) -> 4537 | D4: =COUNTIFS(Results!I:I, A4,Results!B:B, 1) -> 3241 | E4: =D4/C4 -> 0.71434869 | G4: 0 | I4: spaCy + CasEN + opti + priority | J4: 7990 | K4: 0.95181187 | L4: 0.33835846 | M4: 0.025165797
A5: casEN_stanza_priority | B5: =COUNTIF(Results!I:I, A5) -> 1119 | C5: =COUNTIFS(Results!I:I, A5, Results!B:B, 1) + COUNTIFS(Results!I:I, A5, Results!B:B, 0) -> 650 | D5: =COUNTIFS(Results!I:I, A5,Results!B:B, 1) -> 592 | E5: =D5/C5 -> 0.91076923 | G5: 1 | I5: spaCy_casEN_Stanza | J5: =B6 -> 5523 | K5: =E6 -> 0.99116873 | L5: =IFERROR((J5-J3)/J3, 0) -> -0.074874372 | M5: =K3-K5 -> -0.014168734
A6: casEN_spaCy_stanza | B6: =COUNTIF(Results!I:I, A6) -> 5523 | C6: =COUNTIFS(Results!I:I, A6, Results!B:B, 1) + COUNTIFS(Results!I:I, A6, Results!B:B, 0) -> 5322 | D6: =COUNTIFS(Results!I:I, A6,Results!B:B, 1) -> 5275 | E6: =D6/C6 -> 0.99116873 | G6: 1
A7: casEN_stanza | B7: =COUNTIF(Results!I:I, A7) -> 740 | C7: =COUNTIFS(Results!I:I, A7, Results!B:B, 1) + COUNTIFS(Results!I:I, A7, Results!B:B, 0) -> 544 | D7: =COUNTIFS(Results!I:I, A7,Results!B:B, 1) -> 500 | E7: =D7/C7 -> 0.91911765 | G7: 1
A8: casEN | B8: =COUNTIF(Results!I:I, A8) -> 4976 | C8: =COUNTIFS(Results!I:I, A8, Results!B:B, 1) + COUNTIFS(Results!I:I, A8, Results!B:B, 0) -> 1092 | D8: =COUNTIFS(Results!I:I, A8,Results!B:B, 1) -> 376 | E8: =D8/C8 -> 0.34432234 | G8: 0
A9: spaCy_stanza_priority | B9: =COUNTIF(Results!I:I, A9) -> 71 | C9: =COUNTIFS(Results!I:I, A9, Results!B:B, 1) + COUNTIFS(Results!I:I, A9, Results!B:B, 0) -> 57 | D9: =COUNTIFS(Results!I:I, A9,Results!B:B, 1) -> 54 | E9: =D9/C9 -> 0.94736842 | G9: 1
A10: casEN_opti | B10: =COUNTIF(Results!I:I, A10) -> 505 | C10: =COUNTIFS(Results!I:I, A10, Results!B:B, 1) + COUNTIFS(Results!I:I, A10, Results!B:B, 0) -> 378 | D10: =COUNTIFS(Results!I:I, A10,Results!B:B, 1) -> 340 | E10: =D10/C10 -> 0.8994709 | G10: 1 | J10: Total Founds | K10: Corrected | L10: Correct | M10: Accuracy | N10: Data Gains | O10: Accuracy Loss
A11: casEN_spaCy | B11: =COUNTIF(Results!I:I, A11) -> 260 | C11: =COUNTIFS(Results!I:I, A11, Results!B:B, 1) + COUNTIFS(Results!I:I, A11, Results!B:B, 0) -> 236 | D11: =COUNTIFS(Results!I:I, A11,Results!B:B, 1) -> 179 | E11: =D11/C11 -> 0.75847458 | G11: 0 | I11: VS OLD inter | J11: =SUMIF(G2:G12, 1, B2:B12) -> 7958 | K11: =SUMIF(G2:G12, 1, C2:C12) -> 6951 | L11: =SUMIF(G2:G12, 1, D2:D12) -> 6761 | M11: =IFERROR(L11/K11, 0) -> 0.9726658 | N11: =(J11-J3)/J3 -> 0.33299832 | O11: =K3-M11 -> 0.0043341965
A12: casEN_spaCy_priority | B12: =COUNTIF(Results!I:I, A12) -> 110 | C12: =COUNTIFS(Results!I:I, A12, Results!B:B, 1) + COUNTIFS(Results!I:I, A12, Results!B:B, 0) -> 102 | D12: =COUNTIFS(Results!I:I, A12,Results!B:B, 1) -> 76 | E12: =D12/C12 -> 0.74509804 | G12: 0 | I12: VS spaCy casEN opti priority | J12: =SUMIF(G3:G13, 1, B3:B13) -> 7958 | K12: =SUMIF(G3:G13, 1, C3:C13) -> 6951 | L12: =SUMIF(G3:G13, 1, D3:D13) -> 6761 | M12: =IFERROR(L12/K12, 0) -> 0.9726658 | N12: =(J12-J4)/J4 -> -0.0040050063 | O12: =K4-M12 -> -0.02085393
I13: PER | J13: =SUMIF(R22:R33, 1, B22:B33) -> 8041 | K13: =SUMIF(R22:R33, 1, C22:C33) -> 5835 | L13: =SUMIF(R22:R33, 1, D22:D33) -> 5456 | M13: =IFERROR(L13/K13, 0) -> 0.93504713
I14: LOC | J14: =SUMIF(R22:R33, 1, F22:F33) -> 2431 | K14: =SUMIF(R22:R33, 1, G22:G33) -> 1447 | L14: =SUMIF(R22:R33, 1, H22:H33) -> 1369 | M14: =IFERROR(L14/K14, 0) -> 0.94609537
A15: Total CasEN | B15: =B5+B6+B7+B8+B10+B11+B12 -> 13233 | C15: =C5+C6+C7+C8+C10+C11+C12 -> 8324 | D15: =D5+D6+D7+D8+D10+D11+D12 -> 7338 | E15: =D15/C15 -> 0.88154733 | I15: ORG | J15: =SUMIF(R22:R33, 1, J22:J33) -> 2391 | K15: =SUMIF(R22:R33, 1, K22:K33) -> 704 | L15: =SUMIF(R22:R33, 1, L22:L33) -> 258 | M15: =IFERROR(L15/K15, 0) -> 0.36647727
A16: Total Stanza | B16: =B2+B4+B5+B6+B7+B9 -> 20316 | C16: =C2+C4+C5+C6+C7+C9 -> 12568 | D16: =D2+D4+D5+D6+D7+D9 -> 10767 | E16: =D16/C16 -> 0.85669955 | I16: MISC | J16: =SUMIF(R22:R33, 1, N22:N33) -> 0 | K16: =SUMIF(R22:R33, 1, O22:O33) -> 0 | L16: =SUMIF(R22:R33, 1, P22:P33) -> 0 | M16: =IFERROR(L16/K16, 0) -> 0
A17: Total SpaCy | B17: =B3+B4+B6+B9+B11+B12 -> 20912 | C17: =C3+C4+C6+C9+C11+C12 -> 15219 | D17: =D3+D4+D6+D9+D11+D12 -> 9498 | E17: =D17/C17 -> 0.62408831
A21: method | B21: PER | C21: Corrected | D21: Correct | E21: Accuracy | F21: LOC | G21: Corrected | H21: Correct | I21: Accuracy | J21: ORG | K21: Corrected | L21: Correct | M21: Accuracy | N21: MISC | O21: Corrected | P21: Correct | Q21: Accuracy | R21: Choose
A22: stanza | B22: =COUNTIFS(Results!$I:$I, A22, Results!$G:$G, $B$21) -> 3079 | C22: =COUNTIFS(Results!$I:$I, A22, Results!$G:$G, $B$21, Results!B:B, 1) + COUNTIFS(Results!$I:$I, A22, Results!$G:$G, $B$21, Results!B:B, 0) -> 847 | D22: =COUNTIFS(Results!$I:$I, A22, Results!$G:$G, $B$21, Results!B:B, 1) -> 825 | E22: =IFERROR(D22/C22, 0) -> 0.97402597 | F22: =COUNTIFS(Results!$I:$I, $A22, Results!$G:$G, $F$21) -> 816 | G22: =COUNTIFS(Results!$I:$I, $A22, Results!$G:$G, $F$21, Results!B:B, 1) + COUNTIFS(Results!$I:$I, $A22, Results!$G:$G, $F$21, Results!B:B, 0) -> 257 | H22: =COUNTIFS(Results!$I:$I, $A22, Results!$G:$G, $F$21, Results!B:B, 1) -> 218 | I22: =IFERROR(H22/G22, 0) -> 0.84824903 | J22: =COUNTIFS(Results!$I:$I, $A22,Results!$G:$G, $J$21) -> 975 | K22: =COUNTIFS(Results!$I:$I, $A22,Results!$G:$G, $J$21, Results!B:B, 1) + COUNTIFS(Results!$I:$I, $A22,Results!$G:$G, $J$21, Results!B:B, 0) -> 91 | L22: =COUNTIFS(Results!$I:$I, $A22,Results!$G:$G, $J$21, Results!B:B, 1) -> 53 | M22: =IFERROR(L22/K22, 0) -> 0.58241758 | N22: =COUNTIFS(Results!$I:$I, $A22, Results!$G:$G, $N$21) -> 2521 | O22: =COUNTIFS(Results!$I:$I, $A22, Results!$G:$G, $N$21, Results!B:B, 1) + COUNTIFS(Results!$I:$I, $A22, Results!$G:$G, $N$21, Results!B:B, 0) -> 263 | P22: =COUNTIFS(Results!$I:$I, $A22, Results!$G:$G, $N$21, Results!B:B, 1) -> 9 | Q22: =IFERROR(P22/O22, 0) -> 0.034220532 | R22: =G2 -> 0
A23: spaCy_stanza | B23: =COUNTIFS(Results!$I:$I, A23, Results!$G:$G, $B$21) -> 2574 | C23: =COUNTIFS(Results!$I:$I, A23, Results!$G:$G, $B$21, Results!B:B, 1) + COUNTIFS(Results!$I:$I, A23, Results!$G:$G, $B$21, Results!B:B, 0) -> 2138 | D23: =COUNTIFS(Results!$I:$I, A23, Results!$G:$G, $B$21, Results!B:B, 1) -> 2057 | E23: =IFERROR(D23/C23, 0) -> 0.96211413 | F23: =COUNTIFS(Results!$I:$I, $A23, Results!$G:$G, $F$21) -> 1222 | G23: =COUNTIFS(Results!$I:$I, $A23, Results!$G:$G, $F$21, Results!B:B, 1) + COUNTIFS(Results!$I:$I, $A23, Results!$G:$G, $F$21, Results!B:B, 0) -> 1084 | H23: =COUNTIFS(Results!$I:$I, $A23, Results!$G:$G, $F$21, Results!B:B, 1) -> 917 | I23: =IFERROR(H23/G23, 0) -> 0.84594096 | J23: =COUNTIFS(Results!$I:$I, $A23,Results!$G:$G, $J$21) -> 246 | K23: =COUNTIFS(Results!$I:$I, $A23,Results!$G:$G, $J$21, Results!B:B, 1) + COUNTIFS(Results!$I:$I, $A23,Results!$G:$G, $J$21, Results!B:B, 0) -> 183 | L23: =COUNTIFS(Results!$I:$I, $A23,Results!$G:$G, $J$21, Results!B:B, 1) -> 149 | M23: =IFERROR(L23/K23, 0) -> 0.81420765 | N23: =COUNTIFS(Results!$I:$I, $A23, Results!$G:$G, $N$21) -> 1430 | O23: =COUNTIFS(Results!$I:$I, $A23, Results!$G:$G, $N$21, Results!B:B, 1) + COUNTIFS(Results!$I:$I, $A23, Results!$G:$G, $N$21, Results!B:B, 0) -> 1132 | P23: =COUNTIFS(Results!$I:$I, $A23, Results!$G:$G, $N$21, Results!B:B, 1) -> 118 | Q23: =IFERROR(P23/O23, 0) -> 0.10424028 | R23: =G3 -> 0
A24: spaCy | B24: =COUNTIFS(Results!$I:$I, A24, Results!$G:$G, $B$21) -> 1713 | C24: =COUNTIFS(Results!$I:$I, A24, Results!$G:$G, $B$21, Results!B:B, 1) + COUNTIFS(Results!$I:$I, A24, Results!$G:$G, $B$21, Results!B:B, 0) -> 906 | D24: =COUNTIFS(Results!$I:$I, A24, Results!$G:$G, $B$21, Results!B:B, 1) -> 415 | E24: =IFERROR(D24/C24, 0) -> 0.4580574 | F24: =COUNTIFS(Results!$I:$I, $A24, Results!$G:$G, $F$21) -> 4108 | G24: =COUNTIFS(Results!$I:$I, $A24, Results!$G:$G, $F$21, Results!B:B, 1) + COUNTIFS(Results!$I:$I, $A24, Results!$G:$G, $F$21, Results!B:B, 0) -> 2349 | H24: =COUNTIFS(Results!$I:$I, $A24, Results!$G:$G, $F$21, Results!B:B, 1) -> 199 | I24: =IFERROR(H24/G24, 0) -> 0.084716901 | J24: =COUNTIFS(Results!$I:$I, $A24,Results!$G:$G, $J$21) -> 648 | K24: =COUNTIFS(Results!$I:$I, $A24,Results!$G:$G, $J$21, Results!B:B, 1) + COUNTIFS(Results!$I:$I, $A24,Results!$G:$G, $J$21, Results!B:B, 0) -> 258 | L24: =COUNTIFS(Results!$I:$I, $A24,Results!$G:$G, $J$21, Results!B:B, 1) -> 45 | M24: =IFERROR(L24/K24, 0) -> 0.1744186 | N24: =COUNTIFS(Results!$I:$I, $A24, Results!$G:$G, $N$21) -> 3007 | O24: =COUNTIFS(Results!$I:$I, $A24, Results!$G:$G, $N$21, Results!B:B, 1) + COUNTIFS(Results!$I:$I, $A24, Results!$G:$G, $N$21, Results!B:B, 0) -> 1452 | P24: =COUNTIFS(Results!$I:$I, $A24, Results!$G:$G, $N$21, Results!B:B, 1) -> 14 | Q24: =IFERROR(P24/O24, 0) -> 0.0096418733 | R24: =G4 -> 0
A25: casEN_stanza_priority | B25: =COUNTIFS(Results!$I:$I, A25, Results!$G:$G, $B$21) -> 1119 | C25: =COUNTIFS(Results!$I:$I, A25, Results!$G:$G, $B$21, Results!B:B, 1) + COUNTIFS(Results!$I:$I, A25, Results!$G:$G, $B$21, Results!B:B, 0) -> 650 | D25: =COUNTIFS(Results!$I:$I, A25, Results!$G:$G, $B$21, Results!B:B, 1) -> 592 | E25: =IFERROR(D25/C25, 0) -> 0.91076923 | F25: =COUNTIFS(Results!$I:$I, $A25, Results!$G:$G, $F$21) -> 0 | G25: =COUNTIFS(Results!$I:$I, $A25, Results!$G:$G, $F$21, Results!B:B, 1) + COUNTIFS(Results!$I:$I, $A25, Results!$G:$G, $F$21, Results!B:B, 0) -> 0 | H25: =COUNTIFS(Results!$I:$I, $A25, Results!$G:$G, $F$21, Results!B:B, 1) -> 0 | I25: =IFERROR(H25/G25, 0) -> 0 | J25: =COUNTIFS(Results!$I:$I, $A25,Results!$G:$G, $J$21) -> 0 | K25: =COUNTIFS(Results!$I:$I, $A25,Results!$G:$G, $J$21, Results!B:B, 1) + COUNTIFS(Results!$I:$I, $A25,Results!$G:$G, $J$21, Results!B:B, 0) -> 0 | L25: =COUNTIFS(Results!$I:$I, $A25,Results!$G:$G, $J$21, Results!B:B, 1) -> 0 | M25: =IFERROR(L25/K25, 0) -> 0 | N25: =COUNTIFS(Results!$I:$I, $A25, Results!$G:$G, $N$21) -> 0 | O25: =COUNTIFS(Results!$I:$I, $A25, Results!$G:$G, $N$21, Results!B:B, 1) + COUNTIFS(Results!$I:$I, $A25, Results!$G:$G, $N$21, Results!B:B, 0) -> 0 | P25: =COUNTIFS(Results!$I:$I, $A25, Results!$G:$G, $N$21, Results!B:B, 1) -> 0 | Q25: =IFERROR(P25/O25, 0) -> 0 | R25: =G5 -> 1
A26: casEN_spaCy_stanza | B26: =COUNTIFS(Results!$I:$I, A26, Results!$G:$G, $B$21) -> 4507 | C26: =COUNTIFS(Results!$I:$I, A26, Results!$G:$G, $B$21, Results!B:B, 1) + COUNTIFS(Results!$I:$I, A26, Results!$G:$G, $B$21, Results!B:B, 0) -> 4309 | D26: =COUNTIFS(Results!$I:$I, A26, Results!$G:$G, $B$21, Results!B:B, 1) -> 4271 | E26: =IFERROR(D26/C26, 0) -> 0.99118125 | F26: =COUNTIFS(Results!$I:$I, $A26, Results!$G:$G, $F$21) -> 930 | G26: =COUNTIFS(Results!$I:$I, $A26, Results!$G:$G, $F$21, Results!B:B, 1) + COUNTIFS(Results!$I:$I, $A26, Results!$G:$G, $F$21, Results!B:B, 0) -> 928 | H26: =COUNTIFS(Results!$I:$I, $A26, Results!$G:$G, $F$21, Results!B:B, 1) -> 924 | I26: =IFERROR(H26/G26, 0) -> 0.99568966 | J26: =COUNTIFS(Results!$I:$I, $A26,Results!$G:$G, $J$21) -> 86 | K26: =COUNTIFS(Results!$I:$I, $A26,Results!$G:$G, $J$21, Results!B:B, 1) + COUNTIFS(Results!$I:$I, $A26,Results!$G:$G, $J$21, Results!B:B, 0) -> 85 | L26: =COUNTIFS(Results!$I:$I, $A26,Results!$G:$G, $J$21, Results!B:B, 1) -> 80 | M26: =IFERROR(L26/K26, 0) -> 0.94117647 | N26: =COUNTIFS(Results!$I:$I, $A26, Results!$G:$G, $N$21) -> 0 | O26: =COUNTIFS(Results!$I:$I, $A26, Results!$G:$G, $N$21, Results!B:B, 1) + COUNTIFS(Results!$I:$I, $A26, Results!$G:$G, $N$21, Results!B:B, 0) -> 0 | P26: =COUNTIFS(Results!$I:$I, $A26, Results!$G:$G, $N$21, Results!B:B, 1) -> 0 | Q26: =IFERROR(P26/O26, 0) -> 0 | R26: =G6 -> 1
A27: casEN_stanza | B27: =COUNTIFS(Results!$I:$I, A27, Results!$G:$G, $B$21) -> 538 | C27: =COUNTIFS(Results!$I:$I, A27, Results!$G:$G, $B$21, Results!B:B, 1) + COUNTIFS(Results!$I:$I, A27, Results!$G:$G, $B$21, Results!B:B, 0) -> 355 | D27: =COUNTIFS(Results!$I:$I, A27, Results!$G:$G, $B$21, Results!B:B, 1) -> 334 | E27: =IFERROR(D27/C27, 0) -> 0.94084507 | F27: =COUNTIFS(Results!$I:$I, $A27, Results!$G:$G, $F$21) -> 144 | G27: =COUNTIFS(Results!$I:$I, $A27, Results!$G:$G, $F$21, Results!B:B, 1) + COUNTIFS(Results!$I:$I, $A27, Results!$G:$G, $F$21, Results!B:B, 0) -> 139 | H27: =COUNTIFS(Results!$I:$I, $A27, Results!$G:$G, $F$21, Results!B:B, 1) -> 139 | I27: =IFERROR(H27/G27, 0) -> 1 | J27: =COUNTIFS(Results!$I:$I, $A27,Results!$G:$G, $J$21) -> 58 | K27: =COUNTIFS(Results!$I:$I, $A27,Results!$G:$G, $J$21, Results!B:B, 1) + COUNTIFS(Results!$I:$I, $A27,Results!$G:$G, $J$21, Results!B:B, 0) -> 50 | L27: =COUNTIFS(Results!$I:$I, $A27,Results!$G:$G, $J$21, Results!B:B, 1) -> 27 | M27: =IFERROR(L27/K27, 0) -> 0.54 | N27: =COUNTIFS(Results!$I:$I, $A27, Results!$G:$G, $N$21) -> 0 | O27: =COUNTIFS(Results!$I:$I, $A27, Results!$G:$G, $N$21, Results!B:B, 1) + COUNTIFS(Results!$I:$I, $A27, Results!$G:$G, $N$21, Results!B:B, 0) -> 0 | P27: =COUNTIFS(Results!$I:$I, $A27, Results!$G:$G, $N$21, Results!B:B, 1) -> 0 | Q27: =IFERROR(P27/O27, 0) -> 0 | R27: =G7 -> 1
A28: spaCy_stanza_priority | B28: =COUNTIFS(Results!$I:$I, A28, Results!$G:$G, $B$21) -> 71 | C28: =COUNTIFS(Results!$I:$I, A28, Results!$G:$G, $B$21, Results!B:B, 1) + COUNTIFS(Results!$I:$I, A28, Results!$G:$G, $B$21, Results!B:B, 0) -> 57 | D28: =COUNTIFS(Results!$I:$I, A28, Results!$G:$G, $B$21, Results!B:B, 1) -> 54 | E28: =IFERROR(D28/C28, 0) -> 0.94736842 | F28: =COUNTIFS(Results!$I:$I, $A28, Results!$G:$G, $F$21) -> 0 | G28: =COUNTIFS(Results!$I:$I, $A28, Results!$G:$G, $F$21, Results!B:B, 1) + COUNTIFS(Results!$I:$I, $A28, Results!$G:$G, $F$21, Results!B:B, 0) -> 0 | H28: =COUNTIFS(Results!$I:$I, $A28, Results!$G:$G, $F$21, Results!B:B, 1) -> 0 | I28: =IFERROR(H28/G28, 0) -> 0 | J28: =COUNTIFS(Results!$I:$I, $A28,Results!$G:$G, $J$21) -> 0 | K28: =COUNTIFS(Results!$I:$I, $A28,Results!$G:$G, $J$21, Results!B:B, 1) + COUNTIFS(Results!$I:$I, $A28,Results!$G:$G, $J$21, Results!B:B, 0) -> 0 | L28: =COUNTIFS(Results!$I:$I, $A28,Results!$G:$G, $J$21, Results!B:B, 1) -> 0 | M28: =IFERROR(L28/K28, 0) -> 0 | N28: =COUNTIFS(Results!$I:$I, $A28, Results!$G:$G, $N$21) -> 0 | O28: =COUNTIFS(Results!$I:$I, $A28, Results!$G:$G, $N$21, Results!B:B, 1) + COUNTIFS(Results!$I:$I, $A28, Results!$G:$G, $N$21, Results!B:B, 0) -> 0 | P28: =COUNTIFS(Results!$I:$I, $A28, Results!$G:$G, $N$21, Results!B:B, 1) -> 0 | Q28: =IFERROR(P28/O28, 0) -> 0 | R28: =G8 -> 0
A29: casEN | B29: =COUNTIFS(Results!$I:$I, A29, Results!$G:$G, $B$21) -> 1725 | C29: =COUNTIFS(Results!$I:$I, A29, Results!$G:$G, $B$21, Results!B:B, 1) + COUNTIFS(Results!$I:$I, A29, Results!$G:$G, $B$21, Results!B:B, 0) -> 460 | D29: =COUNTIFS(Results!$I:$I, A29, Results!$G:$G, $B$21, Results!B:B, 1) -> 211 | E29: =IFERROR(D29/C29, 0) -> 0.45869565 | F29: =COUNTIFS(Results!$I:$I, $A29, Results!$G:$G, $F$21) -> 1089 | G29: =COUNTIFS(Results!$I:$I, $A29, Results!$G:$G, $F$21, Results!B:B, 1) + COUNTIFS(Results!$I:$I, $A29, Results!$G:$G, $F$21, Results!B:B, 0) -> 134 | H29: =COUNTIFS(Results!$I:$I, $A29, Results!$G:$G, $F$21, Results!B:B, 1) -> 78 | I29: =IFERROR(H29/G29, 0) -> 0.58208955 | J29: =COUNTIFS(Results!$I:$I, $A29,Results!$G:$G, $J$21) -> 2162 | K29: =COUNTIFS(Results!$I:$I, $A29,Results!$G:$G, $J$21, Results!B:B, 1) + COUNTIFS(Results!$I:$I, $A29,Results!$G:$G, $J$21, Results!B:B, 0) -> 498 | L29: =COUNTIFS(Results!$I:$I, $A29,Results!$G:$G, $J$21, Results!B:B, 1) -> 87 | M29: =IFERROR(L29/K29, 0) -> 0.1746988 | N29: =COUNTIFS(Results!$I:$I, $A29, Results!$G:$G, $N$21) -> 0 | O29: =COUNTIFS(Results!$I:$I, $A29, Results!$G:$G, $N$21, Results!B:B, 1) + COUNTIFS(Results!$I:$I, $A29, Results!$G:$G, $N$21, Results!B:B, 0) -> 0 | P29: =COUNTIFS(Results!$I:$I, $A29, Results!$G:$G, $N$21, Results!B:B, 1) -> 0 | Q29: =IFERROR(P29/O29, 0) -> 0 | R29: =G9 -> 1
A30: casEN_opti | B30: =COUNTIFS(Results!$I:$I, A30, Results!$G:$G, $B$21) -> 152 | C30: =COUNTIFS(Results!$I:$I, A30, Results!$G:$G, $B$21, Results!B:B, 1) + COUNTIFS(Results!$I:$I, A30, Results!$G:$G, $B$21, Results!B:B, 0) -> 61 | D30: =COUNTIFS(Results!$I:$I, A30, Results!$G:$G, $B$21, Results!B:B, 1) -> 48 | E30: =IFERROR(D30/C30, 0) -> 0.78688525 | F30: =COUNTIFS(Results!$I:$I, $A30, Results!$G:$G, $F$21) -> 268 | G30: =COUNTIFS(Results!$I:$I, $A30, Results!$G:$G, $F$21, Results!B:B, 1) + COUNTIFS(Results!$I:$I, $A30, Results!$G:$G, $F$21, Results!B:B, 0) -> 246 | H30: =COUNTIFS(Results!$I:$I, $A30, Results!$G:$G, $F$21, Results!B:B, 1) -> 228 | I30: =IFERROR(H30/G30, 0) -> 0.92682927 | J30: =COUNTIFS(Results!$I:$I, $A30,Results!$G:$G, $J$21) -> 85 | K30: =COUNTIFS(Results!$I:$I, $A30,Results!$G:$G, $J$21, Results!B:B, 1) + COUNTIFS(Results!$I:$I, $A30,Results!$G:$G, $J$21, Results!B:B, 0) -> 71 | L30: =COUNTIFS(Results!$I:$I, $A30,Results!$G:$G, $J$21, Results!B:B, 1) -> 64 | M30: =IFERROR(L30/K30, 0) -> 0.90140845 | N30: =COUNTIFS(Results!$I:$I, $A30, Results!$G:$G, $N$21) -> 0 | O30: =COUNTIFS(Results!$I:$I, $A30, Results!$G:$G, $N$21, Results!B:B, 1) + COUNTIFS(Results!$I:$I, $A30, Results!$G:$G, $N$21, Results!B:B, 0) -> 0 | P30: =COUNTIFS(Results!$I:$I, $A30, Results!$G:$G, $N$21, Results!B:B, 1) -> 0 | Q30: =IFERROR(P30/O30, 0) -> 0 | R30: =G10 -> 1
A31: casEN_spaCy | B31: =COUNTIFS(Results!$I:$I, A31, Results!$G:$G, $B$21) -> 135 | C31: =COUNTIFS(Results!$I:$I, A31, Results!$G:$G, $B$21, Results!B:B, 1) + COUNTIFS(Results!$I:$I, A31, Results!$G:$G, $B$21, Results!B:B, 0) -> 127 | D31: =COUNTIFS(Results!$I:$I, A31, Results!$G:$G, $B$21, Results!B:B, 1) -> 116 | E31: =IFERROR(D31/C31, 0) -> 0.91338583 | F31: =COUNTIFS(Results!$I:$I, $A31, Results!$G:$G, $F$21) -> 68 | G31: =COUNTIFS(Results!$I:$I, $A31, Results!$G:$G, $F$21, Results!B:B, 1) + COUNTIFS(Results!$I:$I, $A31, Results!$G:$G, $F$21, Results!B:B, 0) -> 60 | H31: =COUNTIFS(Results!$I:$I, $A31, Results!$G:$G, $F$21, Results!B:B, 1) -> 53 | I31: =IFERROR(H31/G31, 0) -> 0.88333333 | J31: =COUNTIFS(Results!$I:$I, $A31,Results!$G:$G, $J$21) -> 57 | K31: =COUNTIFS(Results!$I:$I, $A31,Results!$G:$G, $J$21, Results!B:B, 1) + COUNTIFS(Results!$I:$I, $A31,Results!$G:$G, $J$21, Results!B:B, 0) -> 49 | L31: =COUNTIFS(Results!$I:$I, $A31,Results!$G:$G, $J$21, Results!B:B, 1) -> 10 | M31: =IFERROR(L31/K31, 0) -> 0.20408163 | N31: =COUNTIFS(Results!$I:$I, $A31, Results!$G:$G, $N$21) -> 0 | O31: =COUNTIFS(Results!$I:$I, $A31, Results!$G:$G, $N$21, Results!B:B, 1) + COUNTIFS(Results!$I:$I, $A31, Results!$G:$G, $N$21, Results!B:B, 0) -> 0 | P31: =COUNTIFS(Results!$I:$I, $A31, Results!$G:$G, $N$21, Results!B:B, 1) -> 0 | Q31: =IFERROR(P31/O31, 0) -> 0 | R31: =G11 -> 0
A32: casEN_spaCy_priority | B32: =COUNTIFS(Results!$I:$I, A32, Results!$G:$G, $B$21) -> 110 | C32: =COUNTIFS(Results!$I:$I, A32, Results!$G:$G, $B$21, Results!B:B, 1) + COUNTIFS(Results!$I:$I, A32, Results!$G:$G, $B$21, Results!B:B, 0) -> 102 | D32: =COUNTIFS(Results!$I:$I, A32, Results!$G:$G, $B$21, Results!B:B, 1) -> 76 | E32: =IFERROR(D32/C32, 0) -> 0.74509804 | F32: =COUNTIFS(Results!$I:$I, $A32, Results!$G:$G, $F$21) -> 0 | G32: =COUNTIFS(Results!$I:$I, $A32, Results!$G:$G, $F$21, Results!B:B, 1) + COUNTIFS(Results!$I:$I, $A32, Results!$G:$G, $F$21, Results!B:B, 0) -> 0 | H32: =COUNTIFS(Results!$I:$I, $A32, Results!$G:$G, $F$21, Results!B:B, 1) -> 0 | I32: =IFERROR(H32/G32, 0) -> 0 | J32: =COUNTIFS(Results!$I:$I, $A32,Results!$G:$G, $J$21) -> 0 | K32: =COUNTIFS(Results!$I:$I, $A32,Results!$G:$G, $J$21, Results!B:B, 1) + COUNTIFS(Results!$I:$I, $A32,Results!$G:$G, $J$21, Results!B:B, 0) -> 0 | L32: =COUNTIFS(Results!$I:$I, $A32,Results!$G:$G, $J$21, Results!B:B, 1) -> 0 | M32: =IFERROR(L32/K32, 0) -> 0 | N32: =COUNTIFS(Results!$I:$I, $A32, Results!$G:$G, $N$21) -> 0 | O32: =COUNTIFS(Results!$I:$I, $A32, Results!$G:$G, $N$21, Results!B:B, 1) + COUNTIFS(Results!$I:$I, $A32, Results!$G:$G, $N$21, Results!B:B, 0) -> 0 | P32: =COUNTIFS(Results!$I:$I, $A32, Results!$G:$G, $N$21, Results!B:B, 1) -> 0 | Q32: =IFERROR(P32/O32, 0) -> 0 | R32: =G12 -> 0
A35: Total | B35: =SUM(B22:B33) -> 15723 | F35: =SUM(F22:F33) -> 8645 | J35: =SUM(J22:J33) -> 4317 | N35: =SUM(N22:N33) -> 6958
A36: pourcentage | B36: =B35/(B35+F35+J35+N35) -> 0.44112448 | F36: =F35/(F35+B35+J35+N35) -> 0.24254412 | J36: =J35/(B35+F35+J35+N35) -> 0.12111775 | N36: =N35/(N35+J35+F35+B35) -> 0.19521365
A40: Corrected | B40: =C2+C3+C4+C5+C6+C7+C8+C9+C10+C11+C12+C13 -> 19341
A41: Missing correction | B41: =COUNTA(Results!M:M) - B40 -> 16303

Sheet graphs_analyses
A1: {=_xlfn.UNIQUE(_xlfn._xlws.FILTER(Results!J:J, Results!J:J<>""))} -> main_graph | B1: Total Founds | C1: Corrected | D1: Correct | E1: Total Accuracy | F1: casEN_spaCy_stanza | G1: Corrected | H1: Correct | I1: Accuracy | J1: Only CasEN | K1: Corrected | L1: Correct | M1: Accuracy | N1: Global Accuray Loss | R1: main_graph | S1: second_graph | T1: Total Founds | U1: Corrected | V1: Correct | W1: Total Accuracy | X1: casEN_spaCy_stanza | Y1: Corrected | Z1: Correct | AA1: Accuracy | AB1: Only CasEN | AC1: Corrected | AD1: Correct | AE1: Accuracy | AF1: Global Accuray Loss | AJ1: main_graph | AK1: second_graph | AL1: third_graph | AM1: Total Founds | AN1: Corrected | AO1: Correct | AP1: Total Accuracy | AQ1: casEN_spaCy_stanza | AR1: Corrected | AS1: Correct | AT1: Accuracy | AU1: Only CasEN | AV1: Corrected | AW1: Correct | AX1: Accuracy | AY1: Global Accuray Loss
A2: grfpersGenerique | B2: =COUNTIF(Results!J:J, A2) -> 5005 | C2: =COUNTIFS(Results!J:J, A2, Results!B:B, 1) + COUNTIFS(Results!J:J, A2, Results!B:B, 0) -> 2941 | D2: =COUNTIFS(Results!J:J, A2, Results!B:B, 1) -> 2796 | E2: =IF(C2=0, 0, D2/C2) -> 0.95069704 | F2: =COUNTIFS(Results!J:J, A2, Results!I:I, $F$1) -> 2181 | G2: =COUNTIFS(Results!J:J, A2, Results!B:B, 1, Results!I:I, $F$1) + COUNTIFS(Results!J:J, A2, Results!B:B, 0, Results!I:I, $F$1) -> 2023 | H2: =COUNTIFS(Results!I:I, $F$1,Results!J:J, A2, Results!B:B, 1) -> 2001 | I2: =IFERROR(H2/G2, 0) -> 0.98912506 | J2: =COUNTIFS(Results!J:J, A2, Results!I:I, "casEN") + COUNTIFS(Results!J:J, A2, Results!I:I, "casEN_opti") -> 1445 | K2: =COUNTIFS(Results!J:J, A2, Results!B:B, 1, Results!I:I, "casEN") + COUNTIFS(Results!J:J, A2, Results!B:B, 0, Results!I:I, "casEN") + COUNTIFS(Results!J:J, A2, Results!B:B, 1, Results!I:I, "casEN_opti") + COUNTIFS(Results!J:J, A2, Results!B:B, 0, Results!I:I, "casEN_opti") -> 197 | L2: =COUNTIFS(Results!I:I, "casEN",Results!J:J, A2, Results!B:B, 1) + COUNTIFS(Results!I:I, "casEN_opti",Results!J:J, A2, Results!B:B, 1) -> 139 | M2: =IFERROR(L2/K2, 0) -> 0.70558376 | N2: =(NER!$L$11+graphs_analyses!L2)/(graphs_analyses!K2 +NER!$K$11) - NER!$M$11 -> -0.0073608231 | R2: {=_xlfn._xlws.SORT( _xlfn.UNIQUE(_xlfn._xlws.FILTER(Results!J:K, (Results!J:J<>"")*(Results!K:K<>""))), 1, TRUE )} -> grfadress | S2: grftagAdresseRue | T2: =COUNTIFS(Results!J:J, R2, Results!K:K, S2) -> 75 | U2: =COUNTIFS(Results!J:J, R2,Results!K:K, S2, Results!B:B, 1) + COUNTIFS(Results!J:J, R2,Results!K:K, S2, Results!B:B, 0) -> 9 | V2: =COUNTIFS(Results!J:J, R2, Results!K:K, S2, Results!B:B, 1) -> 4 | W2: =IFERROR(V2/U2, 0) -> 0.44444444 | X2: =COUNTIFS(Results!J:J, R2, Results!K:K, S2, Results!I:I, $X$1) -> 6 | Y2: =COUNTIFS(Results!J:J, R2,Results!K:K, S2, Results!I:I, $X$1, Results!B:B, 1) + COUNTIFS(Results!J:J, R2,Results!K:K, S2,Results!I:I, $X$1, Results!B:B, 0) -> 6 | Z2: =COUNTIFS(Results!J:J, R2, Results!K:K, S2, Results!I:I, $X$1, Results!B:B, 1) -> 4 | AA2: =IFERROR(Z2/Y2, 0) -> 0.66666667 | AB2: =COUNTIFS(Results!J:J, R2,Results!K:K, S2, Results!I:I, "casEN") + COUNTIFS(Results!J:J, R2,Results!K:K, S2, Results!I:I, "casEN_opti") -> 60 | AC2: =COUNTIFS(Results!J:J, R2,Results!K:K, S2, Results!B:B, 1, Results!I:I, "casEN") + COUNTIFS(Results!J:J, R2,Results!K:K, S2, Results!B:B, 0, Results!I:I, "casEN") + COUNTIFS(Results!J:J, R2,Results!K:K, S2, Results!B:B, 1, Results!I:I, "casEN_opti") + COUNTIFS(Results!J:J, R2,Results!K:K, S2, Results!B:B, 0, Results!I:I, "casEN_opti") -> 3 | AD2: =COUNTIFS(Results!J:J, R2,Results!K:K, S2, Results!B:B, 1, Results!I:I, "casEN") + COUNTIFS(Results!J:J, R2,Results!K:K, S2, Results!B:B, 1, Results!I:I, "casEN_opti") -> 0 | AE2: =IFERROR(AD2/AC2, 0) -> 0 | AF2: =(NER!$L$11+graphs_analyses!AD2)/(graphs_analyses!AC2 +NER!$K$11) - NER!$M$11 -> -0.00041961424 | AJ2: {=_xlfn._xlws.SORT( _xlfn.UNIQUE(_xlfn._xlws.FILTER(Results!J:L, (Results!J:J<>"")*(Results!K:K<>"")*(Results!L:L<>""))), 1, TRUE )} -> grfadress | AK2: grftagZoneIndustrielle | AL2: grftagZoneIndustrielle | AM2: =COUNTIFS(Results!J:J, AJ2, Results!K:K, AK2, Results!L:L, AL2) -> 1 | AN2: =COUNTIFS(Results!J:J, AJ2, Results!K:K, AK2, Results!L:L, AL2, Results!B:B, 1) + COUNTIFS(Results!J:J, AJ2, Results!K:K, AK2, Results!L:L, AL2, Results!B:B, 0) -> 0 | AO2: =COUNTIFS(Results!J:J, AJ2, Results!K:K, AK2, Results!L:L, AL2, Results!B:B, 1) -> 0 | AP2: =IFERROR(AO2/AN2, 0) -> 0 | AQ2: =COUNTIFS(Results!J:J, AJ2, Results!K:K, AK2, Results!L:L, AL2, Results!I:I, $AQ$1) -> 0 | AR2: =COUNTIFS(Results!J:J, AJ2, Results!K:K, AK2, Results!L:L, AL2, Results!I:I, $AQ$1, Results!B:B, 1) + COUNTIFS(Results!J:J, AJ2, Results!K:K, AK2, Results!L:L, AL2, Results!I:I, $AQ$1, Results!B:B, 0) -> 0 | AS2: =COUNTIFS(Results!J:J, AJ2, Results!K:K, AK2, Results!L:L, AL2, Results!I:I, $AQ$1, Results!B:B, 1) -> 0 | AT2: =IFERROR(AS2/AR2, 0) -> 0 | AU2: =COUNTIFS(Results!J:J, AJ2,Results!K:K, AK2, Results!L:L, AL2,Results!I:I, "casEN") + COUNTIFS(Results!J:J, AJ2,Results!K:K, AK2, Results!L:L, AL2,Results!I:I, "casEN_opti") -> 1 | AV2: =COUNTIFS(Results!J:J, AJ2,Results!K:K, AK2, Results!L:L, AL2,Results!I:I, "casEN", Results!B:B, 1) + COUNTIFS(Results!J:J, AJ2,Results!K:K, AK2, Results!L:L, AL2,Results!I:I, "casEN", Results!B:B, 0) + COUNTIFS(Results!J:J, AJ2,Results!K:K, AK2, Results!L:L, AL2,Results!I:I, "casEN_opti", Results!B:B, 1) + COUNTIFS(Results!J:J, AJ2,Results!K:K, AK2, Results!L:L, AL2,Results!I:I, "casEN_opti", Results!B:B, 0) -> 0 | AW2: =COUNTIFS(Results!J:J, AJ2,Results!K:K, AK2, Results!L:L, AL2,Results!I:I, "casEN", Results!B:B, 1) + COUNTIFS(Results!J:J, AJ2,Results!K:K, AK2, Results!L:L, AL2,Results!I:I, "casEN_opti", Results!B:B, 1) -> 0 | AX2: =IFERROR(AW2/AV2, 0) -> 0 | AY2: =(NER!$L$11+graphs_analyses!AW2)/(graphs_analyses!AV2 +NER!$K$11) - NER!$M$11 -> 0
A3: grfpersPrenomNom | B3: =COUNTIF(Results!J:J, A3) -> 2359 | C3: =COUNTIFS(Results!J:J, A3, Results!B:B, 1) + COUNTIFS(Results!J:J, A3, Results!B:B, 0) -> 2354 | D3: =COUNTIFS(Results!J:J, A3, Results!B:B, 1) -> 2147 | E3: =IF(C3=0, 0, D3/C3) -> 0.91206457 | F3: =COUNTIFS(Results!J:J, A3, Results!I:I, $F$1) -> 1845 | G3: =COUNTIFS(Results!J:J, A3, Results!B:B, 1, Results!I:I, $F$1) + COUNTIFS(Results!J:J, A3, Results!B:B, 0, Results!I:I, $F$1) -> 1845 | H3: =COUNTIFS(Results!I:I, $F$1,Results!J:J, A3, Results!B:B, 1) -> 1834 | I3: =IFERROR(H3/G3, 0) -> 0.99403794 | J3: =COUNTIFS(Results!J:J, A3, Results!I:I, "casEN") + COUNTIFS(Results!J:J, A3, Results!I:I, "casEN_opti") -> 227 | K3: =COUNTIFS(Results!J:J, A3, Results!B:B, 1, Results!I:I, "casEN") + COUNTIFS(Results!J:J, A3, Results!B:B, 0, Results!I:I, "casEN") + COUNTIFS(Results!J:J, A3, Results!B:B, 1, Results!I:I, "casEN_opti") + COUNTIFS(Results!J:J, A3, Results!B:B, 0, Results!I:I, "casEN_opti") -> 222 | L3: =COUNTIFS(Results!I:I, "casEN",Results!J:J, A3, Results!B:B, 1) + COUNTIFS(Results!I:I, "casEN_opti",Results!J:J, A3, Results!B:B, 1) -> 57 | M3: =IFERROR(L3/K3, 0) -> 0.25675676 | N3: =(NER!$L$11+graphs_analyses!L3)/(graphs_analyses!K3 +NER!$K$11) - NER!$M$11 -> -0.022156951 | R3: grfadress | S3: grftagZoneIndustrielle | T3: =COUNTIFS(Results!J:J, R3, Results!K:K, S3) -> 18 | U3: =COUNTIFS(Results!J:J, R3,Results!K:K, S3, Results!B:B, 1) + COUNTIFS(Results!J:J, R3,Results!K:K, S3, Results!B:B, 0) -> 0 | V3: =COUNTIFS(Results!J:J, R3, Results!K:K, S3, Results!B:B, 1) -> 0 | W3: =IFERROR(V3/U3, 0) -> 0 | X3: =COUNTIFS(Results!J:J, R3, Results!K:K, S3, Results!I:I, $X$1) -> 0 | Y3: =COUNTIFS(Results!J:J, R3,Results!K:K, S3, Results!I:I, $X$1, Results!B:B, 1) + COUNTIFS(Results!J:J, R3,Results!K:K, S3,Results!I:I, $X$1, Results!B:B, 0) -> 0 | Z3: =COUNTIFS(Results!J:J, R3, Results!K:K, S3, Results!I:I, $X$1, Results!B:B, 1) -> 0 | AA3: =IFERROR(Z3/Y3, 0) -> 0 | AB3: =COUNTIFS(Results!J:J, R3,Results!K:K, S3, Results!I:I, "casEN") + COUNTIFS(Results!J:J, R3,Results!K:K, S3, Results!I:I, "casEN_opti") -> 18 | AC3: =COUNTIFS(Results!J:J, R3,Results!K:K, S3, Results!B:B, 1, Results!I:I, "casEN") + COUNTIFS(Results!J:J, R3,Results!K:K, S3, Results!B:B, 0, Results!I:I, "casEN") + COUNTIFS(Results!J:J, R3,Results!K:K, S3, Results!B:B, 1, Results!I:I, "casEN_opti") + COUNTIFS(Results!J:J, R3,Results!K:K, S3, Results!B:B, 0, Results!I:I, "casEN_opti") -> 0 | AD3: =COUNTIFS(Results!J:J, R3,Results!K:K, S3, Results!B:B, 1, Results!I:I, "casEN") + COUNTIFS(Results!J:J, R3,Results!K:K, S3, Results!B:B, 1, Results!I:I, "casEN_opti") -> 0 | AE3: =IFERROR(AD3/AC3, 0) -> 0 | AF3: =(NER!$L$11+graphs_analyses!AD3)/(graphs_analyses!AC3 +NER!$K$11) - NER!$M$11 -> 0 | AJ3: grforgSeule | AK3: grforgProximite | AL3: grfpersGenerique | AM3: =COUNTIFS(Results!J:J, AJ3, Results!K:K, AK3, Results!L:L, AL3) -> 7 | AN3: =COUNTIFS(Results!J:J, AJ3, Results!K:K, AK3, Results!L:L, AL3, Results!B:B, 1) + COUNTIFS(Results!J:J, AJ3, Results!K:K, AK3, Results!L:L, AL3, Results!B:B, 0) -> 5 | AO3: =COUNTIFS(Results!J:J, AJ3, Results!K:K, AK3, Results!L:L, AL3, Results!B:B, 1) -> 1 | AP3: =IFERROR(AO3/AN3, 0) -> 0.2 | AQ3: =COUNTIFS(Results!J:J, AJ3, Results!K:K, AK3, Results!L:L, AL3, Results!I:I, $AQ$1) -> 0 | AR3: =COUNTIFS(Results!J:J, AJ3, Results!K:K, AK3, Results!L:L, AL3, Results!I:I, $AQ$1, Results!B:B, 1) + COUNTIFS(Results!J:J, AJ3, Results!K:K, AK3, Results!L:L, AL3, Results!I:I, $AQ$1, Results!B:B, 0) -> 0 | AS3: =COUNTIFS(Results!J:J, AJ3, Results!K:K, AK3, Results!L:L, AL3, Results!I:I, $AQ$1, Results!B:B, 1) -> 0 | AT3: =IFERROR(AS3/AR3, 0) -> 0 | AU3: =COUNTIFS(Results!J:J, AJ3,Results!K:K, AK3, Results!L:L, AL3,Results!I:I, "casEN") + COUNTIFS(Results!J:J, AJ3,Results!K:K, AK3, Results!L:L, AL3,Results!I:I, "casEN_opti") -> 6 | AV3: =COUNTIFS(Results!J:J, AJ3,Results!K:K, AK3, Results!L:L, AL3,Results!I:I, "casEN", Results!B:B, 1) + COUNTIFS(Results!J:J, AJ3,Results!K:K, AK3, Results!L:L, AL3,Results!I:I, "casEN", Results!B:B, 0) + COUNTIFS(Results!J:J, AJ3,Results!K:K, AK3, Results!L:L, AL3,Results!I:I, "casEN_opti", Results!B:B, 1) + COUNTIFS(Results!J:J, AJ3,Results!K:K, AK3, Results!L:L, AL3,Results!I:I, "casEN_opti", Results!B:B, 0) -> 5 | AW3: =COUNTIFS(Results!J:J, AJ3,Results!K:K, AK3, Results!L:L, AL3,Results!I:I, "casEN", Results!B:B, 1) + COUNTIFS(Results!J:J, AJ3,Results!K:K, AK3, Results!L:L, AL3,Results!I:I, "casEN_opti", Results!B:B, 1) -> 1 | AX3: =IFERROR(AW3/AV3, 0) -> 0.2 | AY3: =(NER!$L$11+graphs_analyses!AW3)/(graphs_analyses!AV3 +NER!$K$11) - NER!$M$11 -> -0.0005553952
A4: grforgProximite | B4: =COUNTIF(Results!J:J, A4) -> 962 | C4: =COUNTIFS(Results!J:J, A4, Results!B:B, 1) + COUNTIFS(Results!J:J, A4, Results!B:B, 0) -> 30 | D4: =COUNTIFS(Results!J:J, A4, Results!B:B, 1) -> 8 | E4: =IF(C4=0, 0, D4/C4) -> 0.26666667 | F4: =COUNTIFS(Results!J:J, A4, Results!I:I, $F$1) -> 1 | G4: =COUNTIFS(Results!J:J, A4, Results!B:B, 1, Results!I:I, $F$1) + COUNTIFS(Results!J:J, A4, Results!B:B, 0, Results!I:I, $F$1) -> 1 | H4: =COUNTIFS(Results!I:I, $F$1,Results!J:J, A4, Results!B:B, 1) -> 0 | I4: =IFERROR(H4/G4, 0) -> 0 | J4: =COUNTIFS(Results!J:J, A4, Results!I:I, "casEN") + COUNTIFS(Results!J:J, A4, Results!I:I, "casEN_opti") -> 953 | K4: =COUNTIFS(Results!J:J, A4, Results!B:B, 1, Results!I:I, "casEN") + COUNTIFS(Results!J:J, A4, Results!B:B, 0, Results!I:I, "casEN") + COUNTIFS(Results!J:J, A4, Results!B:B, 1, Results!I:I, "casEN_opti") + COUNTIFS(Results!J:J, A4, Results!B:B, 0, Results!I:I, "casEN_opti") -> 22 | L4: =COUNTIFS(Results!I:I, "casEN",Results!J:J, A4, Results!B:B, 1) + COUNTIFS(Results!I:I, "casEN_opti",Results!J:J, A4, Results!B:B, 1) -> 5 | M4: =IFERROR(L4/K4, 0) -> 0.22727273 | N4: =(NER!$L$11+graphs_analyses!L4)/(graphs_analyses!K4 +NER!$K$11) - NER!$M$11 -> -0.0023517349 | R4: grfgeog | S4: grftoolPolylexicalOrgPlace | T4: =COUNTIFS(Results!J:J, R4, Results!K:K, S4) -> 40 | U4: =COUNTIFS(Results!J:J, R4,Results!K:K, S4, Results!B:B, 1) + COUNTIFS(Results!J:J, R4,Results!K:K, S4, Results!B:B, 0) -> 40 | V4: =COUNTIFS(Results!J:J, R4, Results!K:K, S4, Results!B:B, 1) -> 40 | W4: =IFERROR(V4/U4, 0) -> 1 | X4: =COUNTIFS(Results!J:J, R4, Results!K:K, S4, Results!I:I, $X$1) -> 35 | Y4: =COUNTIFS(Results!J:J, R4,Results!K:K, S4, Results!I:I, $X$1, Results!B:B, 1) + COUNTIFS(Results!J:J, R4,Results!K:K, S4,Results!I:I, $X$1, Results!B:B, 0) -> 35 | Z4: =COUNTIFS(Results!J:J, R4, Results!K:K, S4, Results!I:I, $X$1, Results!B:B, 1) -> 35 | AA4: =IFERROR(Z4/Y4, 0) -> 1 | AB4: =COUNTIFS(Results!J:J, R4,Results!K:K, S4, Results!I:I, "casEN") + COUNTIFS(Results!J:J, R4,Results!K:K, S4, Results!I:I, "casEN_opti") -> 3 | AC4: =COUNTIFS(Results!J:J, R4,Results!K:K, S4, Results!B:B, 1, Results!I:I, "casEN") + COUNTIFS(Results!J:J, R4,Results!K:K, S4, Results!B:B, 0, Results!I:I, "casEN") + COUNTIFS(Results!J:J, R4,Results!K:K, S4, Results!B:B, 1, Results!I:I, "casEN_opti") + COUNTIFS(Results!J:J, R4,Results!K:K, S4, Results!B:B, 0, Results!I:I, "casEN_opti") -> 3 | AD4: =COUNTIFS(Results!J:J, R4,Results!K:K, S4, Results!B:B, 1, Results!I:I, "casEN") + COUNTIFS(Results!J:J, R4,Results!K:K, S4, Results!B:B, 1, Results!I:I, "casEN_opti") -> 3 | AE4: =IFERROR(AD4/AC4, 0) -> 1 | AF4: =(NER!$L$11+graphs_analyses!AD4)/(graphs_analyses!AC4 +NER!$K$11) - NER!$M$11 -> 1.1792147e-05 | AJ4: grforgSeule | AK4: grforgArmee | AL4: grfpersPrenomNom | AM4: =COUNTIFS(Results!J:J, AJ4, Results!K:K, AK4, Results!L:L, AL4) -> 1 | AN4: =COUNTIFS(Results!J:J, AJ4, Results!K:K, AK4, Results!L:L, AL4, Results!B:B, 1) + COUNTIFS(Results!J:J, AJ4, Results!K:K, AK4, Results!L:L, AL4, Results!B:B, 0) -> 1 | AO4: =COUNTIFS(Results!J:J, AJ4, Results!K:K, AK4, Results!L:L, AL4, Results!B:B, 1) -> 1 | AP4: =IFERROR(AO4/AN4, 0) -> 1 | AQ4: =COUNTIFS(Results!J:J, AJ4, Results!K:K, AK4, Results!L:L, AL4, Results!I:I, $AQ$1) -> 0 | AR4: =COUNTIFS(Results!J:J, AJ4, Results!K:K, AK4, Results!L:L, AL4, Results!I:I, $AQ$1, Results!B:B, 1) + COUNTIFS(Results!J:J, AJ4, Results!K:K, AK4, Results!L:L, AL4, Results!I:I, $AQ$1, Results!B:B, 0) -> 0 | AS4: =COUNTIFS(Results!J:J, AJ4, Results!K:K, AK4, Results!L:L, AL4, Results!I:I, $AQ$1, Results!B:B, 1) -> 0 | AT4: =IFERROR(AS4/AR4, 0) -> 0 | AU4: =COUNTIFS(Results!J:J, AJ4,Results!K:K, AK4, Results!L:L, AL4,Results!I:I, "casEN") + COUNTIFS(Results!J:J, AJ4,Results!K:K, AK4, Results!L:L, AL4,Results!I:I, "casEN_opti") -> 1 | AV4: =COUNTIFS(Results!J:J, AJ4,Results!K:K, AK4, Results!L:L, AL4,Results!I:I, "casEN", Results!B:B, 1) + COUNTIFS(Results!J:J, AJ4,Results!K:K, AK4, Results!L:L, AL4,Results!I:I, "casEN", Results!B:B, 0) + COUNTIFS(Results!J:J, AJ4,Results!K:K, AK4, Results!L:L, AL4,Results!I:I, "casEN_opti", Results!B:B, 1) + COUNTIFS(Results!J:J, AJ4,Results!K:K, AK4, Results!L:L, AL4,Results!I:I, "casEN_opti", Results!B:B, 0) -> 1 | AW4: =COUNTIFS(Results!J:J, AJ4,Results!K:K, AK4, Results!L:L, AL4,Results!I:I, "casEN", Results!B:B, 1) + COUNTIFS(Results!J:J, AJ4,Results!K:K, AK4, Results!L:L, AL4,Results!I:I, "casEN_opti", Results!B:B, 1) -> 1 | AX4: =IFERROR(AW4/AV4, 0) -> 1 | AY4: =(NER!$L$11+graphs_analyses!AW4)/(graphs_analyses!AV4 +NER!$K$11) - NER!$M$11 -> 3.9318464e-06
A5: grforgSeule | B5: =COUNTIF(Results!J:J, A5) -> 240 | C5: =COUNTIFS(Results!J:J, A5, Results!B:B, 1) + COUNTIFS(Results!J:J, A5, Results!B:B, 0) -> 196 | D5: =COUNTIFS(Results!J:J, A5, Results!B:B, 1) -> 116 | E5: =IF(C5=0, 0, D5/C5) -> 0.59183673 | F5: =COUNTIFS(Results!J:J, A5, Results!I:I, $F$1) -> 12 | G5: =COUNTIFS(Results!J:J, A5, Results!B:B, 1, Results!I:I, $F$1) + COUNTIFS(Results!J:J, A5, Results!B:B, 0, Results!I:I, $F$1) -> 12 | H5: =COUNTIFS(Results!I:I, $F$1,Results!J:J, A5, Results!B:B, 1) -> 12 | I5: =IFERROR(H5/G5, 0) -> 1 | J5: =COUNTIFS(Results!J:J, A5, Results!I:I, "casEN") + COUNTIFS(Results!J:J, A5, Results!I:I, "casEN_opti") -> 218 | K5: =COUNTIFS(Results!J:J, A5, Results!B:B, 1, Results!I:I, "casEN") + COUNTIFS(Results!J:J, A5, Results!B:B, 0, Results!I:I, "casEN") + COUNTIFS(Results!J:J, A5, Results!B:B, 1, Results!I:I, "casEN_opti") + COUNTIFS(Results!J:J, A5, Results!B:B, 0, Results!I:I, "casEN_opti") -> 177 | L5: =COUNTIFS(Results!I:I, "casEN",Results!J:J, A5, Results!B:B, 1) + COUNTIFS(Results!I:I, "casEN_opti",Results!J:J, A5, Results!B:B, 1) -> 99 | M5: =IFERROR(L5/K5, 0) -> 0.55932203 | N5: =(NER!$L$11+graphs_analyses!L5)/(graphs_analyses!K5 +NER!$K$11) - NER!$M$11 -> -0.010264008 | R5: grfgeog | S5: grforgPlaceGeoPolitique | T5: =COUNTIFS(Results!J:J, R5, Results!K:K, S5) -> 32 | U5: =COUNTIFS(Results!J:J, R5,Results!K:K, S5, Results!B:B, 1) + COUNTIFS(Results!J:J, R5,Results!K:K, S5, Results!B:B, 0) -> 23 | V5: =COUNTIFS(Results!J:J, R5, Results!K:K, S5, Results!B:B, 1) -> 23 | W5: =IFERROR(V5/U5, 0) -> 1 | X5: =COUNTIFS(Results!J:J, R5, Results!K:K, S5, Results!I:I, $X$1) -> 0 | Y5: =COUNTIFS(Results!J:J, R5,Results!K:K, S5, Results!I:I, $X$1, Results!B:B, 1) + COUNTIFS(Results!J:J, R5,Results!K:K, S5,Results!I:I, $X$1, Results!B:B, 0) -> 0 | Z5: =COUNTIFS(Results!J:J, R5, Results!K:K, S5, Results!I:I, $X$1, Results!B:B, 1) -> 0 | AA5: =IFERROR(Z5/Y5, 0) -> 0 | AB5: =COUNTIFS(Results!J:J, R5,Results!K:K, S5, Results!I:I, "casEN") + COUNTIFS(Results!J:J, R5,Results!K:K, S5, Results!I:I, "casEN_opti") -> 30 | AC5: =COUNTIFS(Results!J:J, R5,Results!K:K, S5, Results!B:B, 1, Results!I:I, "casEN") + COUNTIFS(Results!J:J, R5,Results!K:K, S5, Results!B:B, 0, Results!I:I, "casEN") + COUNTIFS(Results!J:J, R5,Results!K:K, S5, Results!B:B, 1, Results!I:I, "casEN_opti") + COUNTIFS(Results!J:J, R5,Results!K:K, S5, Results!B:B, 0, Results!I:I, "casEN_opti") -> 21 | AD5: =COUNTIFS(Results!J:J, R5,Results!K:K, S5, Results!B:B, 1, Results!I:I, "casEN") + COUNTIFS(Results!J:J, R5,Results!K:K, S5, Results!B:B, 1, Results!I:I, "casEN_opti") -> 21 | AE5: =IFERROR(AD5/AC5, 0) -> 1 | AF5: =(NER!$L$11+graphs_analyses!AD5)/(graphs_analyses!AC5 +NER!$K$11) - NER!$M$11 -> 8.2331917e-05 | AJ5: grforgSeule | AK5: grforgFinance | AL5: grfpersPrenomNom | AM5: =COUNTIFS(Results!J:J, AJ5, Results!K:K, AK5, Results!L:L, AL5) -> 1 | AN5: =COUNTIFS(Results!J:J, AJ5, Results!K:K, AK5, Results!L:L, AL5, Results!B:B, 1) + COUNTIFS(Results!J:J, AJ5, Results!K:K, AK5, Results!L:L, AL5, Results!B:B, 0) -> 1 | AO5: =COUNTIFS(Results!J:J, AJ5, Results!K:K, AK5, Results!L:L, AL5, Results!B:B, 1) -> 0 | AP5: =IFERROR(AO5/AN5, 0) -> 0 | AQ5: =COUNTIFS(Results!J:J, AJ5, Results!K:K, AK5, Results!L:L, AL5, Results!I:I, $AQ$1) -> 0 | AR5: =COUNTIFS(Results!J:J, AJ5, Results!K:K, AK5, Results!L:L, AL5, Results!I:I, $AQ$1, Results!B:B, 1) + COUNTIFS(Results!J:J, AJ5, Results!K:K, AK5, Results!L:L, AL5, Results!I:I, $AQ$1, Results!B:B, 0) -> 0 | AS5: =COUNTIFS(Results!J:J, AJ5, Results!K:K, AK5, Results!L:L, AL5, Results!I:I, $AQ$1, Results!B:B, 1) -> 0 | AT5: =IFERROR(AS5/AR5, 0) -> 0 | AU5: =COUNTIFS(Results!J:J, AJ5,Results!K:K, AK5, Results!L:L, AL5,Results!I:I, "casEN") + COUNTIFS(Results!J:J, AJ5,Results!K:K, AK5, Results!L:L, AL5,Results!I:I, "casEN_opti") -> 1 | AV5: =COUNTIFS(Results!J:J, AJ5,Results!K:K, AK5, Results!L:L, AL5,Results!I:I, "casEN", Results!B:B, 1) + COUNTIFS(Results!J:J, AJ5,Results!K:K, AK5, Results!L:L, AL5,Results!I:I, "casEN", Results!B:B, 0) + COUNTIFS(Results!J:J, AJ5,Results!K:K, AK5, Results!L:L, AL5,Results!I:I, "casEN_opti", Results!B:B, 1) + COUNTIFS(Results!J:J, AJ5,Results!K:K, AK5, Results!L:L, AL5,Results!I:I, "casEN_opti", Results!B:B, 0) -> 1 | AW5: =COUNTIFS(Results!J:J, AJ5,Results!K:K, AK5, Results!L:L, AL5,Results!I:I, "casEN", Results!B:B, 1) + COUNTIFS(Results!J:J, AJ5,Results!K:K, AK5, Results!L:L, AL5,Results!I:I, "casEN_opti", Results!B:B, 1) -> 0 | AX5: =IFERROR(AW5/AV5, 0) -> 0 | AY5: =(NER!$L$11+graphs_analyses!AW5)/(graphs_analyses!AV5 +NER!$K$11) - NER!$M$11 -> -0.00013991165
A6: grfpersContextePersonne | B6: =COUNTIF(Results!J:J, A6) -> 324 | C6: =COUNTIFS(Results!J:J, A6, Results!B:B, 1) + COUNTIFS(Results!J:J, A6, Results!B:B, 0) -> 324 | D6: =COUNTIFS(Results!J:J, A6, Results!B:B, 1) -> 305 | E6: =IF(C6=0, 0, D6/C6) -> 0.94135802 | F6: =COUNTIFS(Results!J:J, A6, Results!I:I, $F$1) -> 157 | G6: =COUNTIFS(Results!J:J, A6, Results!B:B, 1, Results!I:I, $F$1) + COUNTIFS(Results!J:J, A6, Results!B:B, 0, Results!I:I, $F$1) -> 157 | H6: =COUNTIFS(Results!I:I, $F$1,Results!J:J, A6, Results!B:B, 1) -> 156 | I6: =IFERROR(H6/G6, 0) -> 0.99363057 | J6: =COUNTIFS(Results!J:J, A6, Results!I:I, "casEN") + COUNTIFS(Results!J:J, A6, Results!I:I, "casEN_opti") -> 49 | K6: =COUNTIFS(Results!J:J, A6, Results!B:B, 1, Results!I:I, "casEN") + COUNTIFS(Results!J:J, A6, Results!B:B, 0, Results!I:I, "casEN") + COUNTIFS(Results!J:J, A6, Results!B:B, 1, Results!I:I, "casEN_opti") + COUNTIFS(Results!J:J, A6, Results!B:B, 0, Results!I:I, "casEN_opti") -> 49 | L6: =COUNTIFS(Results!I:I, "casEN",Results!J:J, A6, Results!B:B, 1) + COUNTIFS(Results!I:I, "casEN_opti",Results!J:J, A6, Results!B:B, 1) -> 37 | M6: =IFERROR(L6/K6, 0) -> 0.75510204 | N6: =(NER!$L$11+graphs_analyses!L6)/(graphs_analyses!K6 +NER!$K$11) - NER!$M$11 -> -0.0015229463 | R6: grfGeogPlaceGenerique | S6: grfgeogRiviere | T6: =COUNTIFS(Results!J:J, R6, Results!K:K, S6) -> 18 | U6: =COUNTIFS(Results!J:J, R6,Results!K:K, S6, Results!B:B, 1) + COUNTIFS(Results!J:J, R6,Results!K:K, S6, Results!B:B, 0) -> 11 | V6: =COUNTIFS(Results!J:J, R6, Results!K:K, S6, Results!B:B, 1) -> 11 | W6: =IFERROR(V6/U6, 0) -> 1 | X6: =COUNTIFS(Results!J:J, R6, Results!K:K, S6, Results!I:I, $X$1) -> 10 | Y6: =COUNTIFS(Results!J:J, R6,Results!K:K, S6, Results!I:I, $X$1, Results!B:B, 1) + COUNTIFS(Results!J:J, R6,Results!K:K, S6,Results!I:I, $X$1, Results!B:B, 0) -> 10 | Z6: =COUNTIFS(Results!J:J, R6, Results!K:K, S6, Results!I:I, $X$1, Results!B:B, 1) -> 10 | AA6: =IFERROR(Z6/Y6, 0) -> 1 | AB6: =COUNTIFS(Results!J:J, R6,Results!K:K, S6, Results!I:I, "casEN") + COUNTIFS(Results!J:J, R6,Results!K:K, S6, Results!I:I, "casEN_opti") -> 6 | AC6: =COUNTIFS(Results!J:J, R6,Results!K:K, S6, Results!B:B, 1, Results!I:I, "casEN") + COUNTIFS(Results!J:J, R6,Results!K:K, S6, Results!B:B, 0, Results!I:I, "casEN") + COUNTIFS(Results!J:J, R6,Results!K:K, S6, Results!B:B, 1, Results!I:I, "casEN_opti") + COUNTIFS(Results!J:J, R6,Results!K:K, S6, Results!B:B, 0, Results!I:I, "casEN_opti") -> 0 | AD6: =COUNTIFS(Results!J:J, R6,Results!K:K, S6, Results!B:B, 1, Results!I:I, "casEN") + COUNTIFS(Results!J:J, R6,Results!K:K, S6, Results!B:B, 1, Results!I:I, "casEN_opti") -> 0 | AE6: =IFERROR(AD6/AC6, 0) -> 0 | AF6: =(NER!$L$11+graphs_analyses!AD6)/(graphs_analyses!AC6 +NER!$K$11) - NER!$M$11 -> 0 | AJ6: grforgSeule | AK6: grforgProximite | AL6: grfpersPrenomNom | AM6: =COUNTIFS(Results!J:J, AJ6, Results!K:K, AK6, Results!L:L, AL6) -> 3 | AN6: =COUNTIFS(Results!J:J, AJ6, Results!K:K, AK6, Results!L:L, AL6, Results!B:B, 1) + COUNTIFS(Results!J:J, AJ6, Results!K:K, AK6, Results!L:L, AL6, Results!B:B, 0) -> 3 | AO6: =COUNTIFS(Results!J:J, AJ6, Results!K:K, AK6, Results!L:L, AL6, Results!B:B, 1) -> 1 | AP6: =IFERROR(AO6/AN6, 0) -> 0.33333333 | AQ6: =COUNTIFS(Results!J:J, AJ6, Results!K:K, AK6, Results!L:L, AL6, Results!I:I, $AQ$1) -> 0 | AR6: =COUNTIFS(Results!J:J, AJ6, Results!K:K, AK6, Results!L:L, AL6, Results!I:I, $AQ$1, Results!B:B, 1) + COUNTIFS(Results!J:J, AJ6, Results!K:K, AK6, Results!L:L, AL6, Results!I:I, $AQ$1, Results!B:B, 0) -> 0 | AS6: =COUNTIFS(Results!J:J, AJ6, Results!K:K, AK6, Results!L:L, AL6, Results!I:I, $AQ$1, Results!B:B, 1) -> 0 | AT6: =IFERROR(AS6/AR6, 0) -> 0 | AU6: =COUNTIFS(Results!J:J, AJ6,Results!K:K, AK6, Results!L:L, AL6,Results!I:I, "casEN") + COUNTIFS(Results!J:J, AJ6,Results!K:K, AK6, Results!L:L, AL6,Results!I:I, "casEN_opti") -> 3 | AV6: =COUNTIFS(Results!J:J, AJ6,Results!K:K, AK6, Results!L:L, AL6,Results!I:I, "casEN", Results!B:B, 1) + COUNTIFS(Results!J:J, AJ6,Results!K:K, AK6, Results!L:L, AL6,Results!I:I, "casEN", Results!B:B, 0) + COUNTIFS(Results!J:J, AJ6,Results!K:K, AK6, Results!L:L, AL6,Results!I:I, "casEN_opti", Results!B:B, 1) + COUNTIFS(Results!J:J, AJ6,Results!K:K, AK6, Results!L:L, AL6,Results!I:I, "casEN_opti", Results!B:B, 0) -> 3 | AW6: =COUNTIFS(Results!J:J, AJ6,Results!K:K, AK6, Results!L:L, AL6,Results!I:I, "casEN", Results!B:B, 1) + COUNTIFS(Results!J:J, AJ6,Results!K:K, AK6, Results!L:L, AL6,Results!I:I, "casEN_opti", Results!B:B, 1) -> 1 | AX6: =IFERROR(AW6/AV6, 0) -> 0.33333333 | AY6: =(NER!$L$11+graphs_analyses!AW6)/(graphs_analyses!AV6 +NER!$K$11) - NER!$M$11 -> -0.00027581211
A7: grfpersAmbigus | B7: =COUNTIF(Results!J:J, A7) -> 4 | C7: =COUNTIFS(Results!J:J, A7, Results!B:B, 1) + COUNTIFS(Results!J:J, A7, Results!B:B, 0) -> 4 | D7: =COUNTIFS(Results!J:J, A7, Results!B:B, 1) -> 4 | E7: =IF(C7=0, 0, D7/C7) -> 1 | F7: =COUNTIFS(Results!J:J, A7, Results!I:I, $F$1) -> 1 | G7: =COUNTIFS(Results!J:J, A7, Results!B:B, 1, Results!I:I, $F$1) + COUNTIFS(Results!J:J, A7, Results!B:B, 0, Results!I:I, $F$1) -> 1 | H7: =COUNTIFS(Results!I:I, $F$1,Results!J:J, A7, Results!B:B, 1) -> 1 | I7: =IFERROR(H7/G7, 0) -> 1 | J7: =COUNTIFS(Results!J:J, A7, Results!I:I, "casEN") + COUNTIFS(Results!J:J, A7, Results!I:I, "casEN_opti") -> 3 | K7: =COUNTIFS(Results!J:J, A7, Results!B:B, 1, Results!I:I, "casEN") + COUNTIFS(Results!J:J, A7, Results!B:B, 0, Results!I:I, "casEN") + COUNTIFS(Results!J:J, A7, Results!B:B, 1, Results!I:I, "casEN_opti") + COUNTIFS(Results!J:J, A7, Results!B:B, 0, Results!I:I, "casEN_opti") -> 3 | L7: =COUNTIFS(Results!I:I, "casEN",Results!J:J, A7, Results!B:B, 1) + COUNTIFS(Results!I:I, "casEN_opti",Results!J:J, A7, Results!B:B, 1) -> 3 | M7: =IFERROR(L7/K7, 0) -> 1 | N7: =(NER!$L$11+graphs_analyses!L7)/(graphs_analyses!K7 +NER!$K$11) - NER!$M$11 -> 1.1792147e-05 | R7: grfGeogPlaceGenerique | S7: grfgeogMer | T7: =COUNTIFS(Results!J:J, R7, Results!K:K, S7) -> 2 | U7: =COUNTIFS(Results!J:J, R7,Results!K:K, S7, Results!B:B, 1) + COUNTIFS(Results!J:J, R7,Results!K:K, S7, Results!B:B, 0) -> 0 | V7: =COUNTIFS(Results!J:J, R7, Results!K:K, S7, Results!B:B, 1) -> 0 | W7: =IFERROR(V7/U7, 0) -> 0 | X7: =COUNTIFS(Results!J:J, R7, Results!K:K, S7, Results!I:I, $X$1) -> 0 | Y7: =COUNTIFS(Results!J:J, R7,Results!K:K, S7, Results!I:I, $X$1, Results!B:B, 1) + COUNTIFS(Results!J:J, R7,Results!K:K, S7,Results!I:I, $X$1, Results!B:B, 0) -> 0 | Z7: =COUNTIFS(Results!J:J, R7, Results!K:K, S7, Results!I:I, $X$1, Results!B:B, 1) -> 0 | AA7: =IFERROR(Z7/Y7, 0) -> 0 | AB7: =COUNTIFS(Results!J:J, R7,Results!K:K, S7, Results!I:I, "casEN") + COUNTIFS(Results!J:J, R7,Results!K:K, S7, Results!I:I, "casEN_opti") -> 1 | AC7: =COUNTIFS(Results!J:J, R7,Results!K:K, S7, Results!B:B, 1, Results!I:I, "casEN") + COUNTIFS(Results!J:J, R7,Results!K:K, S7, Results!B:B, 0, Results!I:I, "casEN") + COUNTIFS(Results!J:J, R7,Results!K:K, S7, Results!B:B, 1, Results!I:I, "casEN_opti") + COUNTIFS(Results!J:J, R7,Results!K:K, S7, Results!B:B, 0, Results!I:I, "casEN_opti") -> 0 | AD7: =COUNTIFS(Results!J:J, R7,Results!K:K, S7, Results!B:B, 1, Results!I:I, "casEN") + COUNTIFS(Results!J:J, R7,Results!K:K, S7, Results!B:B, 1, Results!I:I, "casEN_opti") -> 0 | AE7: =IFERROR(AD7/AC7, 0) -> 0 | AF7: =(NER!$L$11+graphs_analyses!AD7)/(graphs_analyses!AC7 +NER!$K$11) - NER!$M$11 -> 0 | AJ7: grforgSeule | AK7: grforgPolice | AL7: grfpersPrenomNom | AM7: =COUNTIFS(Results!J:J, AJ7, Results!K:K, AK7, Results!L:L, AL7) -> 1 | AN7: =COUNTIFS(Results!J:J, AJ7, Results!K:K, AK7, Results!L:L, AL7, Results!B:B, 1) + COUNTIFS(Results!J:J, AJ7, Results!K:K, AK7, Results!L:L, AL7, Results!B:B, 0) -> 1 | AO7: =COUNTIFS(Results!J:J, AJ7, Results!K:K, AK7, Results!L:L, AL7, Results!B:B, 1) -> 0 | AP7: =IFERROR(AO7/AN7, 0) -> 0 | AQ7: =COUNTIFS(Results!J:J, AJ7, Results!K:K, AK7, Results!L:L, AL7, Results!I:I, $AQ$1) -> 0 | AR7: =COUNTIFS(Results!J:J, AJ7, Results!K:K, AK7, Results!L:L, AL7, Results!I:I, $AQ$1, Results!B:B, 1) + COUNTIFS(Results!J:J, AJ7, Results!K:K, AK7, Results!L:L, AL7, Results!I:I, $AQ$1, Results!B:B, 0) -> 0 | AS7: =COUNTIFS(Results!J:J, AJ7, Results!K:K, AK7, Results!L:L, AL7, Results!I:I, $AQ$1, Results!B:B, 1) -> 0 | AT7: =IFERROR(AS7/AR7, 0) -> 0 | AU7: =COUNTIFS(Results!J:J, AJ7,Results!K:K, AK7, Results!L:L, AL7,Results!I:I, "casEN") + COUNTIFS(Results!J:J, AJ7,Results!K:K, AK7, Results!L:L, AL7,Results!I:I, "casEN_opti") -> 1 | AV7: =COUNTIFS(Results!J:J, AJ7,Results!K:K, AK7, Results!L:L, AL7,Results!I:I, "casEN", Results!B:B, 1) + COUNTIFS(Results!J:J, AJ7,Results!K:K, AK7, Results!L:L, AL7,Results!I:I, "casEN", Results!B:B, 0) + COUNTIFS(Results!J:J, AJ7,Results!K:K, AK7, Results!L:L, AL7,Results!I:I, "casEN_opti", Results!B:B, 1) + COUNTIFS(Results!J:J, AJ7,Results!K:K, AK7, Results!L:L, AL7,Results!I:I, "casEN_opti", Results!B:B, 0) -> 1 | AW7: =COUNTIFS(Results!J:J, AJ7,Results!K:K, AK7, Results!L:L, AL7,Results!I:I, "casEN", Results!B:B, 1) + COUNTIFS(Results!J:J, AJ7,Results!K:K, AK7, Results!L:L, AL7,Results!I:I, "casEN_opti", Results!B:B, 1) -> 0 | AX7: =IFERROR(AW7/AV7, 0) -> 0 | AY7: =(NER!$L$11+graphs_analyses!AW7)/(graphs_analyses!AV7 +NER!$K$11) - NER!$M$11 -> -0.00013991165
A8: grforgPolice | B8: =COUNTIF(Results!J:J, A8) -> 71 | C8: =COUNTIFS(Results!J:J, A8, Results!B:B, 1) + COUNTIFS(Results!J:J, A8, Results!B:B, 0) -> 11 | D8: =COUNTIFS(Results!J:J, A8, Results!B:B, 1) -> 10 | E8: =IF(C8=0, 0, D8/C8) -> 0.90909091 | F8: =COUNTIFS(Results!J:J, A8, Results!I:I, $F$1) -> 1 | G8: =COUNTIFS(Results!J:J, A8, Results!B:B, 1, Results!I:I, $F$1) + COUNTIFS(Results!J:J, A8, Results!B:B, 0, Results!I:I, $F$1) -> 1 | H8: =COUNTIFS(Results!I:I, $F$1,Results!J:J, A8, Results!B:B, 1) -> 1 | I8: =IFERROR(H8/G8, 0) -> 1 | J8: =COUNTIFS(Results!J:J, A8, Results!I:I, "casEN") + COUNTIFS(Results!J:J, A8, Results!I:I, "casEN_opti") -> 69 | K8: =COUNTIFS(Results!J:J, A8, Results!B:B, 1, Results!I:I, "casEN") + COUNTIFS(Results!J:J, A8, Results!B:B, 0, Results!I:I, "casEN") + COUNTIFS(Results!J:J, A8, Results!B:B, 1, Results!I:I, "casEN_opti") + COUNTIFS(Results!J:J, A8, Results!B:B, 0, Results!I:I, "casEN_opti") -> 9 | L8: =COUNTIFS(Results!I:I, "casEN",Results!J:J, A8, Results!B:B, 1) + COUNTIFS(Results!I:I, "casEN_opti",Results!J:J, A8, Results!B:B, 1) -> 9 | M8: =IFERROR(L8/K8, 0) -> 1 | N8: =(NER!$L$11+graphs_analyses!L8)/(graphs_analyses!K8 +NER!$K$11) - NER!$M$11 -> 3.5345944e-05 | R8: grfGeogPlaceGenerique | S8: grfgeogPhysique | T8: =COUNTIFS(Results!J:J, R8, Results!K:K, S8) -> 6 | U8: =COUNTIFS(Results!J:J, R8,Results!K:K, S8, Results!B:B, 1) + COUNTIFS(Results!J:J, R8,Results!K:K, S8, Results!B:B, 0) -> 3 | V8: =COUNTIFS(Results!J:J, R8, Results!K:K, S8, Results!B:B, 1) -> 3 | W8: =IFERROR(V8/U8, 0) -> 1 | X8: =COUNTIFS(Results!J:J, R8, Results!K:K, S8, Results!I:I, $X$1) -> 5 | Y8: =COUNTIFS(Results!J:J, R8,Results!K:K, S8, Results!I:I, $X$1, Results!B:B, 1) + COUNTIFS(Results!J:J, R8,Results!K:K, S8,Results!I:I, $X$1, Results!B:B, 0) -> 3 | Z8: =COUNTIFS(Results!J:J, R8, Results!K:K, S8, Results!I:I, $X$1, Results!B:B, 1) -> 3 | AA8: =IFERROR(Z8/Y8, 0) -> 1 | AB8: =COUNTIFS(Results!J:J, R8,Results!K:K, S8, Results!I:I, "casEN") + COUNTIFS(Results!J:J, R8,Results!K:K, S8, Results!I:I, "casEN_opti") -> 1 | AC8: =COUNTIFS(Results!J:J, R8,Results!K:K, S8, Results!B:B, 1, Results!I:I, "casEN") + COUNTIFS(Results!J:J, R8,Results!K:K, S8, Results!B:B, 0, Results!I:I, "casEN") + COUNTIFS(Results!J:J, R8,Results!K:K, S8, Results!B:B, 1, Results!I:I, "casEN_opti") + COUNTIFS(Results!J:J, R8,Results!K:K, S8, Results!B:B, 0, Results!I:I, "casEN_opti") -> 0 | AD8: =COUNTIFS(Results!J:J, R8,Results!K:K, S8, Results!B:B, 1, Results!I:I, "casEN") + COUNTIFS(Results!J:J, R8,Results!K:K, S8, Results!B:B, 1, Results!I:I, "casEN_opti") -> 0 | AE8: =IFERROR(AD8/AC8, 0) -> 0 | AF8: =(NER!$L$11+graphs_analyses!AD8)/(graphs_analyses!AC8 +NER!$K$11) - NER!$M$11 -> 0 | AJ8: grforgSeule | AK8: grforgAssemblee | AL8: grfpersGenerique | AM8: =COUNTIFS(Results!J:J, AJ8, Results!K:K, AK8, Results!L:L, AL8) -> 1 | AN8: =COUNTIFS(Results!J:J, AJ8, Results!K:K, AK8, Results!L:L, AL8, Results!B:B, 1) + COUNTIFS(Results!J:J, AJ8, Results!K:K, AK8, Results!L:L, AL8, Results!B:B, 0) -> 1 | AO8: =COUNTIFS(Results!J:J, AJ8, Results!K:K, AK8, Results!L:L, AL8, Results!B:B, 1) -> 1 | AP8: =IFERROR(AO8/AN8, 0) -> 1 | AQ8: =COUNTIFS(Results!J:J, AJ8, Results!K:K, AK8, Results!L:L, AL8, Results!I:I, $AQ$1) -> 0 | AR8: =COUNTIFS(Results!J:J, AJ8, Results!K:K, AK8, Results!L:L, AL8, Results!I:I, $AQ$1, Results!B:B, 1) + COUNTIFS(Results!J:J, AJ8, Results!K:K, AK8, Results!L:L, AL8, Results!I:I, $AQ$1, Results!B:B, 0) -> 0 | AS8: =COUNTIFS(Results!J:J, AJ8, Results!K:K, AK8, Results!L:L, AL8, Results!I:I, $AQ$1, Results!B:B, 1) -> 0 | AT8: =IFERROR(AS8/AR8, 0) -> 0 | AU8: =COUNTIFS(Results!J:J, AJ8,Results!K:K, AK8, Results!L:L, AL8,Results!I:I, "casEN") + COUNTIFS(Results!J:J, AJ8,Results!K:K, AK8, Results!L:L, AL8,Results!I:I, "casEN_opti") -> 1 | AV8: =COUNTIFS(Results!J:J, AJ8,Results!K:K, AK8, Results!L:L, AL8,Results!I:I, "casEN", Results!B:B, 1) + COUNTIFS(Results!J:J, AJ8,Results!K:K, AK8, Results!L:L, AL8,Results!I:I, "casEN", Results!B:B, 0) + COUNTIFS(Results!J:J, AJ8,Results!K:K, AK8, Results!L:L, AL8,Results!I:I, "casEN_opti", Results!B:B, 1) + COUNTIFS(Results!J:J, AJ8,Results!K:K, AK8, Results!L:L, AL8,Results!I:I, "casEN_opti", Results!B:B, 0) -> 1 | AW8: =COUNTIFS(Results!J:J, AJ8,Results!K:K, AK8, Results!L:L, AL8,Results!I:I, "casEN", Results!B:B, 1) + COUNTIFS(Results!J:J, AJ8,Results!K:K, AK8, Results!L:L, AL8,Results!I:I, "casEN_opti", Results!B:B, 1) -> 1 | AX8: =IFERROR(AW8/AV8, 0) -> 1 | AY8: =(NER!$L$11+graphs_analyses!AW8)/(graphs_analyses!AV8 +NER!$K$11) - NER!$M$11 -> 3.9318464e-06
A9: grfplaceBatiment | B9: =COUNTIF(Results!J:J, A9) -> 754 | C9: =COUNTIFS(Results!J:J, A9, Results!B:B, 1) + COUNTIFS(Results!J:J, A9, Results!B:B, 0) -> 5 | D9: =COUNTIFS(Results!J:J, A9, Results!B:B, 1) -> 0 | E9: =IF(C9=0, 0, D9/C9) -> 0 | F9: =COUNTIFS(Results!J:J, A9, Results!I:I, $F$1) -> 0 | G9: =COUNTIFS(Results!J:J, A9, Results!B:B, 1, Results!I:I, $F$1) + COUNTIFS(Results!J:J, A9, Results!B:B, 0, Results!I:I, $F$1) -> 0 | H9: =COUNTIFS(Results!I:I, $F$1,Results!J:J, A9, Results!B:B, 1) -> 0 | I9: =IFERROR(H9/G9, 0) -> 0 | J9: =COUNTIFS(Results!J:J, A9, Results!I:I, "casEN") + COUNTIFS(Results!J:J, A9, Results!I:I, "casEN_opti") -> 751 | K9: =COUNTIFS(Results!J:J, A9, Results!B:B, 1, Results!I:I, "casEN") + COUNTIFS(Results!J:J, A9, Results!B:B, 0, Results!I:I, "casEN") + COUNTIFS(Results!J:J, A9, Results!B:B, 1, Results!I:I, "casEN_opti") + COUNTIFS(Results!J:J, A9, Results!B:B, 0, Results!I:I, "casEN_opti") -> 4 | L9: =COUNTIFS(Results!I:I, "casEN",Results!J:J, A9, Results!B:B, 1) + COUNTIFS(Results!I:I, "casEN_opti",Results!J:J, A9, Results!B:B, 1) -> 0 | M9: =IFERROR(L9/K9, 0) -> 0 | N9: =(NER!$L$11+graphs_analyses!L9)/(graphs_analyses!K9 +NER!$K$11) - NER!$M$11 -> -0.00055940521 | R9: grfGeogPlaceGenerique | S9: grfgeogHydro | T9: =COUNTIFS(Results!J:J, R9, Results!K:K, S9) -> 1 | U9: =COUNTIFS(Results!J:J, R9,Results!K:K, S9, Results!B:B, 1) + COUNTIFS(Results!J:J, R9,Results!K:K, S9, Results!B:B, 0) -> 1 | V9: =COUNTIFS(Results!J:J, R9, Results!K:K, S9, Results!B:B, 1) -> 1 | W9: =IFERROR(V9/U9, 0) -> 1 | X9: =COUNTIFS(Results!J:J, R9, Results!K:K, S9, Results!I:I, $X$1) -> 1 | Y9: =COUNTIFS(Results!J:J, R9,Results!K:K, S9, Results!I:I, $X$1, Results!B:B, 1) + COUNTIFS(Results!J:J, R9,Results!K:K, S9,Results!I:I, $X$1, Results!B:B, 0) -> 1 | Z9: =COUNTIFS(Results!J:J, R9, Results!K:K, S9, Results!I:I, $X$1, Results!B:B, 1) -> 1 | AA9: =IFERROR(Z9/Y9, 0) -> 1 | AB9: =COUNTIFS(Results!J:J, R9,Results!K:K, S9, Results!I:I, "casEN") + COUNTIFS(Results!J:J, R9,Results!K:K, S9, Results!I:I, "casEN_opti") -> 0 | AC9: =COUNTIFS(Results!J:J, R9,Results!K:K, S9, Results!B:B, 1, Results!I:I, "casEN") + COUNTIFS(Results!J:J, R9,Results!K:K, S9, Results!B:B, 0, Results!I:I, "casEN") + COUNTIFS(Results!J:J, R9,Results!K:K, S9, Results!B:B, 1, Results!I:I, "casEN_opti") + COUNTIFS(Results!J:J, R9,Results!K:K, S9, Results!B:B, 0, Results!I:I, "casEN_opti") -> 0 | AD9: =COUNTIFS(Results!J:J, R9,Results!K:K, S9, Results!B:B, 1, Results!I:I, "casEN") + COUNTIFS(Results!J:J, R9,Results!K:K, S9, Results!B:B, 1, Results!I:I, "casEN_opti") -> 0 | AE9: =IFERROR(AD9/AC9, 0) -> 0 | AF9: =(NER!$L$11+graphs_analyses!AD9)/(graphs_analyses!AC9 +NER!$K$11) - NER!$M$11 -> 0 | AJ9: grforgSeule | AK9: grforgProximite | AL9: grftagCiviliteS | AM9: =COUNTIFS(Results!J:J, AJ9, Results!K:K, AK9, Results!L:L, AL9) -> 2 | AN9: =COUNTIFS(Results!J:J, AJ9, Results!K:K, AK9, Results!L:L, AL9, Results!B:B, 1) + COUNTIFS(Results!J:J, AJ9, Results!K:K, AK9, Results!L:L, AL9, Results!B:B, 0) -> 2 | AO9: =COUNTIFS(Results!J:J, AJ9, Results!K:K, AK9, Results!L:L, AL9, Results!B:B, 1) -> 0 | AP9: =IFERROR(AO9/AN9, 0) -> 0 | AQ9: =COUNTIFS(Results!J:J, AJ9, Results!K:K, AK9, Results!L:L, AL9, Results!I:I, $AQ$1) -> 0 | AR9: =COUNTIFS(Results!J:J, AJ9, Results!K:K, AK9, Results!L:L, AL9, Results!I:I, $AQ$1, Results!B:B, 1) + COUNTIFS(Results!J:J, AJ9, Results!K:K, AK9, Results!L:L, AL9, Results!I:I, $AQ$1, Results!B:B, 0) -> 0 | AS9: =COUNTIFS(Results!J:J, AJ9, Results!K:K, AK9, Results!L:L, AL9, Results!I:I, $AQ$1, Results!B:B, 1) -> 0 | AT9: =IFERROR(AS9/AR9, 0) -> 0 | AU9: =COUNTIFS(Results!J:J, AJ9,Results!K:K, AK9, Results!L:L, AL9,Results!I:I, "casEN") + COUNTIFS(Results!J:J, AJ9,Results!K:K, AK9, Results!L:L, AL9,Results!I:I, "casEN_opti") -> 2 | AV9: =COUNTIFS(Results!J:J, AJ9,Results!K:K, AK9, Results!L:L, AL9,Results!I:I, "casEN", Results!B:B, 1) + COUNTIFS(Results!J:J, AJ9,Results!K:K, AK9, Results!L:L, AL9,Results!I:I, "casEN", Results!B:B, 0) + COUNTIFS(Results!J:J, AJ9,Results!K:K, AK9, Results!L:L, AL9,Results!I:I, "casEN_opti", Results!B:B, 1) + COUNTIFS(Results!J:J, AJ9,Results!K:K, AK9, Results!L:L, AL9,Results!I:I, "casEN_opti", Results!B:B, 0) -> 2 | AW9: =COUNTIFS(Results!J:J, AJ9,Results!K:K, AK9, Results!L:L, AL9,Results!I:I, "casEN", Results!B:B, 1) + COUNTIFS(Results!J:J, AJ9,Results!K:K, AK9, Results!L:L, AL9,Results!I:I, "casEN_opti", Results!B:B, 1) -> 0 | AX9: =IFERROR(AW9/AV9, 0) -> 0 | AY9: =(NER!$L$11+graphs_analyses!AW9)/(graphs_analyses!AV9 +NER!$K$11) - NER!$M$11 -> -0.00027978306
A10: grfgeog | B10: =COUNTIF(Results!J:J, A10) -> 1138 | C10: =COUNTIFS(Results!J:J, A10, Results!B:B, 1) + COUNTIFS(Results!J:J, A10, Results!B:B, 0) -> 1117 | D10: =COUNTIFS(Results!J:J, A10, Results!B:B, 1) -> 1091 | E10: =IF(C10=0, 0, D10/C10) -> 0.97672337 | F10: =COUNTIFS(Results!J:J, A10, Results!I:I, $F$1) -> 749 | G10: =COUNTIFS(Results!J:J, A10, Results!B:B, 1, Results!I:I, $F$1) + COUNTIFS(Results!J:J, A10, Results!B:B, 0, Results!I:I, $F$1) -> 749 | H10: =COUNTIFS(Results!I:I, $F$1,Results!J:J, A10, Results!B:B, 1) -> 747 | I10: =IFERROR(H10/G10, 0) -> 0.99732977 | J10: =COUNTIFS(Results!J:J, A10, Results!I:I, "casEN") + COUNTIFS(Results!J:J, A10, Results!I:I, "casEN_opti") -> 240 | K10: =COUNTIFS(Results!J:J, A10, Results!B:B, 1, Results!I:I, "casEN") + COUNTIFS(Results!J:J, A10, Results!B:B, 0, Results!I:I, "casEN") + COUNTIFS(Results!J:J, A10, Results!B:B, 1, Results!I:I, "casEN_opti") + COUNTIFS(Results!J:J, A10, Results!B:B, 0, Results!I:I, "casEN_opti") -> 219 | L10: =COUNTIFS(Results!I:I, "casEN",Results!J:J, A10, Results!B:B, 1) + COUNTIFS(Results!I:I, "casEN_opti",Results!J:J, A10, Results!B:B, 1) -> 201 | M10: =IFERROR(L10/K10, 0) -> 0.91780822 | N10: =(NER!$L$11+graphs_analyses!L10)/(graphs_analyses!K10 +NER!$K$11) - NER!$M$11 -> -0.0016755664 | R10: grforgSeule | S10: grfpersGenerique | T10: =COUNTIFS(Results!J:J, R10, Results!K:K, S10) -> 14 | U10: =COUNTIFS(Results!J:J, R10,Results!K:K, S10, Results!B:B, 1) + COUNTIFS(Results!J:J, R10,Results!K:K, S10, Results!B:B, 0) -> 1 | V10: =COUNTIFS(Results!J:J, R10, Results!K:K, S10, Results!B:B, 1) -> 1 | W10: =IFERROR(V10/U10, 0) -> 1 | X10: =COUNTIFS(Results!J:J, R10, Results!K:K, S10, Results!I:I, $X$1) -> 0 | Y10: =COUNTIFS(Results!J:J, R10,Results!K:K, S10, Results!I:I, $X$1, Results!B:B, 1) + COUNTIFS(Results!J:J, R10,Results!K:K, S10,Results!I:I, $X$1, Results!B:B, 0) -> 0 | Z10: =COUNTIFS(Results!J:J, R10, Results!K:K, S10, Results!I:I, $X$1, Results!B:B, 1) -> 0 | AA10: =IFERROR(Z10/Y10, 0) -> 0 | AB10: =COUNTIFS(Results!J:J, R10,Results!K:K, S10, Results!I:I, "casEN") + COUNTIFS(Results!J:J, R10,Results!K:K, S10, Results!I:I, "casEN_opti") -> 13 | AC10: =COUNTIFS(Results!J:J, R10,Results!K:K, S10, Results!B:B, 1, Results!I:I, "casEN") + COUNTIFS(Results!J:J, R10,Results!K:K, S10, Results!B:B, 0, Results!I:I, "casEN") + COUNTIFS(Results!J:J, R10,Results!K:K, S10, Results!B:B, 1, Results!I:I, "casEN_opti") + COUNTIFS(Results!J:J, R10,Results!K:K, S10, Results!B:B, 0, Results!I:I, "casEN_opti") -> 0 | AD10: =COUNTIFS(Results!J:J, R10,Results!K:K, S10, Results!B:B, 1, Results!I:I, "casEN") + COUNTIFS(Results!J:J, R10,Results!K:K, S10, Results!B:B, 1, Results!I:I, "casEN_opti") -> 0 | AE10: =IFERROR(AD10/AC10, 0) -> 0 | AF10: =(NER!$L$11+graphs_analyses!AD10)/(graphs_analyses!AC10 +NER!$K$11) - NER!$M$11 -> 0 | AJ10: grforgSeule | AK10: grforgProximite | AL10: grfroleName | AM10: =COUNTIFS(Results!J:J, AJ10, Results!K:K, AK10, Results!L:L, AL10) -> 2 | AN10: =COUNTIFS(Results!J:J, AJ10, Results!K:K, AK10, Results!L:L, AL10, Results!B:B, 1) + COUNTIFS(Results!J:J, AJ10, Results!K:K, AK10, Results!L:L, AL10, Results!B:B, 0) -> 2 | AO10: =COUNTIFS(Results!J:J, AJ10, Results!K:K, AK10, Results!L:L, AL10, Results!B:B, 1) -> 0 | AP10: =IFERROR(AO10/AN10, 0) -> 0 | AQ10: =COUNTIFS(Results!J:J, AJ10, Results!K:K, AK10, Results!L:L, AL10, Results!I:I, $AQ$1) -> 0 | AR10: =COUNTIFS(Results!J:J, AJ10, Results!K:K, AK10, Results!L:L, AL10, Results!I:I, $AQ$1, Results!B:B, 1) + COUNTIFS(Results!J:J, AJ10, Results!K:K, AK10, Results!L:L, AL10, Results!I:I, $AQ$1, Results!B:B, 0) -> 0 | AS10: =COUNTIFS(Results!J:J, AJ10, Results!K:K, AK10, Results!L:L, AL10, Results!I:I, $AQ$1, Results!B:B, 1) -> 0 | AT10: =IFERROR(AS10/AR10, 0) -> 0 | AU10: =COUNTIFS(Results!J:J, AJ10,Results!K:K, AK10, Results!L:L, AL10,Results!I:I, "casEN") + COUNTIFS(Results!J:J, AJ10,Results!K:K, AK10, Results!L:L, AL10,Results!I:I, "casEN_opti") -> 2 | AV10: =COUNTIFS(Results!J:J, AJ10,Results!K:K, AK10, Results!L:L, AL10,Results!I:I, "casEN", Results!B:B, 1) + COUNTIFS(Results!J:J, AJ10,Results!K:K, AK10, Results!L:L, AL10,Results!I:I, "casEN", Results!B:B, 0) + COUNTIFS(Results!J:J, AJ10,Results!K:K, AK10, Results!L:L, AL10,Results!I:I, "casEN_opti", Results!B:B, 1) + COUNTIFS(Results!J:J, AJ10,Results!K:K, AK10, Results!L:L, AL10,Results!I:I, "casEN_opti", Results!B:B, 0) -> 2 | AW10: =COUNTIFS(Results!J:J, AJ10,Results!K:K, AK10, Results!L:L, AL10,Results!I:I, "casEN", Results!B:B, 1) + COUNTIFS(Results!J:J, AJ10,Results!K:K, AK10, Results!L:L, AL10,Results!I:I, "casEN_opti", Results!B:B, 1) -> 0 | AX10: =IFERROR(AW10/AV10, 0) -> 0 | AY10: =(NER!$L$11+graphs_analyses!AW10)/(graphs_analyses!AV10 +NER!$K$11) - NER!$M$11 -> -0.00027978306
A11: grfplaceQuartier | B11: =COUNTIF(Results!J:J, A11) -> 58 | C11: =COUNTIFS(Results!J:J, A11, Results!B:B, 1) + COUNTIFS(Results!J:J, A11, Results!B:B, 0) -> 0 | D11: =COUNTIFS(Results!J:J, A11, Results!B:B, 1) -> 0 | E11: =IF(C11=0, 0, D11/C11) -> 0 | F11: =COUNTIFS(Results!J:J, A11, Results!I:I, $F$1) -> 0 | G11: =COUNTIFS(Results!J:J, A11, Results!B:B, 1, Results!I:I, $F$1) + COUNTIFS(Results!J:J, A11, Results!B:B, 0, Results!I:I, $F$1) -> 0 | H11: =COUNTIFS(Results!I:I, $F$1,Results!J:J, A11, Results!B:B, 1) -> 0 | I11: =IFERROR(H11/G11, 0) -> 0 | J11: =COUNTIFS(Results!J:J, A11, Results!I:I, "casEN") + COUNTIFS(Results!J:J, A11, Results!I:I, "casEN_opti") -> 58 | K11: =COUNTIFS(Results!J:J, A11, Results!B:B, 1, Results!I:I, "casEN") + COUNTIFS(Results!J:J, A11, Results!B:B, 0, Results!I:I, "casEN") + COUNTIFS(Results!J:J, A11, Results!B:B, 1, Results!I:I, "casEN_opti") + COUNTIFS(Results!J:J, A11, Results!B:B, 0, Results!I:I, "casEN_opti") -> 0 | L11: =COUNTIFS(Results!I:I, "casEN",Results!J:J, A11, Results!B:B, 1) + COUNTIFS(Results!I:I, "casEN_opti",Results!J:J, A11, Results!B:B, 1) -> 0 | M11: =IFERROR(L11/K11, 0) -> 0 | N11: =(NER!$L$11+graphs_analyses!L11)/(graphs_analyses!K11 +NER!$K$11) - NER!$M$11 -> 0 | R11: grforgSeule | S11: grforgProximite | T11: =COUNTIFS(Results!J:J, R11, Results!K:K, S11) -> 97 | U11: =COUNTIFS(Results!J:J, R11,Results!K:K, S11, Results!B:B, 1) + COUNTIFS(Results!J:J, R11,Results!K:K, S11, Results!B:B, 0) -> 94 | V11: =COUNTIFS(Results!J:J, R11, Results!K:K, S11, Results!B:B, 1) -> 38 | W11: =IFERROR(V11/U11, 0) -> 0.40425532 | X11: =COUNTIFS(Results!J:J, R11, Results!K:K, S11, Results!I:I, $X$1) -> 3 | Y11: =COUNTIFS(Results!J:J, R11,Results!K:K, S11, Results!I:I, $X$1, Results!B:B, 1) + COUNTIFS(Results!J:J, R11,Results!K:K, S11,Results!I:I, $X$1, Results!B:B, 0) -> 3 | Z11: =COUNTIFS(Results!J:J, R11, Results!K:K, S11, Results!I:I, $X$1, Results!B:B, 1) -> 3 | AA11: =IFERROR(Z11/Y11, 0) -> 1 | AB11: =COUNTIFS(Results!J:J, R11,Results!K:K, S11, Results!I:I, "casEN") + COUNTIFS(Results!J:J, R11,Results!K:K, S11, Results!I:I, "casEN_opti") -> 90 | AC11: =COUNTIFS(Results!J:J, R11,Results!K:K, S11, Results!B:B, 1, Results!I:I, "casEN") + COUNTIFS(Results!J:J, R11,Results!K:K, S11, Results!B:B, 0, Results!I:I, "casEN") + COUNTIFS(Results!J:J, R11,Results!K:K, S11, Results!B:B, 1, Results!I:I, "casEN_opti") + COUNTIFS(Results!J:J, R11,Results!K:K, S11, Results!B:B, 0, Results!I:I, "casEN_opti") -> 88 | AD11: =COUNTIFS(Results!J:J, R11,Results!K:K, S11, Results!B:B, 1, Results!I:I, "casEN") + COUNTIFS(Results!J:J, R11,Results!K:K, S11, Results!B:B, 1, Results!I:I, "casEN_opti") -> 32 | AE11: =IFERROR(AD11/AC11, 0) -> 0.36363636 | AF11: =(NER!$L$11+graphs_analyses!AD11)/(graphs_analyses!AC11 +NER!$K$11) - NER!$M$11 -> -0.0076139495 | AJ11: grforgSeule | AK11: grforgAdministrative | AL11: grfpersGenerique | AM11: =COUNTIFS(Results!J:J, AJ11, Results!K:K, AK11, Results!L:L, AL11) -> 2 | AN11: =COUNTIFS(Results!J:J, AJ11, Results!K:K, AK11, Results!L:L, AL11, Results!B:B, 1) + COUNTIFS(Results!J:J, AJ11, Results!K:K, AK11, Results!L:L, AL11, Results!B:B, 0) -> 1 | AO11: =COUNTIFS(Results!J:J, AJ11, Results!K:K, AK11, Results!L:L, AL11, Results!B:B, 1) -> 0 | AP11: =IFERROR(AO11/AN11, 0) -> 0 | AQ11: =COUNTIFS(Results!J:J, AJ11, Results!K:K, AK11, Results!L:L, AL11, Results!I:I, $AQ$1) -> 0 | AR11: =COUNTIFS(Results!J:J, AJ11, Results!K:K, AK11, Results!L:L, AL11, Results!I:I, $AQ$1, Results!B:B, 1) + COUNTIFS(Results!J:J, AJ11, Results!K:K, AK11, Results!L:L, AL11, Results!I:I, $AQ$1, Results!B:B, 0) -> 0 | AS11: =COUNTIFS(Results!J:J, AJ11, Results!K:K, AK11, Results!L:L, AL11, Results!I:I, $AQ$1, Results!B:B, 1) -> 0 | AT11: =IFERROR(AS11/AR11, 0) -> 0 | AU11: =COUNTIFS(Results!J:J, AJ11,Results!K:K, AK11, Results!L:L, AL11,Results!I:I, "casEN") + COUNTIFS(Results!J:J, AJ11,Results!K:K, AK11, Results!L:L, AL11,Results!I:I, "casEN_opti") -> 2 | AV11: =COUNTIFS(Results!J:J, AJ11,Results!K:K, AK11, Results!L:L, AL11,Results!I:I, "casEN", Results!B:B, 1) + COUNTIFS(Results!J:J, AJ11,Results!K:K, AK11, Results!L:L, AL11,Results!I:I, "casEN", Results!B:B, 0) + COUNTIFS(Results!J:J, AJ11,Results!K:K, AK11, Results!L:L, AL11,Results!I:I, "casEN_opti", Results!B:B, 1) + COUNTIFS(Results!J:J, AJ11,Results!K:K, AK11, Results!L:L, AL11,Results!I:I, "casEN_opti", Results!B:B, 0) -> 1 | AW11: =COUNTIFS(Results!J:J, AJ11,Results!K:K, AK11, Results!L:L, AL11,Results!I:I, "casEN", Results!B:B, 1) + COUNTIFS(Results!J:J, AJ11,Results!K:K, AK11, Results!L:L, AL11,Results!I:I, "casEN_opti", Results!B:B, 1) -> 0 | AX11: =IFERROR(AW11/AV11, 0) -> 0 | AY11: =(NER!$L$11+graphs_analyses!AW11)/(graphs_analyses!AV11 +NER!$K$11) - NER!$M$11 -> -0.00013991165
A12: grforgGenerique | B12: =COUNTIF(Results!J:J, A12) -> 300 | C12: =COUNTIFS(Results!J:J, A12, Results!B:B, 1) + COUNTIFS(Results!J:J, A12, Results!B:B, 0) -> 47 | D12: =COUNTIFS(Results!J:J, A12, Results!B:B, 1) -> 13 | E12: =IF(C12=0, 0, D12/C12) -> 0.27659574 | F12: =COUNTIFS(Results!J:J, A12, Results!I:I, $F$1) -> 10 | G12: =COUNTIFS(Results!J:J, A12, Results!B:B, 1, Results!I:I, $F$1) + COUNTIFS(Results!J:J, A12, Results!B:B, 0, Results!I:I, $F$1) -> 10 | H12: =COUNTIFS(Results!I:I, $F$1,Results!J:J, A12, Results!B:B, 1) -> 10 | I12: =IFERROR(H12/G12, 0) -> 1 | J12: =COUNTIFS(Results!J:J, A12, Results!I:I, "casEN") + COUNTIFS(Results!J:J, A12, Results!I:I, "casEN_opti") -> 280 | K12: =COUNTIFS(Results!J:J, A12, Results!B:B, 1, Results!I:I, "casEN") + COUNTIFS(Results!J:J, A12, Results!B:B, 0, Results!I:I, "casEN") + COUNTIFS(Results!J:J, A12, Results!B:B, 1, Results!I:I, "casEN_opti") + COUNTIFS(Results!J:J, A12, Results!B:B, 0, Results!I:I, "casEN_opti") -> 29 | L12: =COUNTIFS(Results!I:I, "casEN",Results!J:J, A12, Results!B:B, 1) + COUNTIFS(Results!I:I, "casEN_opti",Results!J:J, A12, Results!B:B, 1) -> 3 | M12: =IFERROR(L12/K12, 0) -> 0.10344828 | N12: =(NER!$L$11+graphs_analyses!L12)/(graphs_analyses!K12 +NER!$K$11) - NER!$M$11 -> -0.0036113622 | R12: grforgSeule | S12: grforgPolice | T12: =COUNTIFS(Results!J:J, R12, Results!K:K, S12) -> 18 | U12: =COUNTIFS(Results!J:J, R12,Results!K:K, S12, Results!B:B, 1) + COUNTIFS(Results!J:J, R12,Results!K:K, S12, Results!B:B, 0) -> 18 | V12: =COUNTIFS(Results!J:J, R12, Results!K:K, S12, Results!B:B, 1) -> 16 | W12: =IFERROR(V12/U12, 0) -> 0.88888889 | X12: =COUNTIFS(Results!J:J, R12, Results!K:K, S12, Results!I:I, $X$1) -> 0 | Y12: =COUNTIFS(Results!J:J, R12,Results!K:K, S12, Results!I:I, $X$1, Results!B:B, 1) + COUNTIFS(Results!J:J, R12,Results!K:K, S12,Results!I:I, $X$1, Results!B:B, 0) -> 0 | Z12: =COUNTIFS(Results!J:J, R12, Results!K:K, S12, Results!I:I, $X$1, Results!B:B, 1) -> 0 | AA12: =IFERROR(Z12/Y12, 0) -> 0 | AB12: =COUNTIFS(Results!J:J, R12,Results!K:K, S12, Results!I:I, "casEN") + COUNTIFS(Results!J:J, R12,Results!K:K, S12, Results!I:I, "casEN_opti") -> 18 | AC12: =COUNTIFS(Results!J:J, R12,Results!K:K, S12, Results!B:B, 1, Results!I:I, "casEN") + COUNTIFS(Results!J:J, R12,Results!K:K, S12, Results!B:B, 0, Results!I:I, "casEN") + COUNTIFS(Results!J:J, R12,Results!K:K, S12, Results!B:B, 1, Results!I:I, "casEN_opti") + COUNTIFS(Results!J:J, R12,Results!K:K, S12, Results!B:B, 0, Results!I:I, "casEN_opti") -> 18 | AD12: =COUNTIFS(Results!J:J, R12,Results!K:K, S12, Results!B:B, 1, Results!I:I, "casEN") + COUNTIFS(Results!J:J, R12,Results!K:K, S12, Results!B:B, 1, Results!I:I, "casEN_opti") -> 16 | AE12: =IFERROR(AD12/AC12, 0) -> 0.88888889 | AF12: =(NER!$L$11+graphs_analyses!AD12)/(graphs_analyses!AC12 +NER!$K$11) - NER!$M$11 -> -0.00021638463 | AJ12: grforgSeule | AK12: grftagGentileP | AL12: grftagNomFamille | AM12: =COUNTIFS(Results!J:J, AJ12, Results!K:K, AK12, Results!L:L, AL12) -> 1 | AN12: =COUNTIFS(Results!J:J, AJ12, Results!K:K, AK12, Results!L:L, AL12, Results!B:B, 1) + COUNTIFS(Results!J:J, AJ12, Results!K:K, AK12, Results!L:L, AL12, Results!B:B, 0) -> 0 | AO12: =COUNTIFS(Results!J:J, AJ12, Results!K:K, AK12, Results!L:L, AL12, Results!B:B, 1) -> 0 | AP12: =IFERROR(AO12/AN12, 0) -> 0 | AQ12: =COUNTIFS(Results!J:J, AJ12, Results!K:K, AK12, Results!L:L, AL12, Results!I:I, $AQ$1) -> 0 | AR12: =COUNTIFS(Results!J:J, AJ12, Results!K:K, AK12, Results!L:L, AL12, Results!I:I, $AQ$1, Results!B:B, 1) + COUNTIFS(Results!J:J, AJ12, Results!K:K, AK12, Results!L:L, AL12, Results!I:I, $AQ$1, Results!B:B, 0) -> 0 | AS12: =COUNTIFS(Results!J:J, AJ12, Results!K:K, AK12, Results!L:L, AL12, Results!I:I, $AQ$1, Results!B:B, 1) -> 0 | AT12: =IFERROR(AS12/AR12, 0) -> 0 | AU12: =COUNTIFS(Results!J:J, AJ12,Results!K:K, AK12, Results!L:L, AL12,Results!I:I, "casEN") + COUNTIFS(Results!J:J, AJ12,Results!K:K, AK12, Results!L:L, AL12,Results!I:I, "casEN_opti") -> 1 | AV12: =COUNTIFS(Results!J:J, AJ12,Results!K:K, AK12, Results!L:L, AL12,Results!I:I, "casEN", Results!B:B, 1) + COUNTIFS(Results!J:J, AJ12,Results!K:K, AK12, Results!L:L, AL12,Results!I:I, "casEN", Results!B:B, 0) + COUNTIFS(Results!J:J, AJ12,Results!K:K, AK12, Results!L:L, AL12,Results!I:I, "casEN_opti", Results!B:B, 1) + COUNTIFS(Results!J:J, AJ12,Results!K:K, AK12, Results!L:L, AL12,Results!I:I, "casEN_opti", Results!B:B, 0) -> 0 | AW12: =COUNTIFS(Results!J:J, AJ12,Results!K:K, AK12, Results!L:L, AL12,Results!I:I, "casEN", Results!B:B, 1) + COUNTIFS(Results!J:J, AJ12,Results!K:K, AK12, Results!L:L, AL12,Results!I:I, "casEN_opti", Results!B:B, 1) -> 0 | AX12: =IFERROR(AW12/AV12, 0) -> 0 | AY12: =(NER!$L$11+graphs_analyses!AW12)/(graphs_analyses!AV12 +NER!$K$11) - NER!$M$11 -> 0
A13: grfroleName | B13: =COUNTIF(Results!J:J, A13) -> 82 | C13: =COUNTIFS(Results!J:J, A13, Results!B:B, 1) + COUNTIFS(Results!J:J, A13, Results!B:B, 0) -> 79 | D13: =COUNTIFS(Results!J:J, A13, Results!B:B, 1) -> 12 | E13: =IF(C13=0, 0, D13/C13) -> 0.15189873 | F13: =COUNTIFS(Results!J:J, A13, Results!I:I, $F$1) -> 5 | G13: =COUNTIFS(Results!J:J, A13, Results!B:B, 1, Results!I:I, $F$1) + COUNTIFS(Results!J:J, A13, Results!B:B, 0, Results!I:I, $F$1) -> 5 | H13: =COUNTIFS(Results!I:I, $F$1,Results!J:J, A13, Results!B:B, 1) -> 4 | I13: =IFERROR(H13/G13, 0) -> 0.8 | J13: =COUNTIFS(Results!J:J, A13, Results!I:I, "casEN") + COUNTIFS(Results!J:J, A13, Results!I:I, "casEN_opti") -> 62 | K13: =COUNTIFS(Results!J:J, A13, Results!B:B, 1, Results!I:I, "casEN") + COUNTIFS(Results!J:J, A13, Results!B:B, 0, Results!I:I, "casEN") + COUNTIFS(Results!J:J, A13, Results!B:B, 1, Results!I:I, "casEN_opti") + COUNTIFS(Results!J:J, A13, Results!B:B, 0, Results!I:I, "casEN_opti") -> 59 | L13: =COUNTIFS(Results!I:I, "casEN",Results!J:J, A13, Results!B:B, 1) + COUNTIFS(Results!I:I, "casEN_opti",Results!J:J, A13, Results!B:B, 1) -> 4 | M13: =IFERROR(L13/K13, 0) -> 0.06779661 | N13: =(NER!$L$11+graphs_analyses!L13)/(graphs_analyses!K13 +NER!$K$11) - NER!$M$11 -> -0.0076158748 | R13: grforgSeule | S13: grforgMedia | T13: =COUNTIFS(Results!J:J, R13, Results!K:K, S13) -> 2 | U13: =COUNTIFS(Results!J:J, R13,Results!K:K, S13, Results!B:B, 1) + COUNTIFS(Results!J:J, R13,Results!K:K, S13, Results!B:B, 0) -> 2 | V13: =COUNTIFS(Results!J:J, R13, Results!K:K, S13, Results!B:B, 1) -> 0 | W13: =IFERROR(V13/U13, 0) -> 0 | X13: =COUNTIFS(Results!J:J, R13, Results!K:K, S13, Results!I:I, $X$1) -> 0 | Y13: =COUNTIFS(Results!J:J, R13,Results!K:K, S13, Results!I:I, $X$1, Results!B:B, 1) + COUNTIFS(Results!J:J, R13,Results!K:K, S13,Results!I:I, $X$1, Results!B:B, 0) -> 0 | Z13: =COUNTIFS(Results!J:J, R13, Results!K:K, S13, Results!I:I, $X$1, Results!B:B, 1) -> 0 | AA13: =IFERROR(Z13/Y13, 0) -> 0 | AB13: =COUNTIFS(Results!J:J, R13,Results!K:K, S13, Results!I:I, "casEN") + COUNTIFS(Results!J:J, R13,Results!K:K, S13, Results!I:I, "casEN_opti") -> 2 | AC13: =COUNTIFS(Results!J:J, R13,Results!K:K, S13, Results!B:B, 1, Results!I:I, "casEN") + COUNTIFS(Results!J:J, R13,Results!K:K, S13, Results!B:B, 0, Results!I:I, "casEN") + COUNTIFS(Results!J:J, R13,Results!K:K, S13, Results!B:B, 1, Results!I:I, "casEN_opti") + COUNTIFS(Results!J:J, R13,Results!K:K, S13, Results!B:B, 0, Results!I:I, "casEN_opti") -> 2 | AD13: =COUNTIFS(Results!J:J, R13,Results!K:K, S13, Results!B:B, 1, Results!I:I, "casEN") + COUNTIFS(Results!J:J, R13,Results!K:K, S13, Results!B:B, 1, Results!I:I, "casEN_opti") -> 0 | AE13: =IFERROR(AD13/AC13, 0) -> 0 | AF13: =(NER!$L$11+graphs_analyses!AD13)/(graphs_analyses!AC13 +NER!$K$11) - NER!$M$11 -> -0.00027978306 | AJ13: grforgSeule | AK13: grforgMusique | AL13: grfpersGenerique | AM13: =COUNTIFS(Results!J:J, AJ13, Results!K:K, AK13, Results!L:L, AL13) -> 1 | AN13: =COUNTIFS(Results!J:J, AJ13, Results!K:K, AK13, Results!L:L, AL13, Results!B:B, 1) + COUNTIFS(Results!J:J, AJ13, Results!K:K, AK13, Results!L:L, AL13, Results!B:B, 0) -> 1 | AO13: =COUNTIFS(Results!J:J, AJ13, Results!K:K, AK13, Results!L:L, AL13, Results!B:B, 1) -> 1 | AP13: =IFERROR(AO13/AN13, 0) -> 1 | AQ13: =COUNTIFS(Results!J:J, AJ13, Results!K:K, AK13, Results!L:L, AL13, Results!I:I, $AQ$1) -> 1 | AR13: =COUNTIFS(Results!J:J, AJ13, Results!K:K, AK13, Results!L:L, AL13, Results!I:I, $AQ$1, Results!B:B, 1) + COUNTIFS(Results!J:J, AJ13, Results!K:K, AK13, Results!L:L, AL13, Results!I:I, $AQ$1, Results!B:B, 0) -> 1 | AS13: =COUNTIFS(Results!J:J, AJ13, Results!K:K, AK13, Results!L:L, AL13, Results!I:I, $AQ$1, Results!B:B, 1) -> 1 | AT13: =IFERROR(AS13/AR13, 0) -> 1 | AU13: =COUNTIFS(Results!J:J, AJ13,Results!K:K, AK13, Results!L:L, AL13,Results!I:I, "casEN") + COUNTIFS(Results!J:J, AJ13,Results!K:K, AK13, Results!L:L, AL13,Results!I:I, "casEN_opti") -> 0 | AV13: =COUNTIFS(Results!J:J, AJ13,Results!K:K, AK13, Results!L:L, AL13,Results!I:I, "casEN", Results!B:B, 1) + COUNTIFS(Results!J:J, AJ13,Results!K:K, AK13, Results!L:L, AL13,Results!I:I, "casEN", Results!B:B, 0) + COUNTIFS(Results!J:J, AJ13,Results!K:K, AK13, Results!L:L, AL13,Results!I:I, "casEN_opti", Results!B:B, 1) + COUNTIFS(Results!J:J, AJ13,Results!K:K, AK13, Results!L:L, AL13,Results!I:I, "casEN_opti", Results!B:B, 0) -> 0 | AW13: =COUNTIFS(Results!J:J, AJ13,Results!K:K, AK13, Results!L:L, AL13,Results!I:I, "casEN", Results!B:B, 1) + COUNTIFS(Results!J:J, AJ13,Results!K:K, AK13, Results!L:L, AL13,Results!I:I, "casEN_opti", Results!B:B, 1) -> 0 | AX13: =IFERROR(AW13/AV13, 0) -> 0 | AY13: =(NER!$L$11+graphs_analyses!AW13)/(graphs_analyses!AV13 +NER!$K$11) - NER!$M$11 -> 0
A14: grforgAdministrative | B14: =COUNTIF(Results!J:J, A14) -> 107 | C14: =COUNTIFS(Results!J:J, A14, Results!B:B, 1) + COUNTIFS(Results!J:J, A14, Results!B:B, 0) -> 0 | D14: =COUNTIFS(Results!J:J, A14, Results!B:B, 1) -> 0 | E14: =IF(C14=0, 0, D14/C14) -> 0 | F14: =COUNTIFS(Results!J:J, A14, Results!I:I, $F$1) -> 0 | G14: =COUNTIFS(Results!J:J, A14, Results!B:B, 1, Results!I:I, $F$1) + COUNTIFS(Results!J:J, A14, Results!B:B, 0, Results!I:I, $F$1) -> 0 | H14: =COUNTIFS(Results!I:I, $F$1,Results!J:J, A14, Results!B:B, 1) -> 0 | I14: =IFERROR(H14/G14, 0) -> 0 | J14: =COUNTIFS(Results!J:J, A14, Results!I:I, "casEN") + COUNTIFS(Results!J:J, A14, Results!I:I, "casEN_opti") -> 107 | K14: =COUNTIFS(Results!J:J, A14, Results!B:B, 1, Results!I:I, "casEN") + COUNTIFS(Results!J:J, A14, Results!B:B, 0, Results!I:I, "casEN") + COUNTIFS(Results!J:J, A14, Results!B:B, 1, Results!I:I, "casEN_opti") + COUNTIFS(Results!J:J, A14, Results!B:B, 0, Results!I:I, "casEN_opti") -> 0 | L14: =COUNTIFS(Results!I:I, "casEN",Results!J:J, A14, Results!B:B, 1) + COUNTIFS(Results!I:I, "casEN_opti",Results!J:J, A14, Results!B:B, 1) -> 0 | M14: =IFERROR(L14/K14, 0) -> 0 | N14: =(NER!$L$11+graphs_analyses!L14)/(graphs_analyses!K14 +NER!$K$11) - NER!$M$11 -> 0 | R14: grforgSeule | S14: grftagNomFamille | T14: =COUNTIFS(Results!J:J, R14, Results!K:K, S14) -> 4 | U14: =COUNTIFS(Results!J:J, R14,Results!K:K, S14, Results!B:B, 1) + COUNTIFS(Results!J:J, R14,Results!K:K, S14, Results!B:B, 0) -> 0 | V14: =COUNTIFS(Results!J:J, R14, Results!K:K, S14, Results!B:B, 1) -> 0 | W14: =IFERROR(V14/U14, 0) -> 0 | X14: =COUNTIFS(Results!J:J, R14, Results!K:K, S14, Results!I:I, $X$1) -> 0 | Y14: =COUNTIFS(Results!J:J, R14,Results!K:K, S14, Results!I:I, $X$1, Results!B:B, 1) + COUNTIFS(Results!J:J, R14,Results!K:K, S14,Results!I:I, $X$1, Results!B:B, 0) -> 0 | Z14: =COUNTIFS(Results!J:J, R14, Results!K:K, S14, Results!I:I, $X$1, Results!B:B, 1) -> 0 | AA14: =IFERROR(Z14/Y14, 0) -> 0 | AB14: =COUNTIFS(Results!J:J, R14,Results!K:K, S14, Results!I:I, "casEN") + COUNTIFS(Results!J:J, R14,Results!K:K, S14, Results!I:I, "casEN_opti") -> 4 | AC14: =COUNTIFS(Results!J:J, R14,Results!K:K, S14, Results!B:B, 1, Results!I:I, "casEN") + COUNTIFS(Results!J:J, R14,Results!K:K, S14, Results!B:B, 0, Results!I:I, "casEN") + COUNTIFS(Results!J:J, R14,Results!K:K, S14, Results!B:B, 1, Results!I:I, "casEN_opti") + COUNTIFS(Results!J:J, R14,Results!K:K, S14, Results!B:B, 0, Results!I:I, "casEN_opti") -> 0 | AD14: =COUNTIFS(Results!J:J, R14,Results!K:K, S14, Results!B:B, 1, Results!I:I, "casEN") + COUNTIFS(Results!J:J, R14,Results!K:K, S14, Results!B:B, 1, Results!I:I, "casEN_opti") -> 0 | AE14: =IFERROR(AD14/AC14, 0) -> 0 | AF14: =(NER!$L$11+graphs_analyses!AD14)/(graphs_analyses!AC14 +NER!$K$11) - NER!$M$11 -> 0 | AJ14: grforgSeule | AK14: grforgMusique | AL14: grfpersPrenomNom | AM14: =COUNTIFS(Results!J:J, AJ14, Results!K:K, AK14, Results!L:L, AL14) -> 1 | AN14: =COUNTIFS(Results!J:J, AJ14, Results!K:K, AK14, Results!L:L, AL14, Results!B:B, 1) + COUNTIFS(Results!J:J, AJ14, Results!K:K, AK14, Results!L:L, AL14, Results!B:B, 0) -> 1 | AO14: =COUNTIFS(Results!J:J, AJ14, Results!K:K, AK14, Results!L:L, AL14, Results!B:B, 1) -> 1 | AP14: =IFERROR(AO14/AN14, 0) -> 1 | AQ14: =COUNTIFS(Results!J:J, AJ14, Results!K:K, AK14, Results!L:L, AL14, Results!I:I, $AQ$1) -> 1 | AR14: =COUNTIFS(Results!J:J, AJ14, Results!K:K, AK14, Results!L:L, AL14, Results!I:I, $AQ$1, Results!B:B, 1) + COUNTIFS(Results!J:J, AJ14, Results!K:K, AK14, Results!L:L, AL14, Results!I:I, $AQ$1, Results!B:B, 0) -> 1 | AS14: =COUNTIFS(Results!J:J, AJ14, Results!K:K, AK14, Results!L:L, AL14, Results!I:I, $AQ$1, Results!B:B, 1) -> 1 | AT14: =IFERROR(AS14/AR14, 0) -> 1 | AU14: =COUNTIFS(Results!J:J, AJ14,Results!K:K, AK14, Results!L:L, AL14,Results!I:I, "casEN") + COUNTIFS(Results!J:J, AJ14,Results!K:K, AK14, Results!L:L, AL14,Results!I:I, "casEN_opti") -> 0 | AV14: =COUNTIFS(Results!J:J, AJ14,Results!K:K, AK14, Results!L:L, AL14,Results!I:I, "casEN", Results!B:B, 1) + COUNTIFS(Results!J:J, AJ14,Results!K:K, AK14, Results!L:L, AL14,Results!I:I, "casEN", Results!B:B, 0) + COUNTIFS(Results!J:J, AJ14,Results!K:K, AK14, Results!L:L, AL14,Results!I:I, "casEN_opti", Results!B:B, 1) + COUNTIFS(Results!J:J, AJ14,Results!K:K, AK14, Results!L:L, AL14,Results!I:I, "casEN_opti", Results!B:B, 0) -> 0 | AW14: =COUNTIFS(Results!J:J, AJ14,Results!K:K, AK14, Results!L:L, AL14,Results!I:I, "casEN", Results!B:B, 1) + COUNTIFS(Results!J:J, AJ14,Results!K:K, AK14, Results!L:L, AL14,Results!I:I, "casEN_opti", Results!B:B, 1) -> 0 | AX14: =IFERROR(AW14/AV14, 0) -> 0 | AY14: =(NER!$L$11+graphs_analyses!AW14)/(graphs_analyses!AV14 +NER!$K$11) - NER!$M$11 -> 0
... A28: grforgDico | B28: =COUNTIF(Results!J:J, A28) -> 87 | C28: =COUNTIFS(Results!J:J, A28, Results!B:B, 1) + COUNTIFS(Results!J:J, A28, Results!B:B, 0) -> 87 | D28: =COUNTIFS(Results!J:J, A28, Results!B:B, 1) -> 55 | E28: =IF(C28=0, 0, D28/C28) -> 0.63218391 | F28: =COUNTIFS(Results!J:J, A28, Results!I:I, $F$1) -> 34 | G28: =COUNTIFS(Results!J:J, A28, Results!B:B, 1, Results!I:I, $F$1) + COUNTIFS(Results!J:J, A28, Results!B:B, 0, Results!I:I, $F$1) -> 34 | H28: =COUNTIFS(Results!I:I, $F$1,Results!J:J, A28, Results!B:B, 1) -> 33 | I28: =IFERROR(H28/G28, 0) -> 0.97058824 | J28: =COUNTIFS(Results!J:J, A28, Results!I:I, "casEN") + COUNTIFS(Results!J:J, A28, Results!I:I, "casEN_opti") -> 42 | K28: =COUNTIFS(Results!J:J, A28, Results!B:B, 1, Results!I:I, "casEN") + COUNTIFS(Results!J:J, A28, Results!B:B, 0, Results!I:I, "casEN") + COUNTIFS(Results!J:J, A28, Results!B:B, 1, Results!I:I, "casEN_opti") + COUNTIFS(Results!J:J, A28, Results!B:B, 0, Results!I:I, "casEN_opti") -> 42 | L28: =COUNTIFS(Results!I:I, "casEN",Results!J:J, A28, Results!B:B, 1) + COUNTIFS(Results!I:I, "casEN_opti",Results!J:J, A28, Results!B:B, 1) -> 14 | M28: =IFERROR(L28/K28, 0) -> 0.33333333 | N28: =(NER!$L$11+graphs_analyses!L28)/(graphs_analyses!K28 +NER!$K$11) - NER!$M$11 -> -0.0038398347 | R28: grforgSeule | S28: grftagGentileP | T28: =COUNTIFS(Results!J:J, R28, Results!K:K, S28) -> 1 | U28: =COUNTIFS(Results!J:J, R28,Results!K:K, S28, Results!B:B, 1) + COUNTIFS(Results!J:J, R28,Results!K:K, S28, Results!B:B, 0) -> 0 | V28: =COUNTIFS(Results!J:J, R28, Results!K:K, S28, Results!B:B, 1) -> 0 | W28: =IFERROR(V28/U28, 0) -> 0 | X28: =COUNTIFS(Results!J:J, R28, Results!K:K, S28, Results!I:I, $X$1) -> 0 | Y28: =COUNTIFS(Results!J:J, R28,Results!K:K, S28, Results!I:I, $X$1, Results!B:B, 1) + COUNTIFS(Results!J:J, R28,Results!K:K, S28,Results!I:I, $X$1, Results!B:B, 0) -> 0 | Z28: =COUNTIFS(Results!J:J, R28, Results!K:K, S28, Results!I:I, $X$1, Results!B:B, 1) -> 0 | AA28: =IFERROR(Z28/Y28, 0) -> 0 | AB28: =COUNTIFS(Results!J:J, R28,Results!K:K, S28, Results!I:I, "casEN") + COUNTIFS(Results!J:J, R28,Results!K:K, S28, Results!I:I, "casEN_opti") -> 1 | AC28: =COUNTIFS(Results!J:J, R28,Results!K:K, S28, Results!B:B, 1, Results!I:I, "casEN") + COUNTIFS(Results!J:J, R28,Results!K:K, S28, Results!B:B, 0, Results!I:I, "casEN") + COUNTIFS(Results!J:J, R28,Results!K:K, S28, Results!B:B, 1, Results!I:I, "casEN_opti") + COUNTIFS(Results!J:J, R28,Results!K:K, S28, Results!B:B, 0, Results!I:I, "casEN_opti") -> 0 | AD28: =COUNTIFS(Results!J:J, R28,Results!K:K, S28, Results!B:B, 1, Results!I:I, "casEN") + COUNTIFS(Results!J:J, R28,Results!K:K, S28, Results!B:B, 1, Results!I:I, "casEN_opti") -> 0 | AE28: =IFERROR(AD28/AC28, 0) -> 0 | AF28: =(NER!$L$11+graphs_analyses!AD28)/(graphs_analyses!AC28 +NER!$K$11) - NER!$M$11 -> 0 | AJ28: grfplace | AK28: grfplaceBatiment | AL28: grfroleName | AM28: =COUNTIFS(Results!J:J, AJ28, Results!K:K, AK28, Results!L:L, AL28) -> 1 | AN28: =COUNTIFS(Results!J:J, AJ28, Results!K:K, AK28, Results!L:L, AL28, Results!B:B, 1) + COUNTIFS(Results!J:J, AJ28, Results!K:K, AK28, Results!L:L, AL28, Results!B:B, 0) -> 1 | AO28: =COUNTIFS(Results!J:J, AJ28, Results!K:K, AK28, Results!L:L, AL28, Results!B:B, 1) -> 1 | AP28: =IFERROR(AO28/AN28, 0) -> 1 | AQ28: =COUNTIFS(Results!J:J, AJ28, Results!K:K, AK28, Results!L:L, AL28, Results!I:I, $AQ$1) -> 0 | AR28: =COUNTIFS(Results!J:J, AJ28, Results!K:K, AK28, Results!L:L, AL28, Results!I:I, $AQ$1, Results!B:B, 1) + COUNTIFS(Results!J:J, AJ28, Results!K:K, AK28, Results!L:L, AL28, Results!I:I, $AQ$1, Results!B:B, 0) -> 0 | AS28: =COUNTIFS(Results!J:J, AJ28, Results!K:K, AK28, Results!L:L, AL28, Results!I:I, $AQ$1, Results!B:B, 1) -> 0 | AT28: =IFERROR(AS28/AR28, 0) -> 0 | AU28: =COUNTIFS(Results!J:J, AJ28,Results!K:K, AK28, Results!L:L, AL28,Results!I:I, "casEN") + COUNTIFS(Results!J:J, AJ28,Results!K:K, AK28, Results!L:L, AL28,Results!I:I, "casEN_opti") -> 1 | AV28: =COUNTIFS(Results!J:J, AJ28,Results!K:K, AK28, Results!L:L, AL28,Results!I:I, "casEN", Results!B:B, 1) + COUNTIFS(Results!J:J, AJ28,Results!K:K, AK28, Results!L:L, AL28,Results!I:I, "casEN", Results!B:B, 0) + COUNTIFS(Results!J:J, AJ28,Results!K:K, AK28, Results!L:L, AL28,Results!I:I, "casEN_opti", Results!B:B, 1) + COUNTIFS(Results!J:J, AJ28,Results!K:K, AK28, Results!L:L, AL28,Results!I:I, "casEN_opti", Results!B:B, 0) -> 1 | AW28: =COUNTIFS(Results!J:J, AJ28,Results!K:K, AK28, Results!L:L, AL28,Results!I:I, "casEN", Results!B:B, 1) + COUNTIFS(Results!J:J, AJ28,Results!K:K, AK28, Results!L:L, AL28,Results!I:I, "casEN_opti", Results!B:B, 1) -> 1 | AX28: =IFERROR(AW28/AV28, 0) -> 1 | AY28: =(NER!$L$11+graphs_analyses!AW28)/(graphs_analyses!AV28 +NER!$K$11) - NER!$M$11 -> 3.9318464e-06
A29: grforgGouvernement | B29: =COUNTIF(Results!J:J, A29) -> 26 | C29: =COUNTIFS(Results!J:J, A29, Results!B:B, 1) + COUNTIFS(Results!J:J, A29, Results!B:B, 0) -> 26 | D29: =COUNTIFS(Results!J:J, A29, Results!B:B, 1) -> 2 | E29: =IF(C29=0, 0, D29/C29) -> 0.076923077 | F29: =COUNTIFS(Results!J:J, A29, Results!I:I, $F$1) -> 1 | G29: =COUNTIFS(Results!J:J, A29, Results!B:B, 1, Results!I:I, $F$1) + COUNTIFS(Results!J:J, A29, Results!B:B, 0, Results!I:I, $F$1) -> 1 | H29: =COUNTIFS(Results!I:I, $F$1,Results!J:J, A29, Results!B:B, 1) -> 1 | I29: =IFERROR(H29/G29, 0) -> 1 | J29: =COUNTIFS(Results!J:J, A29, Results!I:I, "casEN") + COUNTIFS(Results!J:J, A29, Results!I:I, "casEN_opti") -> 24 | K29: =COUNTIFS(Results!J:J, A29, Results!B:B, 1, Results!I:I, "casEN") + COUNTIFS(Results!J:J, A29, Results!B:B, 0, Results!I:I, "casEN") + COUNTIFS(Results!J:J, A29, Results!B:B, 1, Results!I:I, "casEN_opti") + COUNTIFS(Results!J:J, A29, Results!B:B, 0, Results!I:I, "casEN_opti") -> 24 | L29: =COUNTIFS(Results!I:I, "casEN",Results!J:J, A29, Results!B:B, 1) + COUNTIFS(Results!I:I, "casEN_opti",Results!J:J, A29, Results!B:B, 1) -> 1 | M29: =IFERROR(L29/K29, 0) -> 0.041666667 | N29: =(NER!$L$11+graphs_analyses!L29)/(graphs_analyses!K29 +NER!$K$11) - NER!$M$11 -> -0.0032034379 | R29: grfpersCivilitePersonne | S29: grftagNomFamille | T29: =COUNTIFS(Results!J:J, R29, Results!K:K, S29) -> 193 | U29: =COUNTIFS(Results!J:J, R29,Results!K:K, S29, Results!B:B, 1) + COUNTIFS(Results!J:J, R29,Results!K:K, S29, Results!B:B, 0) -> 54 | V29: =COUNTIFS(Results!J:J, R29, Results!K:K, S29, Results!B:B, 1) -> 54 | W29: =IFERROR(V29/U29, 0) -> 1 | X29: =COUNTIFS(Results!J:J, R29, Results!K:K, S29, Results!I:I, $X$1) -> 69 | Y29: =COUNTIFS(Results!J:J, R29,Results!K:K, S29, Results!I:I, $X$1, Results!B:B, 1) + COUNTIFS(Results!J:J, R29,Results!K:K, S29,Results!I:I, $X$1, Results!B:B, 0) -> 30 | Z29: =COUNTIFS(Results!J:J, R29, Results!K:K, S29, Results!I:I, $X$1, Results!B:B, 1) -> 30 | AA29: =IFERROR(Z29/Y29, 0) -> 1 | AB29: =COUNTIFS(Results!J:J, R29,Results!K:K, S29, Results!I:I, "casEN") + COUNTIFS(Results!J:J, R29,Results!K:K, S29, Results!I:I, "casEN_opti") -> 99 | AC29: =COUNTIFS(Results!J:J, R29,Results!K:K, S29, Results!B:B, 1, Results!I:I, "casEN") + COUNTIFS(Results!J:J, R29,Results!K:K, S29, Results!B:B, 0, Results!I:I, "casEN") + COUNTIFS(Results!J:J, R29,Results!K:K, S29, Results!B:B, 1, Results!I:I, "casEN_opti") + COUNTIFS(Results!J:J, R29,Results!K:K, S29, Results!B:B, 0, Results!I:I, "casEN_opti") -> 8 | AD29: =COUNTIFS(Results!J:J, R29,Results!K:K, S29, Results!B:B, 1, Results!I:I, "casEN") + COUNTIFS(Results!J:J, R29,Results!K:K, S29, Results!B:B, 1, Results!I:I, "casEN_opti") -> 8 | AE29: =IFERROR(AD29/AC29, 0) -> 1 | AF29: =(NER!$L$11+graphs_analyses!AD29)/(graphs_analyses!AC29 +NER!$K$11) - NER!$M$11 -> 3.1423132e-05 | AJ29: main_graph | AK29: second_graph | AL29: third_graph
A30: grforgMedia | B30: =COUNTIF(Results!J:J, A30) -> 46 | C30: =COUNTIFS(Results!J:J, A30, Results!B:B, 1) + COUNTIFS(Results!J:J, A30, Results!B:B, 0) -> 17 | D30: =COUNTIFS(Results!J:J, A30, Results!B:B, 1) -> 2 | E30: =IF(C30=0, 0, D30/C30) -> 0.11764706 | F30: =COUNTIFS(Results!J:J, A30, Results!I:I, $F$1) -> 0 | G30: =COUNTIFS(Results!J:J, A30, Results!B:B, 1, Results!I:I, $F$1) + COUNTIFS(Results!J:J, A30, Results!B:B, 0, Results!I:I, $F$1) -> 0 | H30: =COUNTIFS(Results!I:I, $F$1,Results!J:J, A30, Results!B:B, 1) -> 0 | I30: =IFERROR(H30/G30, 0) -> 0 | J30: =COUNTIFS(Results!J:J, A30, Results!I:I, "casEN") + COUNTIFS(Results!J:J, A30, Results!I:I, "casEN_opti") -> 46 | K30: =COUNTIFS(Results!J:J, A30, Results!B:B, 1, Results!I:I, "casEN") + COUNTIFS(Results!J:J, A30, Results!B:B, 0, Results!I:I, "casEN") + COUNTIFS(Results!J:J, A30, Results!B:B, 1, Results!I:I, "casEN_opti") + COUNTIFS(Results!J:J, A30, Results!B:B, 0, Results!I:I, "casEN_opti") -> 17 | L30: =COUNTIFS(Results!I:I, "casEN",Results!J:J, A30, Results!B:B, 1) + COUNTIFS(Results!I:I, "casEN_opti",Results!J:J, A30, Results!B:B, 1) -> 2 | M30: =IFERROR(L30/K30, 0) -> 0.11764706 | N30: =(NER!$L$11+graphs_analyses!L30)/(graphs_analyses!K30 +NER!$K$11) - NER!$M$11 -> -0.0020860101 | R30: grfpersCivilitePersonne | S30: grftagNomFamilleDe | T30: =COUNTIFS(Results!J:J, R30, Results!K:K, S30) -> 11 | U30: =COUNTIFS(Results!J:J, R30,Results!K:K, S30, Results!B:B, 1) + COUNTIFS(Results!J:J, R30,Results!K:K, S30, Results!B:B, 0) -> 4 | V30: =COUNTIFS(Results!J:J, R30, Results!K:K, S30, Results!B:B, 1) -> 3 | W30: =IFERROR(V30/U30, 0) -> 0.75 | X30: =COUNTIFS(Results!J:J, R30, Results!K:K, S30, Results!I:I, $X$1) -> 3 | Y30: =COUNTIFS(Results!J:J, R30,Results!K:K, S30, Results!I:I, $X$1, Results!B:B, 1) + COUNTIFS(Results!J:J, R30,Results!K:K, S30,Results!I:I, $X$1, Results!B:B, 0) -> 3 | Z30: =COUNTIFS(Results!J:J, R30, Results!K:K, S30, Results!I:I, $X$1, Results!B:B, 1) -> 3 | AA30: =IFERROR(Z30/Y30, 0) -> 1 | AB30: =COUNTIFS(Results!J:J, R30,Results!K:K, S30, Results!I:I, "casEN") + COUNTIFS(Results!J:J, R30,Results!K:K, S30, Results!I:I, "casEN_opti") -> 7 | AC30: =COUNTIFS(Results!J:J, R30,Results!K:K, S30, Results!B:B, 1, Results!I:I, "casEN") + COUNTIFS(Results!J:J, R30,Results!K:K, S30, Results!B:B, 0, Results!I:I, "casEN") + COUNTIFS(Results!J:J, R30,Results!K:K, S30, Results!B:B, 1, Results!I:I, "casEN_opti") + COUNTIFS(Results!J:J, R30,Results!K:K, S30, Results!B:B, 0, Results!I:I, "casEN_opti") -> 1 | AD30: =COUNTIFS(Results!J:J, R30,Results!K:K, S30, Results!B:B, 1, Results!I:I, "casEN") + COUNTIFS(Results!J:J, R30,Results!K:K, S30, Results!B:B, 1, Results!I:I, "casEN_opti") -> 0 | AE30: =IFERROR(AD30/AC30, 0) -> 0 | AF30: =(NER!$L$11+graphs_analyses!AD30)/(graphs_analyses!AC30 +NER!$K$11) - NER!$M$11 -> -0.00013991165
A31: grforgPlaceGeoPolitique | B31: =COUNTIF(Results!J:J, A31) -> 85 | C31: =COUNTIFS(Results!J:J, A31, Results!B:B, 1) + COUNTIFS(Results!J:J, A31, Results!B:B, 0) -> 62 | D31: =COUNTIFS(Results!J:J, A31, Results!B:B, 1) -> 62 | E31: =IF(C31=0, 0, D31/C31) -> 1 | F31: =COUNTIFS(Results!J:J, A31, Results!I:I, $F$1) -> 1 | G31: =COUNTIFS(Results!J:J, A31, Results!B:B, 1, Results!I:I, $F$1) + COUNTIFS(Results!J:J, A31, Results!B:B, 0, Results!I:I, $F$1) -> 0 | H31: =COUNTIFS(Results!I:I, $F$1,Results!J:J, A31, Results!B:B, 1) -> 0 | I31: =IFERROR(H31/G31, 0) -> 0 | J31: =COUNTIFS(Results!J:J, A31, Results!I:I, "casEN") + COUNTIFS(Results!J:J, A31, Results!I:I, "casEN_opti") -> 73 | K31: =COUNTIFS(Results!J:J, A31, Results!B:B, 1, Results!I:I, "casEN") + COUNTIFS(Results!J:J, A31, Results!B:B, 0, Results!I:I, "casEN") + COUNTIFS(Results!J:J, A31, Results!B:B, 1, Results!I:I, "casEN_opti") + COUNTIFS(Results!J:J, A31, Results!B:B, 0, Results!I:I, "casEN_opti") -> 52 | L31: =COUNTIFS(Results!I:I, "casEN",Results!J:J, A31, Results!B:B, 1) + COUNTIFS(Results!I:I, "casEN_opti",Results!J:J, A31, Results!B:B, 1) -> 52 | M31: =IFERROR(L31/K31, 0) -> 1 | N31: =(NER!$L$11+graphs_analyses!L31)/(graphs_analyses!K31 +NER!$K$11) - NER!$M$11 -> 0.00020296705 | R31: grfpersCivilitePersonne | S31: grftagTitreNobiliaireS | T31: =COUNTIFS(Results!J:J, R31, Results!K:K, S31) -> 15 | U31: =COUNTIFS(Results!J:J, R31,Results!K:K, S31, Results!B:B, 1) + COUNTIFS(Results!J:J, R31,Results!K:K, S31, Results!B:B, 0) -> 15 | V31: =COUNTIFS(Results!J:J, R31, Results!K:K, S31, Results!B:B, 1) -> 10 | W31: =IFERROR(V31/U31, 0) -> 0.66666667 | X31: =COUNTIFS(Results!J:J, R31, Results!K:K, S31, Results!I:I, $X$1) -> 8 | Y31: =COUNTIFS(Results!J:J, R31,Results!K:K, S31, Results!I:I, $X$1, Results!B:B, 1) + COUNTIFS(Results!J:J, R31,Results!K:K, S31,Results!I:I, $X$1, Results!B:B, 0) -> 8 | Z31: =COUNTIFS(Results!J:J, R31, Results!K:K, S31, Results!I:I, $X$1, Results!B:B, 1) -> 6 | AA31: =IFERROR(Z31/Y31, 0) -> 0.75 | AB31: =COUNTIFS(Results!J:J, R31,Results!K:K, S31, Results!I:I, "casEN") + COUNTIFS(Results!J:J, R31,Results!K:K, S31, Results!I:I, "casEN_opti") -> 3 | AC31: =COUNTIFS(Results!J:J, R31,Results!K:K, S31, Results!B:B, 1, Results!I:I, "casEN") + COUNTIFS(Results!J:J, R31,Results!K:K, S31, Results!B:B, 0, Results!I:I, "casEN") + COUNTIFS(Results!J:J, R31,Results!K:K, S31, Results!B:B, 1, Results!I:I, "casEN_opti") + COUNTIFS(Results!J:J, R31,Results!K:K, S31, Results!B:B, 0, Results!I:I, "casEN_opti") -> 3 | AD31: =COUNTIFS(Results!J:J, R31,Results!K:K, S31, Results!B:B, 1, Results!I:I, "casEN") + COUNTIFS(Results!J:J, R31,Results!K:K, S31, Results!B:B, 1, Results!I:I, "casEN_opti") -> 0 | AE31: =IFERROR(AD31/AC31, 0) -> 0 | AF31: =(NER!$L$11+graphs_analyses!AD31)/(graphs_analyses!AC31 +NER!$K$11) - NER!$M$11 -> -0.00041961424
A32: grforgMusique | B32: =COUNTIF(Results!J:J, A32) -> 64 | C32: =COUNTIFS(Results!J:J, A32, Results!B:B, 1) + COUNTIFS(Results!J:J, A32, Results!B:B, 0) -> 0 | D32: =COUNTIFS(Results!J:J, A32, Results!B:B, 1) -> 0 | E32: =IF(C32=0, 0, D32/C32) -> 0 | F32: =COUNTIFS(Results!J:J, A32, Results!I:I, $F$1) -> 0 | G32: =COUNTIFS(Results!J:J, A32, Results!B:B, 1, Results!I:I, $F$1) + COUNTIFS(Results!J:J, A32, Results!B:B, 0, Results!I:I, $F$1) -> 0 | H32: =COUNTIFS(Results!I:I, $F$1,Results!J:J, A32, Results!B:B, 1) -> 0 | I32: =IFERROR(H32/G32, 0) -> 0 | J32: =COUNTIFS(Results!J:J, A32, Results!I:I, "casEN") + COUNTIFS(Results!J:J, A32, Results!I:I, "casEN_opti") -> 64 | K32: =COUNTIFS(Results!J:J, A32, Results!B:B, 1, Results!I:I, "casEN") + COUNTIFS(Results!J:J, A32, Results!B:B, 0, Results!I:I, "casEN") + COUNTIFS(Results!J:J, A32, Results!B:B, 1, Results!I:I, "casEN_opti") + COUNTIFS(Results!J:J, A32, Results!B:B, 0, Results!I:I, "casEN_opti") -> 0 | L32: =COUNTIFS(Results!I:I, "casEN",Results!J:J, A32, Results!B:B, 1) + COUNTIFS(Results!I:I, "casEN_opti",Results!J:J, A32, Results!B:B, 1) -> 0 | M32: =IFERROR(L32/K32, 0) -> 0 | N32: =(NER!$L$11+graphs_analyses!L32)/(graphs_analyses!K32 +NER!$K$11) - NER!$M$11 -> 0 | R32: grfpersContextePersonne | S32: grftagNomFamille | T32: =COUNTIFS(Results!J:J, R32, Results!K:K, S32) -> 324 | U32: =COUNTIFS(Results!J:J, R32,Results!K:K, S32, Results!B:B, 1) + COUNTIFS(Results!J:J, R32,Results!K:K, S32, Results!B:B, 0) -> 324 | V32: =COUNTIFS(Results!J:J, R32, Results!K:K, S32, Results!B:B, 1) -> 305 | W32: =IFERROR(V32/U32, 0) -> 0.94135802 | X32: =COUNTIFS(Results!J:J, R32, Results!K:K, S32, Results!I:I, $X$1) -> 157 | Y32: =COUNTIFS(Results!J:J, R32,Results!K:K, S32, Results!I:I, $X$1, Results!B:B, 1) + COUNTIFS(Results!J:J, R32,Results!K:K, S32,Results!I:I, $X$1, Results!B:B, 0) -> 157 | Z32: =COUNTIFS(Results!J:J, R32, Results!K:K, S32, Results!I:I, $X$1, Results!B:B, 1) -> 156 | AA32: =IFERROR(Z32/Y32, 0) -> 0.99363057 | AB32: =COUNTIFS(Results!J:J, R32,Results!K:K, S32, Results!I:I, "casEN") + COUNTIFS(Results!J:J, R32,Results!K:K, S32, Results!I:I, "casEN_opti") -> 49 | AC32: =COUNTIFS(Results!J:J, R32,Results!K:K, S32, Results!B:B, 1, Results!I:I, "casEN") + COUNTIFS(Results!J:J, R32,Results!K:K, S32, Results!B:B, 0, Results!I:I, "casEN") + COUNTIFS(Results!J:J, R32,Results!K:K, S32, Results!B:B, 1, Results!I:I, "casEN_opti") + COUNTIFS(Results!J:J, R32,Results!K:K, S32, Results!B:B, 0, Results!I:I, "casEN_opti") -> 49 | AD32: =COUNTIFS(Results!J:J, R32,Results!K:K, S32, Results!B:B, 1, Results!I:I, "casEN") + COUNTIFS(Results!J:J, R32,Results!K:K, S32, Results!B:B, 1, Results!I:I, "casEN_opti") -> 37 | AE32: =IFERROR(AD32/AC32, 0) -> 0.75510204 | AF32: =(NER!$L$11+graphs_analyses!AD32)/(graphs_analyses!AC32 +NER!$K$11) - NER!$M$11 -> -0.0015229463
A33: grforgJustice | B33: =COUNTIF(Results!J:J, A33) -> 6 | C33: =COUNTIFS(Results!J:J, A33, Results!B:B, 1) + COUNTIFS(Results!J:J, A33, Results!B:B, 0) -> 0 | D33: =COUNTIFS(Results!J:J, A33, Results!B:B, 1) -> 0 | E33: =IF(C33=0, 0, D33/C33) -> 0 | F33: =COUNTIFS(Results!J:J, A33, Results!I:I, $F$1) -> 0 | G33: =COUNTIFS(Results!J:J, A33, Results!B:B, 1, Results!I:I, $F$1) + COUNTIFS(Results!J:J, A33, Results!B:B, 0, Results!I:I, $F$1) -> 0 | H33: =COUNTIFS(Results!I:I, $F$1,Results!J:J, A33, Results!B:B, 1) -> 0 | I33: =IFERROR(H33/G33, 0) -> 0 | J33: =COUNTIFS(Results!J:J, A33, Results!I:I, "casEN") + COUNTIFS(Results!J:J, A33, Results!I:I, "casEN_opti") -> 6 | K33: =COUNTIFS(Results!J:J, A33, Results!B:B, 1, Results!I:I, "casEN") + COUNTIFS(Results!J:J, A33, Results!B:B, 0, Results!I:I, "casEN") + COUNTIFS(Results!J:J, A33, Results!B:B, 1, Results!I:I, "casEN_opti") + COUNTIFS(Results!J:J, A33, Results!B:B, 0, Results!I:I, "casEN_opti") -> 0 | L33: =COUNTIFS(Results!I:I, "casEN",Results!J:J, A33, Results!B:B, 1) + COUNTIFS(Results!I:I, "casEN_opti",Results!J:J, A33, Results!B:B, 1) -> 0 | M33: =IFERROR(L33/K33, 0) -> 0 | N33: =(NER!$L$11+graphs_analyses!L33)/(graphs_analyses!K33 +NER!$K$11) - NER!$M$11 -> 0 | R33: grfpersPrenomNom | S33: grftagPrenom | T33: =COUNTIFS(Results!J:J, R33, Results!K:K, S33) -> 2299 | U33: =COUNTIFS(Results!J:J, R33,Results!K:K, S33, Results!B:B, 1) + COUNTIFS(Results!J:J, R33,Results!K:K, S33, Results!B:B, 0) -> 2294 | V33: =COUNTIFS(Results!J:J, R33, Results!K:K, S33, Results!B:B, 1) -> 2118 | W33: =IFERROR(V33/U33, 0) -> 0.92327812 | X33: =COUNTIFS(Results!J:J, R33, Results!K:K, S33, Results!I:I, $X$1) -> 1822 | Y33: =COUNTIFS(Results!J:J, R33,Results!K:K, S33, Results!I:I, $X$1, Results!B:B, 1) + COUNTIFS(Results!J:J, R33,Results!K:K, S33,Results!I:I, $X$1, Results!B:B, 0) -> 1822 | Z33: =COUNTIFS(Results!J:J, R33, Results!K:K, S33, Results!I:I, $X$1, Results!B:B, 1) -> 1813 | AA33: =IFERROR(Z33/Y33, 0) -> 0.99506037 | AB33: =COUNTIFS(Results!J:J, R33,Results!K:K, S33, Results!I:I, "casEN") + COUNTIFS(Results!J:J, R33,Results!K:K, S33, Results!I:I, "casEN_opti") -> 197 | AC33: =COUNTIFS(Results!J:J, R33,Results!K:K, S33, Results!B:B, 1, Results!I:I, "casEN") + COUNTIFS(Results!J:J, R33,Results!K:K, S33, Results!B:B, 0, Results!I:I, "casEN") + COUNTIFS(Results!J:J, R33,Results!K:K, S33, Results!B:B, 1, Results!I:I, "casEN_opti") + COUNTIFS(Results!J:J, R33,Results!K:K, S33, Results!B:B, 0, Results!I:I, "casEN_opti") -> 192 | AD33: =COUNTIFS(Results!J:J, R33,Results!K:K, S33, Results!B:B, 1, Results!I:I, "casEN") + COUNTIFS(Results!J:J, R33,Results!K:K, S33, Results!B:B, 1, Results!I:I, "casEN_opti") -> 54 | AE33: =IFERROR(AD33/AC33, 0) -> 0.28125 | AF33: =(NER!$L$11+graphs_analyses!AD33)/(graphs_analyses!AC33 +NER!$K$11) - NER!$M$11 -> -0.018584885
A34: grforgFinance | B34: =COUNTIF(Results!J:J, A34) -> 12 | C34: =COUNTIFS(Results!J:J, A34, Results!B:B, 1) + COUNTIFS(Results!J:J, A34, Results!B:B, 0) -> 0 | D34: =COUNTIFS(Results!J:J, A34, Results!B:B, 1) -> 0 | E34: =IF(C34=0, 0, D34/C34) -> 0 | F34: =COUNTIFS(Results!J:J, A34, Results!I:I, $F$1) -> 0 | G34: =COUNTIFS(Results!J:J, A34, Results!B:B, 1, Results!I:I, $F$1) + COUNTIFS(Results!J:J, A34, Results!B:B, 0, Results!I:I, $F$1) -> 0 | H34: =COUNTIFS(Results!I:I, $F$1,Results!J:J, A34, Results!B:B, 1) -> 0 | I34: =IFERROR(H34/G34, 0) -> 0 | J34: =COUNTIFS(Results!J:J, A34, Results!I:I, "casEN") + COUNTIFS(Results!J:J, A34, Results!I:I, "casEN_opti") -> 12 | K34: =COUNTIFS(Results!J:J, A34, Results!B:B, 1, Results!I:I, "casEN") + COUNTIFS(Results!J:J, A34, Results!B:B, 0, Results!I:I, "casEN") + COUNTIFS(Results!J:J, A34, Results!B:B, 1, Results!I:I, "casEN_opti") + COUNTIFS(Results!J:J, A34, Results!B:B, 0, Results!I:I, "casEN_opti") -> 0 | L34: =COUNTIFS(Results!I:I, "casEN",Results!J:J, A34, Results!B:B, 1) + COUNTIFS(Results!I:I, "casEN_opti",Results!J:J, A34, Results!B:B, 1) -> 0 | M34: =IFERROR(L34/K34, 0) -> 0 | N34: =(NER!$L$11+graphs_analyses!L34)/(graphs_analyses!K34 +NER!$K$11) - NER!$M$11 -> 0 | R34: grfpersPrenomNom | S34: grftagNomFamilleParticule | T34: =COUNTIFS(Results!J:J, R34, Results!K:K, S34) -> 25 | U34: =COUNTIFS(Results!J:J, R34,Results!K:K, S34, Results!B:B, 1) + COUNTIFS(Results!J:J, R34,Results!K:K, S34, Results!B:B, 0) -> 25 | V34: =COUNTIFS(Results!J:J, R34, Results!K:K, S34, Results!B:B, 1) -> 12 | W34: =IFERROR(V34/U34, 0) -> 0.48 | X34: =COUNTIFS(Results!J:J, R34, Results!K:K, S34, Results!I:I, $X$1) -> 10 | Y34: =COUNTIFS(Results!J:J, R34,Results!K:K, S34, Results!I:I, $X$1, Results!B:B, 1) + COUNTIFS(Results!J:J, R34,Results!K:K, S34,Results!I:I, $X$1, Results!B:B, 0) -> 10 | Z34: =COUNTIFS(Results!J:J, R34, Results!K:K, S34, Results!I:I, $X$1, Results!B:B, 1) -> 9 | AA34: =IFERROR(Z34/Y34, 0) -> 0.9 | AB34: =COUNTIFS(Results!J:J, R34,Results!K:K, S34, Results!I:I, "casEN") + COUNTIFS(Results!J:J, R34,Results!K:K, S34, Results!I:I, "casEN_opti") -> 12 | AC34: =COUNTIFS(Results!J:J, R34,Results!K:K, S34, Results!B:B, 1, Results!I:I, "casEN") + COUNTIFS(Results!J:J, R34,Results!K:K, S34, Results!B:B, 0, Results!I:I, "casEN") + COUNTIFS(Results!J:J, R34,Results!K:K, S34, Results!B:B, 1, Results!I:I, "casEN_opti") + COUNTIFS(Results!J:J, R34,Results!K:K, S34, Results!B:B, 0, Results!I:I, "casEN_opti") -> 12 | AD34: =COUNTIFS(Results!J:J, R34,Results!K:K, S34, Results!B:B, 1, Results!I:I, "casEN") + COUNTIFS(Results!J:J, R34,Results!K:K, S34, Results!B:B, 1, Results!I:I, "casEN_opti") -> 1 | AE34: =IFERROR(AD34/AC34, 0) -> 0.083333333 | AF34: =(NER!$L$11+graphs_analyses!AD34)/(graphs_analyses!AC34 +NER!$K$11) - NER!$M$11 -> -0.0015326712
A35: grfplace2org | B35: =COUNTIF(Results!J:J, A35) -> 1 | C35: =COUNTIFS(Results!J:J, A35, Results!B:B, 1) + COUNTIFS(Results!J:J, A35, Results!B:B, 0) -> 0 | D35: =COUNTIFS(Results!J:J, A35, Results!B:B, 1) -> 0 | E35: =IF(C35=0, 0, D35/C35) -> 0 | F35: =COUNTIFS(Results!J:J, A35, Results!I:I, $F$1) -> 0 | G35: =COUNTIFS(Results!J:J, A35, Results!B:B, 1, Results!I:I, $F$1) + COUNTIFS(Results!J:J, A35, Results!B:B, 0, Results!I:I, $F$1) -> 0 | H35: =COUNTIFS(Results!I:I, $F$1,Results!J:J, A35, Results!B:B, 1) -> 0 | I35: =IFERROR(H35/G35, 0) -> 0 | J35: =COUNTIFS(Results!J:J, A35, Results!I:I, "casEN") + COUNTIFS(Results!J:J, A35, Results!I:I, "casEN_opti") -> 1 | K35: =COUNTIFS(Results!J:J, A35, Results!B:B, 1, Results!I:I, "casEN") + COUNTIFS(Results!J:J, A35, Results!B:B, 0, Results!I:I, "casEN") + COUNTIFS(Results!J:J, A35, Results!B:B, 1, Results!I:I, "casEN_opti") + COUNTIFS(Results!J:J, A35, Results!B:B, 0, Results!I:I, "casEN_opti") -> 0 | L35: =COUNTIFS(Results!I:I, "casEN",Results!J:J, A35, Results!B:B, 1) + COUNTIFS(Results!I:I, "casEN_opti",Results!J:J, A35, Results!B:B, 1) -> 0 | M35: =IFERROR(L35/K35, 0) -> 0 | N35: =(NER!$L$11+graphs_analyses!L35)/(graphs_analyses!K35 +NER!$K$11) - NER!$M$11 -> 0 | R35: grfpersPrenomNom | S35: grftagParticule | T35: =COUNTIFS(Results!J:J, R35, Results!K:K, S35) -> 23 | U35: =COUNTIFS(Results!J:J, R35,Results!K:K, S35, Results!B:B, 1) + COUNTIFS(Results!J:J, R35,Results!K:K, S35, Results!B:B, 0) -> 23 | V35: =COUNTIFS(Results!J:J, R35, Results!K:K, S35, Results!B:B, 1) -> 16 | W35: =IFERROR(V35/U35, 0) -> 0.69565217 | X35: =COUNTIFS(Results!J:J, R35, Results!K:K, S35, Results!I:I, $X$1) -> 13 | Y35: =COUNTIFS(Results!J:J, R35,Results!K:K, S35, Results!I:I, $X$1, Results!B:B, 1) + COUNTIFS(Results!J:J, R35,Results!K:K, S35,Results!I:I, $X$1, Results!B:B, 0) -> 13 | Z35: =COUNTIFS(Results!J:J, R35, Results!K:K, S35, Results!I:I, $X$1, Results!B:B, 1) -> 12 | AA35: =IFERROR(Z35/Y35, 0) -> 0.92307692 | AB35: =COUNTIFS(Results!J:J, R35,Results!K:K, S35, Results!I:I, "casEN") + COUNTIFS(Results!J:J, R35,Results!K:K, S35, Results!I:I, "casEN_opti") -> 6 | AC35: =COUNTIFS(Results!J:J, R35,Results!K:K, S35, Results!B:B, 1, Results!I:I, "casEN") + COUNTIFS(Results!J:J, R35,Results!K:K, S35, Results!B:B, 0, Results!I:I, "casEN") + COUNTIFS(Results!J:J, R35,Results!K:K, S35, Results!B:B, 1, Results!I:I, "casEN_opti") + COUNTIFS(Results!J:J, R35,Results!K:K, S35, Results!B:B, 0, Results!I:I, "casEN_opti") -> 6 | AD35: =COUNTIFS(Results!J:J, R35,Results!K:K, S35, Results!B:B, 1, Results!I:I, "casEN") + COUNTIFS(Results!J:J, R35,Results!K:K, S35, Results!B:B, 1, Results!I:I, "casEN_opti") -> 1 | AE35: =IFERROR(AD35/AC35, 0) -> 0.16666667 | AF35: =(NER!$L$11+graphs_analyses!AD35)/(graphs_analyses!AC35 +NER!$K$11) - NER!$M$11 -> -0.00069512647
A36: grforgAssemblee | B36: =COUNTIF(Results!J:J, A36) -> 2 | C36: =COUNTIFS(Results!J:J, A36, Results!B:B, 1) + COUNTIFS(Results!J:J, A36, Results!B:B, 0) -> 2 | D36: =COUNTIFS(Results!J:J, A36, Results!B:B, 1) -> 2 | E36: =IF(C36=0, 0, D36/C36) -> 1 | F36: =COUNTIFS(Results!J:J, A36, Results!I:I, $F$1) -> 2 | G36: =COUNTIFS(Results!J:J, A36, Results!B:B, 1, Results!I:I, $F$1) + COUNTIFS(Results!J:J, A36, Results!B:B, 0, Results!I:I, $F$1) -> 2 | H36: =COUNTIFS(Results!I:I, $F$1,Results!J:J, A36, Results!B:B, 1) -> 2 | I36: =IFERROR(H36/G36, 0) -> 1 | J36: =COUNTIFS(Results!J:J, A36, Results!I:I, "casEN") + COUNTIFS(Results!J:J, A36, Results!I:I, "casEN_opti") -> 0 | K36: =COUNTIFS(Results!J:J, A36, Results!B:B, 1, Results!I:I, "casEN") + COUNTIFS(Results!J:J, A36, Results!B:B, 0, Results!I:I, "casEN") + COUNTIFS(Results!J:J, A36, Results!B:B, 1, Results!I:I, "casEN_opti") + COUNTIFS(Results!J:J, A36, Results!B:B, 0, Results!I:I, "casEN_opti") -> 0 | L36: =COUNTIFS(Results!I:I, "casEN",Results!J:J, A36, Results!B:B, 1) + COUNTIFS(Results!I:I, "casEN_opti",Results!J:J, A36, Results!B:B, 1) -> 0 | M36: =IFERROR(L36/K36, 0) -> 0 | N36: =(NER!$L$11+graphs_analyses!L36)/(graphs_analyses!K36 +NER!$K$11) - NER!$M$11 -> 0 | R36: grfpersPrenomNom | S36: grftagNumRegne | T36: =COUNTIFS(Results!J:J, R36, Results!K:K, S36) -> 12 | U36: =COUNTIFS(Results!J:J, R36,Results!K:K, S36, Results!B:B, 1) + COUNTIFS(Results!J:J, R36,Results!K:K, S36, Results!B:B, 0) -> 12 | V36: =COUNTIFS(Results!J:J, R36, Results!K:K, S36, Results!B:B, 1) -> 1 | W36: =IFERROR(V36/U36, 0) -> 0.083333333 | X36: =COUNTIFS(Results!J:J, R36, Results!K:K, S36, Results!I:I, $X$1) -> 0 | Y36: =COUNTIFS(Results!J:J, R36,Results!K:K, S36, Results!I:I, $X$1, Results!B:B, 1) + COUNTIFS(Results!J:J, R36,Results!K:K, S36,Results!I:I, $X$1, Results!B:B, 0) -> 0 | Z36: =COUNTIFS(Results!J:J, R36, Results!K:K, S36, Results!I:I, $X$1, Results!B:B, 1) -> 0 | AA36: =IFERROR(Z36/Y36, 0) -> 0 | AB36: =COUNTIFS(Results!J:J, R36,Results!K:K, S36, Results!I:I, "casEN") + COUNTIFS(Results!J:J, R36,Results!K:K, S36, Results!I:I, "casEN_opti") -> 12 | AC36: =COUNTIFS(Results!J:J, R36,Results!K:K, S36, Results!B:B, 1, Results!I:I, "casEN") + COUNTIFS(Results!J:J, R36,Results!K:K, S36, Results!B:B, 0, Results!I:I, "casEN") + COUNTIFS(Results!J:J, R36,Results!K:K, S36, Results!B:B, 1, Results!I:I, "casEN_opti") + COUNTIFS(Results!J:J, R36,Results!K:K, S36, Results!B:B, 0, Results!I:I, "casEN_opti") -> 12 | AD36: =COUNTIFS(Results!J:J, R36,Results!K:K, S36, Results!B:B, 1, Results!I:I, "casEN") + COUNTIFS(Results!J:J, R36,Results!K:K, S36, Results!B:B, 1, Results!I:I, "casEN_opti") -> 1 | AE36: =IFERROR(AD36/AC36, 0) -> 0.083333333 | AF36: =(NER!$L$11+graphs_analyses!AD36)/(graphs_analyses!AC36 +NER!$K$11) - NER!$M$11 -> -0.0015326712
A37: grftagOrgFunder | B37: =COUNTIF(Results!J:J, A37) -> 13 | C37: =COUNTIFS(Results!J:J, A37, Results!B:B, 1) + COUNTIFS(Results!J:J, A37, Results!B:B, 0) -> 11 | D37: =COUNTIFS(Results!J:J, A37, Results!B:B, 1) -> 0 | E37: =IF(C37=0, 0, D37/C37) -> 0 | F37: =COUNTIFS(Results!J:J, A37, Results!I:I, $F$1) -> 0 | G37: =COUNTIFS(Results!J:J, A37, Results!B:B, 1, Results!I:I, $F$1) + COUNTIFS(Results!J:J, A37, Results!B:B, 0, Results!I:I, $F$1) -> 0 | H37: =COUNTIFS(Results!I:I, $F$1,Results!J:J, A37, Results!B:B, 1) -> 0 | I37: =IFERROR(H37/G37, 0) -> 0 | J37: =COUNTIFS(Results!J:J, A37, Results!I:I, "casEN") + COUNTIFS(Results!J:J, A37, Results!I:I, "casEN_opti") -> 13 | K37: =COUNTIFS(Results!J:J, A37, Results!B:B, 1, Results!I:I, "casEN") + COUNTIFS(Results!J:J, A37, Results!B:B, 0, Results!I:I, "casEN") + COUNTIFS(Results!J:J, A37, Results!B:B, 1, Results!I:I, "casEN_opti") + COUNTIFS(Results!J:J, A37, Results!B:B, 0, Results!I:I, "casEN_opti") -> 11 | L37: =COUNTIFS(Results!I:I, "casEN",Results!J:J, A37, Results!B:B, 1) + COUNTIFS(Results!I:I, "casEN_opti",Results!J:J, A37, Results!B:B, 1) -> 0 | M37: =IFERROR(L37/K37, 0) -> 0 | N37: =(NER!$L$11+graphs_analyses!L37)/(graphs_analyses!K37 +NER!$K$11) - NER!$M$11 -> -0.0015368176 | R37: grfplace | S37: grfplaceBatiment | T37: =COUNTIFS(Results!J:J, R37, Results!K:K, S37) -> 92 | U37: =COUNTIFS(Results!J:J, R37,Results!K:K, S37, Results!B:B, 1) + COUNTIFS(Results!J:J, R37,Results!K:K, S37, Results!B:B, 0) -> 89 | V37: =COUNTIFS(Results!J:J, R37, Results!K:K, S37, Results!B:B, 1) -> 43 | W37: =IFERROR(V37/U37, 0) -> 0.48314607 | X37: =COUNTIFS(Results!J:J, R37, Results!K:K, S37, Results!I:I, $X$1) -> 15 | Y37: =COUNTIFS(Results!J:J, R37,Results!K:K, S37, Results!I:I, $X$1, Results!B:B, 1) + COUNTIFS(Results!J:J, R37,Results!K:K, S37,Results!I:I, $X$1, Results!B:B, 0) -> 15 | Z37: =COUNTIFS(Results!J:J, R37, Results!K:K, S37, Results!I:I, $X$1, Results!B:B, 1) -> 15 | AA37: =IFERROR(Z37/Y37, 0) -> 1 | AB37: =COUNTIFS(Results!J:J, R37,Results!K:K, S37, Results!I:I, "casEN") + COUNTIFS(Results!J:J, R37,Results!K:K, S37, Results!I:I, "casEN_opti") -> 72 | AC37: =COUNTIFS(Results!J:J, R37,Results!K:K, S37, Results!B:B, 1, Results!I:I, "casEN") + COUNTIFS(Results!J:J, R37,Results!K:K, S37, Results!B:B, 0, Results!I:I, "casEN") + COUNTIFS(Results!J:J, R37,Results!K:K, S37, Results!B:B, 1, Results!I:I, "casEN_opti") + COUNTIFS(Results!J:J, R37,Results!K:K, S37, Results!B:B, 0, Results!I:I, "casEN_opti") -> 69 | AD37: =COUNTIFS(Results!J:J, R37,Results!K:K, S37, Results!B:B, 1, Results!I:I, "casEN") + COUNTIFS(Results!J:J, R37,Results!K:K, S37, Results!B:B, 1, Results!I:I, "casEN_opti") -> 23 | AE37: =IFERROR(AD37/AC37, 0) -> 0.33333333 | AF37: =(NER!$L$11+graphs_analyses!AD37)/(graphs_analyses!AC37 +NER!$K$11) - NER!$M$11 -> -0.0062840371
A38: grftagOrgNameEntreprise | B38: =COUNTIF(Results!J:J, A38) -> 3 | C38: =COUNTIFS(Results!J:J, A38, Results!B:B, 1) + COUNTIFS(Results!J:J, A38, Results!B:B, 0) -> 3 | D38: =COUNTIFS(Results!J:J, A38, Results!B:B, 1) -> 3 | E38: =IF(C38=0, 0, D38/C38) -> 1 | F38: =COUNTIFS(Results!J:J, A38, Results!I:I, $F$1) -> 0 | G38: =COUNTIFS(Results!J:J, A38, Results!B:B, 1, Results!I:I, $F$1) + COUNTIFS(Results!J:J, A38, Results!B:B, 0, Results!I:I, $F$1) -> 0 | H38: =COUNTIFS(Results!I:I, $F$1,Results!J:J, A38, Results!B:B, 1) -> 0 | I38: =IFERROR(H38/G38, 0) -> 0 | J38: =COUNTIFS(Results!J:J, A38, Results!I:I, "casEN") + COUNTIFS(Results!J:J, A38, Results!I:I, "casEN_opti") -> 2 | K38: =COUNTIFS(Results!J:J, A38, Results!B:B, 1, Results!I:I, "casEN") + COUNTIFS(Results!J:J, A38, Results!B:B, 0, Results!I:I, "casEN") + COUNTIFS(Results!J:J, A38, Results!B:B, 1, Results!I:I, "casEN_opti") + COUNTIFS(Results!J:J, A38, Results!B:B, 0, Results!I:I, "casEN_opti") -> 2 | L38: =COUNTIFS(Results!I:I, "casEN",Results!J:J, A38, Results!B:B, 1) + COUNTIFS(Results!I:I, "casEN_opti",Results!J:J, A38, Results!B:B, 1) -> 2 | M38: =IFERROR(L38/K38, 0) -> 1 | N38: =(NER!$L$11+graphs_analyses!L38)/(graphs_analyses!K38 +NER!$K$11) - NER!$M$11 -> 7.8625619e-06 | R38: grfplace | S38: grfplaceQuartier | T38: =COUNTIFS(Results!J:J, R38, Results!K:K, S38) -> 17 | U38: =COUNTIFS(Results!J:J, R38,Results!K:K, S38, Results!B:B, 1) + COUNTIFS(Results!J:J, R38,Results!K:K, S38, Results!B:B, 0) -> 16 | V38: =COUNTIFS(Results!J:J, R38, Results!K:K, S38, Results!B:B, 1) -> 13 | W38: =IFERROR(V38/U38, 0) -> 0.8125 | X38: =COUNTIFS(Results!J:J, R38, Results!K:K, S38, Results!I:I, $X$1) -> 0 | Y38: =COUNTIFS(Results!J:J, R38,Results!K:K, S38, Results!I:I, $X$1, Results!B:B, 1) + COUNTIFS(Results!J:J, R38,Results!K:K, S38,Results!I:I, $X$1, Results!B:B, 0) -> 0 | Z38: =COUNTIFS(Results!J:J, R38, Results!K:K, S38, Results!I:I, $X$1, Results!B:B, 1) -> 0 | AA38: =IFERROR(Z38/Y38, 0) -> 0 | AB38: =COUNTIFS(Results!J:J, R38,Results!K:K, S38, Results!I:I, "casEN") + COUNTIFS(Results!J:J, R38,Results!K:K, S38, Results!I:I, "casEN_opti") -> 17 | AC38: =COUNTIFS(Results!J:J, R38,Results!K:K, S38, Results!B:B, 1, Results!I:I, "casEN") + COUNTIFS(Results!J:J, R38,Results!K:K, S38, Results!B:B, 0, Results!I:I, "casEN") + COUNTIFS(Results!J:J, R38,Results!K:K, S38, Results!B:B, 1, Results!I:I, "casEN_opti") + COUNTIFS(Results!J:J, R38,Results!K:K, S38, Results!B:B, 0, Results!I:I, "casEN_opti") -> 16 | AD38: =COUNTIFS(Results!J:J, R38,Results!K:K, S38, Results!B:B, 1, Results!I:I, "casEN") + COUNTIFS(Results!J:J, R38,Results!K:K, S38, Results!B:B, 1, Results!I:I, "casEN_opti") -> 13 | AE38: =IFERROR(AD38/AC38, 0) -> 0.8125 | AF38: =(NER!$L$11+graphs_analyses!AD38)/(graphs_analyses!AC38 +NER!$K$11) - NER!$M$11 -> -0.00036782731
A39: grfgeogRiviere | B39: =COUNTIF(Results!J:J, A39) -> 1 | C39: =COUNTIFS(Results!J:J, A39, Results!B:B, 1) + COUNTIFS(Results!J:J, A39, Results!B:B, 0) -> 1 | D39: =COUNTIFS(Results!J:J, A39, Results!B:B, 1) -> 1 | E39: =IF(C39=0, 0, D39/C39) -> 1 | F39: =COUNTIFS(Results!J:J, A39, Results!I:I, $F$1) -> 1 | G39: =COUNTIFS(Results!J:J, A39, Results!B:B, 1, Results!I:I, $F$1) + COUNTIFS(Results!J:J, A39, Results!B:B, 0, Results!I:I, $F$1) -> 1 | H39: =COUNTIFS(Results!I:I, $F$1,Results!J:J, A39, Results!B:B, 1) -> 1 | I39: =IFERROR(H39/G39, 0) -> 1 | J39: =COUNTIFS(Results!J:J, A39, Results!I:I, "casEN") + COUNTIFS(Results!J:J, A39, Results!I:I, "casEN_opti") -> 0 | K39: =COUNTIFS(Results!J:J, A39, Results!B:B, 1, Results!I:I, "casEN") + COUNTIFS(Results!J:J, A39, Results!B:B, 0, Results!I:I, "casEN") + COUNTIFS(Results!J:J, A39, Results!B:B, 1, Results!I:I, "casEN_opti") + COUNTIFS(Results!J:J, A39, Results!B:B, 0, Results!I:I, "casEN_opti") -> 0 | L39: =COUNTIFS(Results!I:I, "casEN",Results!J:J, A39, Results!B:B, 1) + COUNTIFS(Results!I:I, "casEN_opti",Results!J:J, A39, Results!B:B, 1) -> 0 | M39: =IFERROR(L39/K39, 0) -> 0 | N39: =(NER!$L$11+graphs_analyses!L39)/(graphs_analyses!K39 +NER!$K$11) - NER!$M$11 -> 0 | R39: grfplace | S39: grfplaceRoutes | T39: =COUNTIFS(Results!J:J, R39, Results!K:K, S39) -> 2 | U39: =COUNTIFS(Results!J:J, R39,Results!K:K, S39, Results!B:B, 1) + COUNTIFS(Results!J:J, R39,Results!K:K, S39, Results!B:B, 0) -> 1 | V39: =COUNTIFS(Results!J:J, R39, Results!K:K, S39, Results!B:B, 1) -> 1 | W39: =IFERROR(V39/U39, 0) -> 1 | X39: =COUNTIFS(Results!J:J, R39, Results!K:K, S39, Results!I:I, $X$1) -> 0 | Y39: =COUNTIFS(Results!J:J, R39,Results!K:K, S39, Results!I:I, $X$1, Results!B:B, 1) + COUNTIFS(Results!J:J, R39,Results!K:K, S39,Results!I:I, $X$1, Results!B:B, 0) -> 0 | Z39: =COUNTIFS(Results!J:J, R39, Results!K:K, S39, Results!I:I, $X$1, Results!B:B, 1) -> 0 | AA39: =IFERROR(Z39/Y39, 0) -> 0 | AB39: =COUNTIFS(Results!J:J, R39,Results!K:K, S39, Results!I:I, "casEN") + COUNTIFS(Results!J:J, R39,Results!K:K, S39, Results!I:I, "casEN_opti") -> 2 | AC39: =COUNTIFS(Results!J:J, R39,Results!K:K, S39, Results!B:B, 1, Results!I:I, "casEN") + COUNTIFS(Results!J:J, R39,Results!K:K, S39, Results!B:B, 0, Results!I:I, "casEN") + COUNTIFS(Results!J:J, R39,Results!K:K, S39, Results!B:B, 1, Results!I:I, "casEN_opti") + COUNTIFS(Results!J:J, R39,Results!K:K, S39, Results!B:B, 0, Results!I:I, "casEN_opti") -> 1 | AD39: =COUNTIFS(Results!J:J, R39,Results!K:K, S39, Results!B:B, 1, Results!I:I, "casEN") + COUNTIFS(Results!J:J, R39,Results!K:K, S39, Results!B:B, 1, Results!I:I, "casEN_opti") -> 1 | AE39: =IFERROR(AD39/AC39, 0) -> 1 | AF39: =(NER!$L$11+graphs_analyses!AD39)/(graphs_analyses!AC39 +NER!$K$11) - NER!$M$11 -> 3.9318464e-06
A40: grforgSuiviDeParentheses | B40: =COUNTIF(Results!J:J, A40) -> 2 | C40: =COUNTIFS(Results!J:J, A40, Results!B:B, 1) + COUNTIFS(Results!J:J, A40, Results!B:B, 0) -> 2 | D40: =COUNTIFS(Results!J:J, A40, Results!B:B, 1) -> 2 | E40: =IF(C40=0, 0, D40/C40) -> 1 | F40: =COUNTIFS(Results!J:J, A40, Results!I:I, $F$1) -> 2 | G40: =COUNTIFS(Results!J:J, A40, Results!B:B, 1, Results!I:I, $F$1) + COUNTIFS(Results!J:J, A40, Results!B:B, 0, Results!I:I, $F$1) -> 2 | H40: =COUNTIFS(Results!I:I, $F$1,Results!J:J, A40, Results!B:B, 1) -> 2 | I40: =IFERROR(H40/G40, 0) -> 1 | J40: =COUNTIFS(Results!J:J, A40, Results!I:I, "casEN") + COUNTIFS(Results!J:J, A40, Results!I:I, "casEN_opti") -> 0 | K40: =COUNTIFS(Results!J:J, A40, Results!B:B, 1, Results!I:I, "casEN") + COUNTIFS(Results!J:J, A40, Results!B:B, 0, Results!I:I, "casEN") + COUNTIFS(Results!J:J, A40, Results!B:B, 1, Results!I:I, "casEN_opti") + COUNTIFS(Results!J:J, A40, Results!B:B, 0, Results!I:I, "casEN_opti") -> 0 | L40: =COUNTIFS(Results!I:I, "casEN",Results!J:J, A40, Results!B:B, 1) + COUNTIFS(Results!I:I, "casEN_opti",Results!J:J, A40, Results!B:B, 1) -> 0 | M40: =IFERROR(L40/K40, 0) -> 0 | N40: =(NER!$L$11+graphs_analyses!L40)/(graphs_analyses!K40 +NER!$K$11) - NER!$M$11 -> 0 | R40: grfplace2org | S40: grfgeog | T40: =COUNTIFS(Results!J:J, R40, Results!K:K, S40) -> 1 | U40: =COUNTIFS(Results!J:J, R40,Results!K:K, S40, Results!B:B, 1) + COUNTIFS(Results!J:J, R40,Results!K:K, S40, Results!B:B, 0) -> 0 | V40: =COUNTIFS(Results!J:J, R40, Results!K:K, S40, Results!B:B, 1) -> 0 | W40: =IFERROR(V40/U40, 0) -> 0 | X40: =COUNTIFS(Results!J:J, R40, Results!K:K, S40, Results!I:I, $X$1) -> 0 | Y40: =COUNTIFS(Results!J:J, R40,Results!K:K, S40, Results!I:I, $X$1, Results!B:B, 1) + COUNTIFS(Results!J:J, R40,Results!K:K, S40,Results!I:I, $X$1, Results!B:B, 0) -> 0 | Z40: =COUNTIFS(Results!J:J, R40, Results!K:K, S40, Results!I:I, $X$1, Results!B:B, 1) -> 0 | AA40: =IFERROR(Z40/Y40, 0) -> 0 | AB40: =COUNTIFS(Results!J:J, R40,Results!K:K, S40, Results!I:I, "casEN") + COUNTIFS(Results!J:J, R40,Results!K:K, S40, Results!I:I, "casEN_opti") -> 1 | AC40: =COUNTIFS(Results!J:J, R40,Results!K:K, S40, Results!B:B, 1, Results!I:I, "casEN") + COUNTIFS(Results!J:J, R40,Results!K:K, S40, Results!B:B, 0, Results!I:I, "casEN") + COUNTIFS(Results!J:J, R40,Results!K:K, S40, Results!B:B, 1, Results!I:I, "casEN_opti") + COUNTIFS(Results!J:J, R40,Results!K:K, S40, Results!B:B, 0, Results!I:I, "casEN_opti") -> 0 | AD40: =COUNTIFS(Results!J:J, R40,Results!K:K, S40, Results!B:B, 1, Results!I:I, "casEN") + COUNTIFS(Results!J:J, R40,Results!K:K, S40, Results!B:B, 1, Results!I:I, "casEN_opti") -> 0 | AE40: =IFERROR(AD40/AC40, 0) -> 0 | AF40: =(NER!$L$11+graphs_analyses!AD40)/(graphs_analyses!AC40 +NER!$K$11) - NER!$M$11 -> 0
R41: grfplaceRoutes | S41: grfgeog | T41: =COUNTIFS(Results!J:J, R41, Results!K:K, S41) -> 1 | U41: =COUNTIFS(Results!J:J, R41,Results!K:K, S41, Results!B:B, 1) + COUNTIFS(Results!J:J, R41,Results!K:K, S41, Results!B:B, 0) -> 1 | V41: =COUNTIFS(Results!J:J, R41, Results!K:K, S41, Results!B:B, 1) -> 1 | W41: =IFERROR(V41/U41, 0) -> 1 | X41: =COUNTIFS(Results!J:J, R41, Results!K:K, S41, Results!I:I, $X$1) -> 0 | Y41: =COUNTIFS(Results!J:J, R41,Results!K:K, S41, Results!I:I, $X$1, Results!B:B, 1) + COUNTIFS(Results!J:J, R41,Results!K:K, S41,Results!I:I, $X$1, Results!B:B, 0) -> 0 | Z41: =COUNTIFS(Results!J:J, R41, Results!K:K, S41, Results!I:I, $X$1, Results!B:B, 1) -> 0 | AA41: =IFERROR(Z41/Y41, 0) -> 0 | AB41: =COUNTIFS(Results!J:J, R41,Results!K:K, S41, Results!I:I, "casEN") + COUNTIFS(Results!J:J, R41,Results!K:K, S41, Results!I:I, "casEN_opti") -> 1 | AC41: =COUNTIFS(Results!J:J, R41,Results!K:K, S41, Results!B:B, 1, Results!I:I, "casEN") + COUNTIFS(Results!J:J, R41,Results!K:K, S41, Results!B:B, 0, Results!I:I, "casEN") + COUNTIFS(Results!J:J, R41,Results!K:K, S41, Results!B:B, 1, Results!I:I, "casEN_opti") + COUNTIFS(Results!J:J, R41,Results!K:K, S41, Results!B:B, 0, Results!I:I, "casEN_opti") -> 1 | AD41: =COUNTIFS(Results!J:J, R41,Results!K:K, S41, Results!B:B, 1, Results!I:I, "casEN") + COUNTIFS(Results!J:J, R41,Results!K:K, S41, Results!B:B, 1, Results!I:I, "casEN_opti") -> 1 | AE41: =IFERROR(AD41/AC41, 0) -> 1 | AF41: =(NER!$L$11+graphs_analyses!AD41)/(graphs_analyses!AC41 +NER!$K$11) - NER!$M$11 -> 3.9318464e-06
R42: grftagOrgFunder | S42: grfroleName | T42: =COUNTIFS(Results!J:J, R42, Results!K:K, S42) -> 8 | U42: =COUNTIFS(Results!J:J, R42,Results!K:K, S42, Results!B:B, 1) + COUNTIFS(Results!J:J, R42,Results!K:K, S42, Results!B:B, 0) -> 8 | V42: =COUNTIFS(Results!J:J, R42, Results!K:K, S42, Results!B:B, 1) -> 0 | W42: =IFERROR(V42/U42, 0) -> 0 | X42: =COUNTIFS(Results!J:J, R42, Results!K:K, S42, Results!I:I, $X$1) -> 0 | Y42: =COUNTIFS(Results!J:J, R42,Results!K:K, S42, Results!I:I, $X$1, Results!B:B, 1) + COUNTIFS(Results!J:J, R42,Results!K:K, S42,Results!I:I, $X$1, Results!B:B, 0) -> 0 | Z42: =COUNTIFS(Results!J:J, R42, Results!K:K, S42, Results!I:I, $X$1, Results!B:B, 1) -> 0 | AA42: =IFERROR(Z42/Y42, 0) -> 0 | AB42: =COUNTIFS(Results!J:J, R42,Results!K:K, S42, Results!I:I, "casEN") + COUNTIFS(Results!J:J, R42,Results!K:K, S42, Results!I:I, "casEN_opti") -> 8 | AC42: =COUNTIFS(Results!J:J, R42,Results!K:K, S42, Results!B:B, 1, Results!I:I, "casEN") + COUNTIFS(Results!J:J, R42,Results!K:K, S42, Results!B:B, 0, Results!I:I, "casEN") + COUNTIFS(Results!J:J, R42,Results!K:K, S42, Results!B:B, 1, Results!I:I, "casEN_opti") + COUNTIFS(Results!J:J, R42,Results!K:K, S42, Results!B:B, 0, Results!I:I, "casEN_opti") -> 8 | AD42: =COUNTIFS(Results!J:J, R42,Results!K:K, S42, Results!B:B, 1, Results!I:I, "casEN") + COUNTIFS(Results!J:J, R42,Results!K:K, S42, Results!B:B, 1, Results!I:I, "casEN_opti") -> 0 | AE42: =IFERROR(AD42/AC42, 0) -> 0 | AF42: =(NER!$L$11+graphs_analyses!AD42)/(graphs_analyses!AC42 +NER!$K$11) - NER!$M$11 -> -0.0011181673
R43: grftagOrgFunder | S43: grforgProximite | T43: =COUNTIFS(Results!J:J, R43, Results!K:K, S43) -> 2 | U43: =COUNTIFS(Results!J:J, R43,Results!K:K, S43, Results!B:B, 1) + COUNTIFS(Results!J:J, R43,Results!K:K, S43, Results!B:B, 0) -> 0 | V43: =COUNTIFS(Results!J:J, R43, Results!K:K, S43, Results!B:B, 1) -> 0 | W43: =IFERROR(V43/U43, 0) -> 0 | X43: =COUNTIFS(Results!J:J, R43, Results!K:K, S43, Results!I:I, $X$1) -> 0 | Y43: =COUNTIFS(Results!J:J, R43,Results!K:K, S43, Results!I:I, $X$1, Results!B:B, 1) + COUNTIFS(Results!J:J, R43,Results!K:K, S43,Results!I:I, $X$1, Results!B:B, 0) -> 0 | Z43: =COUNTIFS(Results!J:J, R43, Results!K:K, S43, Results!I:I, $X$1, Results!B:B, 1) -> 0 | AA43: =IFERROR(Z43/Y43, 0) -> 0 | AB43: =COUNTIFS(Results!J:J, R43,Results!K:K, S43, Results!I:I, "casEN") + COUNTIFS(Results!J:J, R43,Results!K:K, S43, Results!I:I, "casEN_opti") -> 2 | AC43: =COUNTIFS(Results!J:J, R43,Results!K:K, S43, Results!B:B, 1, Results!I:I, "casEN") + COUNTIFS(Results!J:J, R43,Results!K:K, S43, Results!B:B, 0, Results!I:I, "casEN") + COUNTIFS(Results!J:J, R43,Results!K:K, S43, Results!B:B, 1, Results!I:I, "casEN_opti") + COUNTIFS(Results!J:J, R43,Results!K:K, S43, Results!B:B, 0, Results!I:I, "casEN_opti") -> 0 | AD43: =COUNTIFS(Results!J:J, R43,Results!K:K, S43, Results!B:B, 1, Results!I:I, "casEN") + COUNTIFS(Results!J:J, R43,Results!K:K, S43, Results!B:B, 1, Results!I:I, "casEN_opti") -> 0 | AE43: =IFERROR(AD43/AC43, 0) -> 0 | AF43: =(NER!$L$11+graphs_analyses!AD43)/(graphs_analyses!AC43 +NER!$K$11) - NER!$M$11 -> 0
R44: grftagOrgNameEntreprise | S44: grfpersPrenomNom | T44: =COUNTIFS(Results!J:J, R44, Results!K:K, S44) -> 1 | U44: =COUNTIFS(Results!J:J, R44,Results!K:K, S44, Results!B:B, 1) + COUNTIFS(Results!J:J, R44,Results!K:K, S44, Results!B:B, 0) -> 1 | V44: =COUNTIFS(Results!J:J, R44, Results!K:K, S44, Results!B:B, 1) -> 1 | W44: =IFERROR(V44/U44, 0) -> 1 | X44: =COUNTIFS(Results!J:J, R44, Results!K:K, S44, Results!I:I, $X$1) -> 0 | Y44: =COUNTIFS(Results!J:J, R44,Results!K:K, S44, Results!I:I, $X$1, Results!B:B, 1) + COUNTIFS(Results!J:J, R44,Results!K:K, S44,Results!I:I, $X$1, Results!B:B, 0) -> 0 | Z44: =COUNTIFS(Results!J:J, R44, Results!K:K, S44, Results!I:I, $X$1, Results!B:B, 1) -> 0 | AA44: =IFERROR(Z44/Y44, 0) -> 0 | AB44: =COUNTIFS(Results!J:J, R44,Results!K:K, S44, Results!I:I, "casEN") + COUNTIFS(Results!J:J, R44,Results!K:K, S44, Results!I:I, "casEN_opti") -> 1 | AC44: =COUNTIFS(Results!J:J, R44,Results!K:K, S44, Results!B:B, 1, Results!I:I, "casEN") + COUNTIFS(Results!J:J, R44,Results!K:K, S44, Results!B:B, 0, Results!I:I, "casEN") + COUNTIFS(Results!J:J, R44,Results!K:K, S44, Results!B:B, 1, Results!I:I, "casEN_opti") + COUNTIFS(Results!J:J, R44,Results!K:K, S44, Results!B:B, 0, Results!I:I, "casEN_opti") -> 1 | AD44: =COUNTIFS(Results!J:J, R44,Results!K:K, S44, Results!B:B, 1, Results!I:I, "casEN") + COUNTIFS(Results!J:J, R44,Results!K:K, S44, Results!B:B, 1, Results!I:I, "casEN_opti") -> 1 | AE44: =IFERROR(AD44/AC44, 0) -> 1 | AF44: =(NER!$L$11+graphs_analyses!AD44)/(graphs_analyses!AC44 +NER!$K$11) - NER!$M$11 -> 3.9318464e-06
R45: grftagOrgNameEntreprise | S45: grfpersGenerique | T45: =COUNTIFS(Results!J:J, R45, Results!K:K, S45) -> 1 | U45: =COUNTIFS(Results!J:J, R45,Results!K:K, S45, Results!B:B, 1) + COUNTIFS(Results!J:J, R45,Results!K:K, S45, Results!B:B, 0) -> 1 | V45: =COUNTIFS(Results!J:J, R45, Results!K:K, S45, Results!B:B, 1) -> 1 | W45: =IFERROR(V45/U45, 0) -> 1 | X45: =COUNTIFS(Results!J:J, R45, Results!K:K, S45, Results!I:I, $X$1) -> 0 | Y45: =COUNTIFS(Results!J:J, R45,Results!K:K, S45, Results!I:I, $X$1, Results!B:B, 1) + COUNTIFS(Results!J:J, R45,Results!K:K, S45,Results!I:I, $X$1, Results!B:B, 0) -> 0 | Z45: =COUNTIFS(Results!J:J, R45, Results!K:K, S45, Results!I:I, $X$1, Results!B:B, 1) -> 0 | AA45: =IFERROR(Z45/Y45, 0) -> 0 | AB45: =COUNTIFS(Results!J:J, R45,Results!K:K, S45, Results!I:I, "casEN") + COUNTIFS(Results!J:J, R45,Results!K:K, S45, Results!I:I, "casEN_opti") -> 0 | AC45: =COUNTIFS(Results!J:J, R45,Results!K:K, S45, Results!B:B, 1, Results!I:I, "casEN") + COUNTIFS(Results!J:J, R45,Results!K:K, S45, Results!B:B, 0, Results!I:I, "casEN") + COUNTIFS(Results!J:J, R45,Results!K:K, S45, Results!B:B, 1, Results!I:I, "casEN_opti") + COUNTIFS(Results!J:J, R45,Results!K:K, S45, Results!B:B, 0, Results!I:I, "casEN_opti") -> 0 | AD45: =COUNTIFS(Results!J:J, R45,Results!K:K, S45, Results!B:B, 1, Results!I:I, "casEN") + COUNTIFS(Results!J:J, R45,Results!K:K, S45, Results!B:B, 1, Results!I:I, "casEN_opti") -> 0 | AE45: =IFERROR(AD45/AC45, 0) -> 0 | AF45: =(NER!$L$11+graphs_analyses!AD45)/(graphs_analyses!AC45 +NER!$K$11) - NER!$M$11 -> 0
R46: main_graph | S46: second_graph

Sheet solver
B1: Total | C1: Corrected | D1: Correct | E1: Accuracy
A2: intersection | B2: 4085 | C2: 4085 | D2: 3990 | E2: 0.97674419 | G2: Main_graph | H2: Second_graph | I2: Third_graph | J2: Global Accuracy loss | K2: GAIN | L2: Selected
G3: grfpersGenerique | J3: -0.0073608231 | K3: 1445 | L3: 1
G4: grfpersPrenomNom | J4: -0.022156951 | K4: 227 | L4: 0
A5: New NER | B5: Total Gain | C5: Total loss | D5: Selected | G5: grforgProximite | J5: -0.0023517349 | K5: 953 | L5: 1
B6: =SUMPRODUCT(K1:K998, L1:L998) -> 3987 | C6: =SUMPRODUCT(J1:J998, L1:L998) -> -0.0099340183 | D6: =SUM(L1:L998) -> 59 | G6: grforgSeule | J6: -0.010264008 | K6: 218 | L6: 0
G7: grfpersContextePersonne | J7: -0.0015229463 | K7: 49 | L7: 0
G8: grfpersAmbigus | J8: 1.1792147e-05 | K8: 3 | L8: 1
G9: grforgPolice | J9: 3.5345944e-05 | K9: 69 | L9: 1
G10: grfplaceBatiment | J10: -0.00055940521 | K10: 751 | L10: 1
G11: grfgeog | J11: -0.0016755664 | K11: 240 | L11: 0
G12: grfplaceQuartier | J12: 0 | K12: 58 | L12: 1
G13: grforgGenerique | J13: -0.0036113622 | K13: 280 | L13: 0
G14: grfroleName | J14: -0.0076158748 | K14: 62 | L14: 0
G15: grforgAdministrative | J15: 0 | K15: 107 | L15: 1
G16: grftagNomFamille | J16: -0.00055940521 | K16: 4 | L16: 0
G17: grftoolPolylexicalOrgPlace | J17: 1.5720602e-05 | K17: 4 | L17: 1
G18: grforgSport | J18: 0 | K18: 7 | L18: 1
... G41: grforgSuiviDeParentheses | J41: 0 | K41: 0 | L41: 1
G42: grfadress | H42: grftagAdresseRue | J42: -0.00041961424 | K42: 60 | L42: 0
G43: grfadress | H43: grftagZoneIndustrielle | J43: 0 | K43: 18 | L43: 1
G44: grfgeog | H44: grftoolPolylexicalOrgPlace | J44: 1.1792147e-05 | K44: 3 | L44: 1
G45: grfgeog | H45: grforgPlaceGeoPolitique | J45: 8.2331917e-05 | K45: 30 | L45: 1
G46: grfGeogPlaceGenerique | H46: grfgeogRiviere | J46: 0 | K46: 6 | L46: 1
G47: grfGeogPlaceGenerique | H47: grfgeogMer | J47: 0 | K47: 1 | L47: 1
G48: grfGeogPlaceGenerique | H48: grfgeogPhysique | J48: 0 | K48: 1 | L48: 1
G49: grfGeogPlaceGenerique | H49: grfgeogHydro | J49: 0 | K49: 0 | L49: 1
G50: grforgSeule | H50: grfpersGenerique | J50: 0 | K50: 13 | L50: 1
G51: grforgSeule | H51: grforgProximite | J51: -0.0076139495 | K51: 90 | L51: 0
G52: grforgSeule | H52: grforgPolice | J52: -0.00021638463 | K52: 18 | L52: 0
G53: grforgSeule | H53: grforgMedia | J53: -0.00027978306 | K53: 2 | L53: 0
... G85: grftagOrgNameEntreprise | H85: grfpersGenerique | J85: 0 | K85: 0 | L85: 1
G86: grfadress | H86: grftagZoneIndustrielle | I86: grftagZoneIndustrielle | J86: 0 | K86: 1 | L86: 1
G87: grforgSeule | H87: grforgProximite | I87: grfpersGenerique | J87: -0.0005553952 | K87: 6 | L87: 0
G88: grforgSeule | H88: grforgArmee | I88: grfpersPrenomNom | J88: 3.9318464e-06 | K88: 1 | L88: 1
G89: grforgSeule | H89: grforgFinance | I89: grfpersPrenomNom | J89: -0.00013991165 | K89: 1 | L89: 0
G90: grforgSeule | H90: grforgProximite | I90: grfpersPrenomNom | J90: -0.00027581211 | K90: 3 | L90: 0
G91: grforgSeule | H91: grforgPolice | I91: grfpersPrenomNom | J91: -0.00013991165 | K91: 1 | L91: 0
G92: grforgSeule | H92: grforgAssemblee | I92: grfpersGenerique | J92: 3.9318464e-06 | K92: 1 | L92: 1
G93: grforgSeule | H93: grforgProximite | I93: grftagCiviliteS | J93: -0.00027978306 | K93: 2 | L93: 0
G94: grforgSeule | H94: grforgProximite | I94: grfroleName | J94: -0.00027978306 | K94: 2 | L94: 0
G95: grforgSeule | H95: grforgAdministrative | I95: grfpersGenerique | J95: -0.00013991165 | K95: 2 | L95: 0
G96: grforgSeule | H96: grftagGentileP | I96: grftagNomFamille | J96: 0 | K96: 1 | L96: 1
G97: grforgSeule | H97: grforgMusique | I97: grfpersGenerique | J97: 0 | K97: 0 | L97: 1
... G112: grfplace | H112: grfplaceBatiment | I112: grfroleName | J112: 3.9318464e-06 | K112: 1 | L112: 1
