Workbook

Sheet Results
A1: manual cat | B1: correct | C1: extent | D1: category | E1: titles | F1: NER | G1: NER_label | H1: desc | I1: method | J1: main_graph | K1: second_graph | L1: third_graph | M1: file_id
E2: L'héritage | F2: Nathalie | G2: MISC | H2: le familiale depuis des générations.... Nathalie et Marianne aimeraient la vendre. Mais | I2: spaCy | M2: 0
A3: ERR | B3: 0 | C3: 0 | D3: ERR | E3: Money Flower | F3: A. Dans | G3: PER | H3: à la tête de la société Cheong A. Dans la lutte pour la succession du groupe, | I3: casEN | J3: grfpersPrenomNom | K3: grftagNomFamille | M3: 5268
A4: PER | B4: 1 | C4: 1 | D4: 1 | E4: Vampire Diaries (S4-E10) | F4: Aaron | G4: PER | H4: Elena se rend dans le dortoir d’Aaron, l’ancien colocataire de Jesse, afin qu’il l’aide à retrouver le docteur Maxfield et Damon. Il l’emmène dans la maison Whitmore, repaire des membres de la société Augustine. À leur arrivée, Wes injecte à la jeune fille une piqûre de verveine et l’enferme... avec son petit ami dans une cellule. Pendant ce temps, Caroline revient à Mystic Falls, déterminée à exorciser les démons de Stefan. | I4: intersection | J4: grfpersGenerique | M4: 253
E5: Bob l'éponge | F5: - Epidémie de hoquet | G5: LOC | H5: d'un nouvel ami adorable, mais collant. - Epidémie de hoquet . A Bikini Bottom, personne n'est à l'a | I5: spaCy | M5: 6625
A6: PER | B6: 0 | C6: 0 | D6: 1 | E6: L'héritage | F6: capitaine Dubreuil | G6: PER | H6: les rênes. Parallèlement, alors que le capitaine Dubreuil et son équipe piétinent dans leur enquê | I6: spaCy | M6: 0
E7: Phinéas et Ferb (S4-E22) | F7: - Recyclage | G7: LOC | H7: n de disparaître à la dernière seconde. - Recyclage d'inventions . Phineas, Ferb et leurs a | I7: spaCy | M7: 2790
E8: L'héritage | F8: Tessa | G8: MISC | H8: son équipe piétinent dans leur enquête, Tessa et ses sœurs entendent mener leurs prop | I8: spaCy | M8: 0
A9: ORG | B9: 0 | C9: 0 | D9: 1 | E9: Inazuma Eleven Go | F9: Académie | G9: ORG | H9: Le match contre la Royale Académie s'avère être très difficile. L'équipe est composée | I9: casEN | J9: grforgProximite | M9: 1564
A10: ERR | B10: 0 | C10: 0 | D10: ERR | E10: Money Flower | F10: A. Jalousé | G10: PER | H10: est directeur juridique du grand groupe Cheong A. Jalousé et envié, il est considéré comme le | I10: casEN | J10: grfpersPrenomNom | K10: grftagNomFamille | M10: 5268
E11: Phinéas et Ferb (S4-E22) | F11: - Retour | G11: LOC | H11: uve accidentellement changée en mouche. - Retour vers les années 50 . Phineas et Ferb re | I11: spaCy | M11: 2789
A12: PER | B12: 1 | C12: 1 | D12: 1 | E12: Vampire Diaries (S4-E10) | F12: Aaron | G12: PER | H12: chercher Stefan. Les deux frères partent questionner Aaron afin d'obtenir des informations sur le lieu | I12: intersection | J12: grfpersGenerique | M12: 254
A13: ORG | B13: 1 | C13: 1 | D13: 1 | E13: Nick Bollettieri, une vie de tennis | F13: académie | G13: ORG | H13: Inventeur du concept de l'académie géante de tennis, Nick Bollettieri a contribué à l'émergence de grands champions tels que André Agassi, Maria Sharapova, Monica Seles, ou encore Jim Courrier. Outre le portrait d'un des plus grands coachs du tennis moderne, ce film analyse les techniques... d'entraînements novatrices introduites par Bollettieri. | I13: casEN | J13: grforgProximite | M13: 1935
A14: PER | B14: 1 | C14: 1 | D14: 1 | E14: Somewhere Boy (S1-E1) | F14: Aaron | G14: PER | H14: Daisy invite Aaron et Danny à la fête agricole qu'elle | I14: intersection | J14: grfpersGenerique | M14: 1960
A15: PER | B15: 1 | C15: 1 | D15: 1 | E15: Somewhere Boy (S1-E1) | F15: Aaron | G15: PER | H15: Daisy invite Aaron et Danny à la fête agricole qu'elle | I15: intersection | J15: grfpersGenerique | M15: 1960
A16: PER | B16: 1 | C16: 1 | D16: 1 | E16: Somewhere Boy (S1-E1) | F16: Aaron | G16: PER | H16: Daisy invite Aaron et Danny à la fête agricole qu'elle | I16: intersection | J16: grfpersGenerique | M16: 1960
E17: 1, 2, 3 musette | F17: 123 Musette | G17: LOC | H17: 123 Musette - Spécial Grand Ouest | I17: spaCy | M17: 8352
E18: Himawari | F18: académie | G18: ORG | H18: Nouvelle à l'académie spécialisée dans la formation des femmes ninja, la jeune Himawari a juré fidélité et protection à celui qu'elle considère comme son mentor, un nouvel enseignant à qui un passé mystérieux la lie peut-être... Himawari va tout faire pour le protéger des embrouilles... causées par ses collègues et de la vie quotidienne à l'académie. | I18: casEN | J18: grforgProximite | M18: 5251
E19: Himawari | F19: académie | G19: ORG | H19: Nouvelle à l'académie spécialisée dans la formation des femmes ninja, la jeune Himawari a juré fidélité et protection à celui qu'elle considère comme son mentor, un nouvel enseignant à qui un passé mystérieux la lie peut-être... Himawari va tout faire pour le protéger des embrouilles... causées par ses collègues et de la vie quotidienne à l'académie. | I19: casEN | J19: grforgProximite | M19: 5251
E20: Himawari | F20: académie | G20: ORG | H20: Nouvelle à l'académie spécialisée dans la formation des femmes ninja, la jeune Himawari a juré fidélité et protection à celui qu'elle considère comme son mentor, un nouvel enseignant à qui un passé mystérieux la lie peut-être... Himawari va tout faire pour le protéger des embrouilles... causées par ses collègues et de la vie quotidienne à l'académie. | I20: casEN | J20: grforgProximite | M20: 5252
A21: PER | B21: 1 | C21: 1 | D21: 1 | E21: Somewhere Boy (S1-E1) | F21: Aaron | G21: PER | H21: Daisy invite Aaron et Danny à la fête agricole qu'elle | I21: intersection | J21: grfpersGenerique | M21: 1960
A22: PER | B22: 1 | C22: 1 | D22: 1 | E22: Somewhere Boy (S1-E1) | F22: Aaron | G22: PER | H22: Aaron est furieux contre Danny qui a gâché | I22: intersection | J22: grfpersGenerique | M22: 1961
A23: ERR | B23: 0 | C23: 0 | D23: ERR | E23: Wheeler Dealers France | F23: 231 ch | G23: LOC | H23: sur un modèle doté d'un V8 de 231 ch, mais malgré tout avec quelques défaillances mécaniques. | I23: casEN | J23: grfadress | K23: grftagAdresseRue | M23: 7296
E24: Ski alpin : Coupe du monde à Sölden | F24: 2e | G24: LOC | H24: Epreuve de Sölden. Slalom géant dames . 2e manche. | I24: spaCy | M24: 3115
A25: PER | B25: 1 | C25: 1 | D25: 1 | E25: Somewhere Boy (S1-E1) | F25: Aaron | G25: PER | H25: Aaron est furieux contre Danny qui a gâché | I25: intersection | J25: grfpersGenerique | M25: 1961
E26: Ski alpin : Coupe du monde à Sölden | F26: 2e | G26: LOC | H26: Epreuve de Sölden. Slalom géant dames . 2e manche. | I26: spaCy | M26: 3129
E27: Himawari | F27: académie | G27: ORG | H27: Nouvelle à l'académie spécialisée dans la formation des femmes ninja, la jeune Himawari a juré fidélité et protection à celui qu'elle considère comme son mentor, un nouvel enseignant à qui un passé mystérieux la lie peut-être... Himawari va tout faire pour le protéger des embrouilles... causées par ses collègues et de la vie quotidienne à l'académie. | I27: casEN | J27: grforgProximite | M27: 5252
E28: Yu-Gi-Oh ! GX | F28: Académie | G28: ORG | H28: L'année s'achève à la Duel Académie et les élèves vont bientôt connaître les | I28: casEN | J28: grforgProximite | M28: 5259
A29: PER | B29: 1 | C29: 1 | D29: 1 | E29: Ransom (S3-E1) | F29: Beaumont | G29: PER | H29: kidnappées. Lors de ses investigations, Beaumont découvre le milieu impitoyable du balle | I29: spaCy | M29: 8
A30: LOC | B30: 0 | C30: 0 | D30: 1 | E30: Envie dehors | F30: 3 Pays de la Loire | G30: LOC | H30: Production exécutive Nouveaux Jours productions France Télévisions - France 3 Pays de la Loire | I30: casEN | J30: grfadress | K30: grftagAdresseRue | M30: 4663
A31: PER | B31: 0 | C31: 0 | D31: 1 | E31: Comédie Club Tour : Kev Adams | F31: Adams | G31: PER | H31: Comedy Room, le 1er septembre 2020, Kev Adams, reçoit le Comédie Club tour où il | I31: casEN | J31: grfpersGenerique | M31: 2478
E32: Ransom (S3-E1) | F32: FBI | G32: ORG | H32: Le FBI est contraint de faire appel à Beaumont | I32: spaCy | M32: 9
E33: Pokémon : Diamant et perle | F33: académie | G33: ORG | H33: Bonville où habite Angie, de la Pokemon académie. La ville est terrorisée, car, le soir | I33: casEN | J33: grforgProximite | M33: 5983
E34: Orchestre de l'Opéra de Paris et Gustavo Dudamel : Concert inaugural | F34: Académie | G34: ORG | H34: Résumé Premier concert inaugural de Gustavo Duhamel à l'Opéra Garnier de Paris. Il dirige à cette occasion les artistes des Chœurs et de l’Académie ainsi que des solistes invités. De Carmen de Georges Bizet à Doctor Atomic de John Adams, de Lohengrin de Richard Wagner à Ainadamar de Osvaldo... Golijov, du Chevalier à la rose de Richard Strauss à Falstaff de Giuseppe Verdi, de La Vida breve de Manuel De Falla à Peter Grimes de Benjamin Britten, les plus grands morceaux mythiques (duo, ballets, ballets, ensembles ou encore interludes) sont interprétés. Voirplusmoins | I34: casEN | J34: grforgProximite | M34: 6271
A35: PER | B35: 1 | C35: 1 | D35: 1 | E35: Somewhere Boy (S1-E1) | F35: Aaron | G35: PER | H35: Aaron est furieux contre Danny qui a gâché | I35: intersection | J35: grfpersGenerique | M35: 1961
A36: PER | B36: 1 | C36: 1 | D36: 1 | E36: Somewhere Boy (S1-E1) | F36: Aaron | G36: PER | H36: Aaron est furieux contre Danny qui a gâché | I36: intersection | J36: grfpersGenerique | M36: 1961
E37: Révélations monumentales | F37: 3D | G37: LOC | H37: e. Du drone technique aux relevés laser 3D, le monument est ausculté par les scien | I37: spaCy | M37: 5342
A38: PER | B38: 1 | C38: 1 | D38: 1 | E38: Chicago Police Department (S2-E10) | F38: Erin | G38: PER | H38: tente de le faire parler. De son côté, Erin a du mal à reprendre le dessus et doit | I38: spaCy | M38: 13
E39: Yu-Gi-Oh ! GX | F39: Académie des Duellistes fondée | G39: ORG | H39: Yu-Gi-Oh-! GX se déroule des années après l'histoire de Yugi Mûto. On y découvre Juudai Yuuki dans le rôle du héros. Ce dernier va à l'Académie des Duellistes fondée par Seto KaÔba pour y être admis. Il croise en route un personnage dont la coupe de cheveux rappelle Yugi Mûto et reçoit... une carte qui l'accompagnera durant son aventure. Yuuki est admis et, dès lors, son avenir sera truffé de combats toujours plus difficiles les uns que les autres. | I39: casEN | J39: grforgEconomie | M39: 5265
A40: PER | B40: 1 | C40: 1 | D40: 1 | E40: Chicago Police Department (S2-E10) | F40: Voight | G40: PER | H40: e affaire sur laquelle elle intervient. Voight parvient à neutraliser l'un... des malf | I40: spaCy | M40: 13
E41: Lutèce, l'enfance de Paris | F41: 3D | G41: LOC | H41: velles techniques de reconstitutions en 3D permettent aujourd'hui de reconstituer | I41: spaCy | M41: 7082
A42: ERR | B42: 0 | C42: 0 | D42: ERR | E42: La catastrophe de l'Escaut : mort et renaissance d'un fleuve | F42: 44 piscines olympiques | G42: LOC | H42: sucrière Téréos, près de Cambrai, déverse l'équivalent de 44 piscines olympiques d'eaux polluées dans le fleuve. En | I42: casEN | J42: grfadress | K42: grftagAdresseRue | M42: 5851
A43: PER | B43: 1 | C43: 1 | D43: 1 | E43: Chicago Police Department (S2-E10) | F43: Hank | G43: PER | H43: és dans le racket de dealers de drogue. Hank a un plan pour le sortir de cette situa | I43: spaCy | M43: 14
A44: ERR | B44: 0 | C44: 0 | D44: ERR | E44: Astérix et le coup du menhir | F44: 52 av. J. | G44: LOC | H44: En 52 av. J.-C., le druide Panoramix est devenu amnésique après avoir reçu un coup de menhir sur la tête. Par conséquent, il a oublié la formule de la célèbre potion magique, garante de la résistance du village d'Astérix et Obélix contre les garnisons romaines. Bientôt, le devin Prolix,... un charlatan à la solde des Romains, en profite pour s'installer dans la forêt voisine où il abuse de la crédulité des habitants du village. Astérix et Obélix se doivent de réagir. Avant tout, il leur faut trouver un moyen pour rendre la raison à Panoramix... | I44: casEN | J44: grfadress | K44: grftagAdresseRue | M44: 7498
A45: PER | B45: 1 | C45: 1 | D45: 1 | E45: Chicago Police Department (S2-E10) | F45: Linda | G45: PER | H45: De son côté, Olinsky est sollicité par Linda, une femme avec laquelle il a eu une li | I45: spaCy | M45: 14
E46: 100% Loup | F46: académie d'Hurleville | G46: ORG | H46: Freddy Lupin réussit à convaincre les anciens de la meute de le laisser passer l'épreuve d'entrée à l'académie d'Hurleville, réservée aux loups. | I46: casEN | J46: grforgSeule | K46: grforgProximite | M46: 1554
E47: 100% Loup | F47: académie d'Hurleville | G47: ORG | H47: Freddy Lupin réussit à convaincre les anciens de la meute de le laisser passer l'épreuve d'entrée à l'académie d'Hurleville, réservée aux loups. | I47: casEN | J47: grforgSeule | K47: grforgProximite | M47: 1555
A48: PER | B48: 1 | C48: 1 | D48: 1 | E48: Chicago Police Department (S2-E10) | F48: Olinsky | G48: PER | H48: que... reste très fragile. De son côté, Olinsky est sollicité par Linda, une femme avec | I48: spaCy | M48: 14
A49: PER | B49: 1 | C49: 1 | D49: 1 | E49: Somewhere Boy (S1-E1) | F49: Aaron | G49: PER | H49: a coûté la vie à sa mère. Aaron avoue à sue qu'il ne veut plus | I49: intersection | J49: grfpersGenerique | M49: 1962
A50: PER | B50: 1 | C50: 1 | D50: 1 | E50: Somewhere Boy (S1-E1) | F50: Aaron | G50: PER | H50: Aaron éprouve de la culpabilité après le départ | I50: intersection | J50: grfpersGenerique | M50: 1963
A51: PER | B51: 1 | C51: 1 | D51: 1 | E51: Chicago Police Department (S2-E10) | F51: Halstead | G51: PER | H51: d'un gang qui la met sur les traces de Halstead. De son côté, Erin poursuit sa lente et | I51: spaCy | M51: 15
A52: ERR | B52: 0 | C52: 0 | D52: ERR | E52: La Pat Patrouille (S7-E15) | F52: A | G52: LOC | H52: 20: La Pat' Patrouille et les écureuils / A la recherche du bébé kangourou La | I52: intersection | J52: grforgGenerique | M52: 6567
A53: ERR | B53: 0 | C53: 0 | D53: ERR | E53: La belle affaire | F53: A | G53: LOC | H53: A la frontière suisse, une détective est chargée | I53: casEN | J53: grforgGenerique | M53: 4
A54: PER | B54: 1 | C54: 1 | D54: 1 | E54: Chicago Police Department (S2-E10) | F54: Olinsky | G54: PER | H54: e. Jay tente de la raisonner ; en vain. Olinsky confie son... secret à Platt. Lorsque l | I54: spaCy | M54: 15
A55: PER | B55: 1 | C55: 1 | D55: 1 | E55: Chroniques bibliques | F55: Aaron | G55: PER | H55: Il y a des prophétesses. Dix, au moins. La première, c'est Myriam, la Sœur de Moïse et d'Aaron, car chanter la gloire de Dieu après le passage miraculeux de la Mer Rouge. Dans le Nouveau Testament, nous trouvons Anne, le jour de la présentation de Jésus au Temple et les 4 filles de Philippe... (le diacre). On a reconnu à des femmes le titre de prophétesses, tout au long de l'histoire biblique. | I55: intersection | J55: grfpersGenerique | M55: 5502
A56: PER | B56: 1 | C56: 1 | D56: 1 | E56: Chicago Police Department (S2-E10) | F56: Halstead | G56: PER | H56: t. Lorsque les choses tournent mal pour Halstead, il décide d'informer Lindsay. | I56: spaCy | M56: 15
A57: PER | B57: 1 | C57: 1 | D57: 1 | E57: Chicago Police Department (S2-E10) | F57: Erin | G57: PER | H57: ur les traces de Halstead. De son côté, Erin poursuit sa lente et inéluctable descen | I57: spaCy | M57: 15
A58: ERR | B58: 0 | C58: 0 | D58: ERR | E58: Alex Hugo (S5-E1) | F58: A | G58: LOC | H58: A Lusagne, l'heure est à la fête : | I58: casEN | J58: grforgGenerique | M58: 6
E59: 100% Wolf | F59: académie d'Hurleville | G59: ORG | H59: Freddy Lupin réussit à convaincre les anciens de la meute de le laisser passer l'épreuve d'entrée à l'académie d'Hurleville, réservée aux loups. | I59: casEN | J59: grforgSeule | K59: grforgProximite | M59: 5550
A60: PER | B60: 1 | C60: 1 | D60: 1 | E60: Chicago Police Department (S2-E10) | F60: Halstead | G60: PER | H60: Dans le même temps, Voight demande... à Halstead de veiller discrètement sur Erin. Kim c | I60: spaCy | M60: 16
E61: Chicago Police Department (S2-E10) | F61: Lindsay | G61: MISC | H61: né sur un terrain abandonné. Antonio et Lindsay, qui a réintégré son poste à certaines | I61: spaCy | M61: 16
A62: PER | B62: 1 | C62: 1 | D62: 1 | E62: Chicago Police Department (S2-E10) | F62: Voight | G62: PER | H62: rrogent un suspect. Dans le même temps, Voight demande... à Halstead de veiller discrè | I62: spaCy | M62: 16
A63: ERR | B63: 0 | C63: 0 | D63: ERR | E63: Chicago Police Department (S2-E10) | F63: A | G63: LOC | H63: A l'issue d'une course-poursuite pour attraper un malfaiteur, | I63: casEN | J63: grforgGenerique | M63: 16
A64: PER | B64: 0 | C64: 0 | D64: 1 | E64: Comédie Club Tour : Kev Adams | F64: Adams | G64: PER | H64: Comedy Room, le 1er septembre 2020, Kev Adams, reçoit le Comédie Club tour. David Voinson, | I64: casEN | J64: grfpersGenerique | M64: 2479
A65: PER | B65: 1 | C65: 1 | D65: 1 | E65: Pokémon : Diamant et perle | F65: Aaron | G65: PER | H65: et ses amis font la connaissance de Aaron, un des membres de l'Elite des quatre, | I65: intersection | J65: grfpersGenerique | M65: 5984
A66: PER | B66: 1 | C66: 1 | D66: 1 | E66: American Trip | F66: Aaron | G66: PER | H66: A Los Angeles, Aaron Green travaille dans la maison de disque | I66: intersection | J66: grfpersGenerique | M66: 6851
E67: Chicago Police Department (S2-E10) | F67: Antonio | G67: MISC | H67: ns, assassiné sur un terrain abandonné. Antonio et Lindsay, qui a réintégré son poste à | I67: spaCy | M67: 16
A68: PER | B68: 1 | C68: 1 | D68: 1 | E68: Chicago Police Department (S2-E10) | F68: Burgess | G68: PER | H68: -poursuite pour attraper un malfaiteur, Burgess et Roman découvrent le corps d'un enfan | I68: spaCy | M68: 16
A69: ERR | B69: 0 | C69: 0 | D69: ERR | E69: Kalahari - Gesetz der Wildnis | F69: A | G69: LOC | H69: survivre dans un environnement hostile et impitoyable. A la fin d’une courte saison des pluies, | I69: casEN | J69: grforgGenerique | M69: 95
A70: PER | B70: 1 | C70: 1 | D70: 1 | E70: Cleaners les experts du ménage | F70: Adeline | G70: PER | H70: experts du ménage, viennent en aide à Adeline qui habite à Quiévrain. Après la naissance | I70: casEN | J70: grfpersGenerique | M70: 279
E71: Fiorentina / Juventus Turin | F71: ACF Fiorentina | G71: ORG | H71: Serie A. 11e journée. ACF Fiorentina / Juventus FC. | I71: casEN | J71: grforgDico | M71: 9365
A72: PER | B72: 1 | C72: 1 | D72: 1 | E72: Chicago Police Department (S2-E10) | F72: Voight | G72: PER | H72: me temps, le commandant Fischer informe Voight... que Bunny est en mesure d'apporter d | I72: spaCy | M72: 17
A73: ERR | B73: 0 | C73: 0 | D73: ERR | E73: Programmes de la nuit | F73: A | G73: LOC | H73: A suivre, des rediffusions de vos émissions préférées, | I73: casEN | J73: grforgGenerique | M73: 108
A74: ERR | B74: 0 | C74: 0 | D74: ERR | E74: Chicago Police Department (S2-E10) | F74: Soudain | G74: PER | H74: que l'unité retrouve sa fille disparue. Soudain, il perd patience et prend un homme en | I74: spaCy | M74: 17
A75: PER | B75: 1 | C75: 1 | D75: 1 | E75: Glory of a Big Dick | F75: Aaron | G75: PER | H75: de ses entrailles. Placé près d'un glory-hole, Aaron Trainer voit sa patience... porter ses fruits | I75: intersection | J75: grfpersGenerique | M75: 6938
E76: Sous tutelle... | F76: Agathe | G76: ORG | H76: En France, près d’un million de personnes sont sous tutelle ou curatelle. Mais, s’il se veut protecteur, ce régime est souvent vécu comme une injustice et une privation de liberté. Olivier Pighetti est parti à la rencontre de quatre personnes mises sous tutelle : Gilbert, un retraité... de 83 ans doté d’une retraite de 8 000 euros, Nathalie, placée sous tutelle de façon abusive, Gilles, bouleversé par une mesure qui va le priver de sa maison, et la mère d’Agathe, qui a été pillée de tous ses biens immobiliers, revendus au tiers de leur prix par un organisme tutélaire déficient. | I76: casEN | J76: grfroleName | M76: 7144
A77: ERR | B77: 0 | C77: 0 | D77: ERR | E77: Storage Wars : enchères surprises | F77: A | G77: LOC | H77: A Rancho Cucamonga, en Californie, Jarrod et Brandi, | I77: casEN | J77: grforgGenerique | M77: 303
E78: Tandem (S5-E1) | F78: Agathe | G78: ORG | H78: et une perle qui n’était visiblement pas destinée à Agathe, sa femme.... Les enquêteurs soupçonnent | I78: casEN | J78: grforgGenerique | M78: 8602
E79: Inside Man : Most Wanted | F79: Réserve fédérale des Etats-Unis | G79: ORG | H79: nazi, une bande organisée cambriole la Réserve fédérale des Etats-Unis. Ariella Barash ou Most Wanted est à | I79: spaCy | M79: 18
E80: Inside Man : Most Wanted | F80: Most Wanted | G80: MISC | H80: rale des Etats-Unis. Ariella Barash ou Most Wanted est à la tête de cette prise d'otages | I80: spaCy | M80: 18
A81: ORG | B81: 1 | C81: 1 | D81: 1 | E81: Karambolage | F81: Académie française | G81: ORG | H81: la chanson Michel Souris nous raconte l'histoire d'un hit allemand très connu en France : 99 Luftballons , de la chanteuse Nena. l'institution Suivons Claire Doutriaux dans le temple de la langue française : l'Académie française. la devinette * 99 Luftballons * 1 *L'Académie française*... 2 | I81: intersection | J81: grforgDico | M81: 435
A82: PER | B82: 1 | C82: 1 | D82: 1 | E82: Criminal Minds (S10-E11) | F82: Aaron | G82: PER | H82: trouvé sur les lieux du massacre. Parallèlement, Aaron est confronté à des problèmes familiaux. | I82: intersection | J82: grfpersGenerique | M82: 7175
A83: PER | B83: 1 | C83: 1 | D83: 1 | E83: American Trip | F83: Aaron Green | G83: PER | H83: A Los Angeles, Aaron Green travaille dans la maison de disque du | I83: intersection | J83: grfpersPrenomNom | K83: grftagPrenom | L83: grftagNomFamille | M83: 6851
A84: PER | B84: 1 | C84: 1 | D84: 1 | E84: Les experts (S1-E18) | F84: Aaron Pratt | G84: PER | H84: morte. Les premiers soupçons se portent sur Aaron Pratt, le bibliothécaire qui travaillait avec la victime. | I84: intersection | J84: grfpersPrenomNom | K84: grftagPrenom | L84: grftagNomFamille | M84: 8608
A85: PER | B85: 1 | C85: 1 | D85: 1 | E85: Glory of a Big Dick | F85: Aaron Trainer | G85: PER | H85: de ses entrailles. Placé près d'un glory-hole, Aaron Trainer voit sa patience... porter ses fruits lorsque | I85: intersection | J85: grfpersPrenomNom | K85: grftagPrenom | L85: grftagNomFamille | M85: 6938
A86: ERR | B86: 0 | C86: 0 | D86: ERR | E86: Storage Wars : enchères surprises | F86: A | G86: LOC | H86: A Orange, la vente a lieu dans un | I86: casEN | J86: grforgGenerique | M86: 307
E87: Chicago Fire (S11-E10) | F87: Ritter | G87: PER | H87: idement demander de l’aide à Gallo et à Ritter. Plusieurs individus présentent les mêm | I87: spaCy | M87: 19
A88: ERR | B88: 0 | C88: 0 | D88: ERR | E88: Adjugé, vendu ! | F88: A | G88: LOC | H88: A Newmarket, dans le New Hampshire, une équipe | I88: casEN | J88: grforgGenerique | M88: 313
E89: xXx | F89: Agence | G89: ORG | H89: Xander Cage, surnommé xXx, féru de sports extrêmes, n'a de cesse de filmer ses exploits, qu'il met en ligne sur Internet. Cage, dont les spectaculaires cascades ne sont pas toujours appréciées par les autorités, est bientôt approché par Augustus Gibbons. Ce responsable de l'Agence de... sécurité nationale américaine (NSA), souhaite recruter un agent secret hors normes, pour infiltrer Anarchie 99, une organisation criminelle dont le siège est à Prague. Il propose la mission à Xander. Sur place, Cage tombe bientôt sous le charme de la vénéneuse Yelena. | I89: casEN | J89: grforgEconomie | M89: 335
E90: Chicago Fire (S11-E10) | F90: Herrmann | G90: PER | H90: Violet craignent le pire scénario. Les Herrmann... sont anxieux en attendant les résult | I90: spaCy | M90: 19
A91: PER | B91: 1 | C91: 1 | D91: 1 | E91: Les tyrans de l'histoire | F91: Adolf Hitler | G91: PER | H91: de... comprendre l'origine du mal chez ces dictateurs. Adolf Hitler est la personnification même du mal. | I91: casEN | J91: grfpersPrenomNom | K91: grftagPrenom | L91: grftagNomFamille | M91: 6918
A92: PER | B92: 1 | C92: 1 | D92: 1 | E92: Italia mia: Luana cuisine Rome | F92: Abdel Alaoui | G92: PER | H92: Luana a invité son ami le chef Abdel Alaoui, ils préparent deux recettes aux saveurs d'été, | I92: intersection | J92: grfpersPrenomNom | K92: grftagPrenom | L92: grftagNomFamille | M92: 6346
E93: Chicago Fire (S11-E10) | F93: Mouch | G93: PER | H93: Mouch se lance dans la construction d’une maq | I93: spaCy | M93: 19
A94: ERR | B94: 0 | C94: 0 | D94: ERR | E94: Adjugé, vendu ! | F94: A | G94: LOC | H94: A North York, c'est l'anniversaire de Rick, et | I94: casEN | J94: grforgGenerique | M94: 315
A95: PER | B95: 1 | C95: 1 | D95: 1 | E95: L'innocent | F95: Abel | G95: PER | H95: elle doit annoncer la nouvelle à son fils Abel, afin que celui-ci puisse assister au | I95: intersection | J95: grfpersContextePersonne | K95: grftagNomFamille | M95: 1651
E96: WOMEX 2018 | F96: agences de presse | G96: ORG | H96: (Womex) attire des musiciens, des imprésarios, des agences de presse ainsi que des entreprises médiatiques du monde | I96: casEN | J96: grforgMedia | M96: 7761
E97: Chicago Fire (S11-E10) | F97: Kidd | G97: MISC | H97: la grande surprise de tout le monde et Kidd est invitée à rejoindre une force d’int | I97: spaCy | M97: 20
E98: Chicago Fire (S11-E10) | F98: Gallo | G98: MISC | H98: Mouch et Capp le soutiennent. La vie de Gallo connaît des... bouleversements lorsqu’i | I98: spaCy | M98: 20
A99: PER | B99: 1 | C99: 1 | D99: 1 | E99: Clem (S8-E1) | F99: Adrian | G99: PER | H99: son professeur de français. Pendant ce temps, Adrian a du mal à vivre l'absence d'Alyzée | I99: casEN | J99: grfpersGenerique | M99: 237
A100: ERR | B100: 0 | C100: 0 | D100: ERR | E100: Adjugé, vendu ! | F100: A | G100: LOC | H100: A Orangeville, les enchérisseurs doivent se montrer particulièrement | I100: casEN | J100: grforgGenerique | M100: 317
...

Sheet Analyses
A1: {=_xlfn.UNIQUE(_xlfn._xlws.FILTER(Results!I:I, Results!I:I <> ""))} -> method | B1: Total Found | C1: (corrected lines) | D1: Total Correct | E1: Accuracy
A2: spaCy | B2: =COUNTIF(Results!I:I, A2) -> 15127 | C2: =COUNTIFS(Results!I:I, A2, Results!B:B, 1) + COUNTIFS(Results!I:I, A2, Results!B:B, 0) -> 17 | D2: =COUNTIFS(Results!I:I, A2, Results!B:B, 1) -> 14 | E2: =IFERROR(D2/C2, 0) -> 0.82352941
A3: casEN | B3: =COUNTIF(Results!I:I, A3) -> 7536 | C3: =COUNTIFS(Results!I:I, A3, Results!B:B, 1) + COUNTIFS(Results!I:I, A3, Results!B:B, 0) -> 1359 | D3: =COUNTIFS(Results!I:I, A3, Results!B:B, 1) -> 727 | E3: =IFERROR(D3/C3, 0) -> 0.53495217
A4: intersection | B4: =COUNTIF(Results!I:I, A4) -> 7548 | C4: =COUNTIFS(Results!I:I, A4, Results!B:B, 1) + COUNTIFS(Results!I:I, A4, Results!B:B, 0) -> 7524 | D4: =COUNTIFS(Results!I:I, A4, Results!B:B, 1) -> 6920 | E4: =IFERROR(D4/C4, 0) -> 0.91972355
B9: NER system | D9: lines | E9: total errors | F9: extent correct | G9: category correct | H9: extent+catégory correct | I9: erreur | J9: precision extent but some incorrect categories | K9: precision categorized | L9: precision extent+categorized | M9: it is a PER but not well tagged by system | N9: it is a LOC but not well tagged by system | O9: it is a ORG but not well tagged by system | P9: category PER error among NE found by system | Q9: category LOC error among NE found by system | R9: category ORG error among NE found by system | S9: estimated recall : good entities found by a system / all good entities
A10: intersection spacy/CasEN | B10: intersection | C10: NE | D10: =COUNTIFS(Results!I:I, B10) -> 7548 | E10: =COUNTIFS(Results!I:I, B11, Results!B:B, 0) -> 604 | F10: =COUNTIFS(Results!I:I, B10, Results!C:C, 1) -> 6984 | G10: =COUNTIFS(Results!I:I, B10, Results!D:D, 1) -> 7364 | H10: =COUNTIFS(Results!I:I, B10, Results!B:B, 1) -> 6920 | I10: =IFERROR(E10/D10, 0) -> 0.080021198 | J10: =IFERROR(F10/$D$10, 0) -> 0.92527822 | K10: =IFERROR(G10/$D$10, 0) -> 0.97562268 | L10: =IFERROR(H10/$D$10, 0) -> 0.91679915 | M10: =SUM(M11:M14) -> 10 | N10: =SUM(N11:N14) -> 3 | O10: =SUM(O11:O14) -> 19 | P10: =IFERROR(M10/F10, 0) -> 0.0014318442 | Q10: =IFERROR(N10/G10, 0) -> 0.00040738729 | R10: =IFERROR(O10/H10, 0) -> 0.0027456647
B11: intersection | C11: PER | D11: =COUNTIFS(Results!G:G, C11, Results!I:I, B11) -> 6091 | E11: =COUNTIFS(Results!G:G, C11, Results!I:I, B11, Results!B:B, 0) -> 513 | F11: =COUNTIFS(Results!G:G, C11, Results!I:I, B11, Results!C:C, 1) -> 5604 | G11: =COUNTIFS(Results!G:G, C11, Results!I:I, B11, Results!D:D, 1) -> 5973 | H11: =COUNTIFS(Results!G:G, C11, Results!I:I, B11, Results!B:B, 1) -> 5565 | I11: =IFERROR(E11/D11, 0) -> 0.084222624 | J11: =IFERROR(F11/$D$11, 0) -> 0.92004597 | K11: =IFERROR(G11/$D$11, 0) -> 0.98062715 | L11: =IFERROR(H11/$D$11, 0) -> 0.91364308 | M11: 0 | N11: =COUNTIFS(Results!I:I,$B$11,Results!G:G,$C$11,Results!C:C, 1, Results!A:A,"LOC") -> 3 | O11: =COUNTIFS(Results!I:I,$B$11,Results!G:G,$C$11,Results!C:C, 1, Results!A:A,"ORG") -> 6 | P11: =IFERROR(M11/F11, 0) -> 0 | Q11: =IFERROR(N11/G11, 0) -> 0.00050226017 | R11: =IFERROR(O11/H11, 0) -> 0.0010781671
B12: intersection | C12: LOC | D12: =COUNTIFS(Results!G:G, C12, Results!I:I, B12) -> 1296 | E12: =COUNTIFS(Results!G:G, C12, Results!I:I, B12, Results!B:B, 0) -> 74 | F12: =COUNTIFS(Results!G:G, C12, Results!I:I, B12, Results!C:C, 1) -> 1238 | G12: =COUNTIFS(Results!G:G, C12, Results!I:I, B12, Results!D:D, 1) -> 1253 | H12: =COUNTIFS(Results!G:G, C12, Results!I:I, B12, Results!B:B, 1) -> 1217 | I12: =IFERROR(E12/D12, 0) -> 0.057098765 | J12: =IFERROR(F12/$D$12, 0) -> 0.95524691 | K12: =IFERROR(G12/$D$12, 0) -> 0.96682099 | L12: =IFERROR(H12/$D$12, 0) -> 0.93904321 | M12: =COUNTIFS(Results!$I:$I,$B$12,Results!$G:$G,$C$12,Results!$C:$C, 1, Results!$A:$A,"PER") -> 6 | N12: 0 | O12: =COUNTIFS(Results!$I:$I,$B$12,Results!$G:$G,$C$12,Results!$C:$C, 1, Results!$A:$A,"ORG") -> 13 | P12: =IFERROR(M12/F12, 0) -> 0.0048465267 | Q12: =IFERROR(N12/G12, 0) -> 0 | R12: =IFERROR(O12/H12, 0) -> 0.010682005
B13: intersection | C13: ORG | D13: =COUNTIFS(Results!G:G, C13, Results!I:I, B13) -> 161 | E13: =COUNTIFS(Results!G:G, C13, Results!I:I, B13, Results!B:B, 0) -> 17 | F13: =COUNTIFS(Results!G:G, C13, Results!I:I, B13, Results!C:C, 1) -> 142 | G13: =COUNTIFS(Results!G:G, C13, Results!I:I, B13, Results!D:D, 1) -> 138 | H13: =COUNTIFS(Results!G:G, C13, Results!I:I, B13, Results!B:B, 1) -> 138 | I13: =IFERROR(E13/D13, 0) -> 0.10559006 | J13: =IFERROR(F13/$D$13, 0) -> 0.88198758 | K13: =IFERROR(G13/$D$13, 0) -> 0.85714286 | L13: =IFERROR(H13/$D$13, 0) -> 0.85714286 | M13: =COUNTIFS(Results!$I:$I,$B$13,Results!$G:$G,$C$13,Results!$C:$C, 1, Results!$A:$A,"PER") -> 4 | N13: =COUNTIFS(Results!$I:$I,$B$13,Results!$G:$G,$C$13,Results!$C:$C, 1, Results!$A:$A,"LOC") -> 0 | O13: 0 | P13: =IFERROR(M13/F13, 0) -> 0.028169014 | Q13: =IFERROR(N13/G13, 0) -> 0 | R13: =IFERROR(O13/H13, 0) -> 0
B14: intersection | C14: MISC | D14: =COUNTIFS(Results!G:G, C14, Results!I:I, B14) -> 0 | E14: =COUNTIFS(Results!G:G, C14, Results!I:I, B14, Results!B:B, 0) -> 0 | F14: =COUNTIFS(Results!G:G, C14, Results!I:I, B14, Results!C:C, 1) -> 0 | G14: =COUNTIFS(Results!G:G, C14, Results!I:I, B14, Results!D:D, 1) -> 0 | H14: =COUNTIFS(Results!G:G, C14, Results!I:I, B14, Results!B:B, 1) -> 0 | I14: =IFERROR(E14/D14, 0) -> 0 | J14: =IFERROR(F14/$D$14, 0) -> 0 | K14: =IFERROR(G14/$D$14, 0) -> 0 | L14: =IFERROR(H14/$D$14, 0) -> 0 | M14: =COUNTIFS(Results!$I:$I,B14,Results!$G:$G,C14,Results!$C:$C, 1, Results!$A:$A,"PER") -> 0 | N14: 0 | O14: 0 | P14: =IFERROR(M14/F14, 0) -> 0 | Q14: =IFERROR(N14/G14, 0) -> 0 | R14: =IFERROR(O14/H14, 0) -> 0
A18: NE only found by casEN (without intersection) | B18: casEN | C18: NE | D18: =COUNTIFS(Results!I:I, B18) -> 7536 | E18: =COUNTIFS(Results!I:I, B19, Results!B:B, 0) -> 632 | F18: =COUNTIFS(Results!I:I, B18, Results!C:C, 1) -> 770 | G18: =COUNTIFS(Results!I:I, B18, Results!D:D, 1) -> 817 | H18: =COUNTIFS(Results!I:I, B18, Results!B:B, 1) -> 727 | I18: =IFERROR(E18/D18, 0) -> 0.083864119 | J18: =IFERROR(F18/$D$18, 0) -> 0.10217622 | K18: =IFERROR(G18/$D$18, 0) -> 0.10841295 | L18: =IFERROR(H18/$D$18, 0) -> 0.096470276 | M18: =SUM(M19:M22) -> 8 | N18: =SUM(N19:N22) -> 16 | O18: =SUM(O19:O22) -> 17 | P18: =IFERROR(M18/F18, 0) -> 0.01038961 | Q18: =IFERROR(N18/G18, 0) -> 0.019583843 | R18: =IFERROR(O18/H18, 0) -> 0.023383769
B19: casEN | C19: PER | D19: =COUNTIFS(Results!G:G, C19, Results!I:I, B19) -> 4202 | E19: =COUNTIFS(Results!G:G, C19, Results!I:I, B19, Results!B:B, 0) -> 119 | F19: =COUNTIFS(Results!G:G, C19, Results!I:I, B19, Results!C:C, 1) -> 338 | G19: =COUNTIFS(Results!G:G, C19, Results!I:I, B19, Results!D:D, 1) -> 334 | H19: =COUNTIFS(Results!G:G, C19, Results!I:I, B19, Results!B:B, 1) -> 315 | I19: =IFERROR(E19/$D$19, 0) -> 0.028319848 | J19: =IFERROR(F19/$D$19, 0) -> 0.080437887 | K19: =IFERROR(G19/$D$19, 0) -> 0.079485959 | L19: =IFERROR(H19/$D$19, 0) -> 0.074964303 | M19: 0 | N19: =COUNTIFS(Results!I:I,$B$19,Results!G:G,$C$19,Results!C:C, 1, Results!A:A,"LOC") -> 16 | O19: =COUNTIFS(Results!I:I,$B$19,Results!G:G,$C$19,Results!C:C, 1, Results!A:A,"ORG") -> 5 | P19: =IFERROR(M19/F19, 0) -> 0 | Q19: =IFERROR(N19/G19, 0) -> 0.047904192 | R19: =IFERROR(O19/H19, 0) -> 0.015873016
B20: casEN | C20: LOC | D20: =COUNTIFS(Results!G:G, C20, Results!I:I, B20) -> 925 | E20: =COUNTIFS(Results!G:G, C20, Results!I:I, B20, Results!B:B, 0) -> 511 | F20: =COUNTIFS(Results!G:G, C20, Results!I:I, B20, Results!C:C, 1) -> 430 | G20: =COUNTIFS(Results!G:G, C20, Results!I:I, B20, Results!D:D, 1) -> 480 | H20: =COUNTIFS(Results!G:G, C20, Results!I:I, B20, Results!B:B, 1) -> 410 | I20: =IFERROR(E20/$D$20, 0) -> 0.55243243 | J20: =IFERROR(F20/$D$20, 0) -> 0.46486486 | K20: =IFERROR(G20/$D$20, 0) -> 0.51891892 | L20: =IFERROR(H20/$D$20, 0) -> 0.44324324 | M20: =COUNTIFS(Results!I:I,$B$20,Results!G:G,$C$20,Results!C:C, 1, Results!A:A,"PER") -> 8 | N20: 0 | O20: =COUNTIFS(Results!I:I,$B$20,Results!G:G,$C$20,Results!C:C, 1, Results!A:A,"ORG") -> 12 | P20: =IFERROR(M20/F20, 0) -> 0.018604651 | Q20: =IFERROR(N20/G20, 0) -> 0 | R20: =IFERROR(O20/H20, 0) -> 0.029268293
B21: casEN | C21: ORG | D21: =COUNTIFS(Results!G:G, C21, Results!I:I, B21) -> 2409 | E21: =COUNTIFS(Results!G:G, C21, Results!I:I, B21, Results!B:B, 0) -> 2 | F21: =COUNTIFS(Results!G:G, C21, Results!I:I, B21, Results!C:C, 1) -> 2 | G21: =COUNTIFS(Results!G:G, C21, Results!I:I, B21, Results!D:D, 1) -> 3 | H21: =COUNTIFS(Results!G:G, C21, Results!I:I, B21, Results!B:B, 1) -> 2 | I21: =IFERROR(E21/$D$21, 0) -> 0.00083022001 | J21: =IFERROR(F21/$D$21, 0) -> 0.00083022001 | K21: =IFERROR(G21/$D$21, 0) -> 0.00124533 | L21: =IFERROR(H21/$D$21, 0) -> 0.00083022001 | M21: =COUNTIFS(Results!I:I,$B$21,Results!G:G,$C$21,Results!C:C, 1, Results!A:A,"PER") -> 0 | N21: =COUNTIFS(Results!I:I,$B$21,Results!G:G,$C$21,Results!C:C, 1, Results!A:A,"LOC") -> 0 | O21: 0 | P21: =IFERROR(M21/F21, 0) -> 0 | Q21: =IFERROR(N21/G21, 0) -> 0 | R21: =IFERROR(O21/H21, 0) -> 0
B22: casEN | C22: MISC | D22: =COUNTIFS(Results!G:G, C22, Results!I:I, B22) -> 0 | E22: =COUNTIFS(Results!G:G, C22, Results!I:I, B22, Results!B:B, 0) -> 0 | F22: =COUNTIFS(Results!G:G, C22, Results!I:I, B22, Results!C:C, 1) -> 0 | G22: =COUNTIFS(Results!G:G, C22, Results!I:I, B22, Results!D:D, 1) -> 0 | H22: =COUNTIFS(Results!G:G, C22, Results!I:I, B22, Results!B:B, 1) -> 0 | I22: =IFERROR(E22/$D$22, 0) -> 0 | J22: =IFERROR(F22/$D$22, 0) -> 0 | K22: =IFERROR(G22/$D$22, 0) -> 0 | L22: =IFERROR(H22/$D$22, 0) -> 0 | M22: 0 | N22: 0 | O22: 0 | P22: =IFERROR(M22/F22, 0) -> 0 | Q22: =IFERROR(N22/G22, 0) -> 0 | R22: =IFERROR(O22/H22, 0) -> 0
A26: NE only found by spaCy (without intersection) | B26: spaCy | C26: NE | D26: =COUNTIFS(Results!I:I, B26) -> 15127 | E26: =COUNTIFS(Results!I:I, B27, Results!B:B, 0) -> 3 | F26: =COUNTIFS(Results!I:I, B26, Results!C:C, 1) -> 14 | G26: =COUNTIFS(Results!I:I, B26, Results!D:D, 1) -> 15 | H26: =COUNTIFS(Results!I:I, B26, Results!B:B, 1) -> 14 | I26: =IFERROR(E26/$D$26, 0) -> 0.00019832088 | J26: =IFERROR(F26/$D$26, 0) -> 0.00092549745 | K26: =IFERROR(G26/$D$26, 0) -> 0.00099160442 | L26: =IFERROR(H26/$D$26, 0) -> 0.00092549745 | M26: =SUM(M27:M30) -> 0 | N26: =SUM(N27:N30) -> 0 | O26: =SUM(O27:O30) -> 0 | P26: =IFERROR(M26/F26, 0) -> 0 | Q26: =IFERROR(N26/G26, 0) -> 0 | R26: =IFERROR(O26/H26, 0) -> 0
B27: spaCy | C27: PER | D27: =COUNTIFS(Results!G:G, C27, Results!I:I, B27) -> 4413 | E27: =COUNTIFS(Results!G:G, C27, Results!I:I, B27, Results!B:B, 0) -> 2 | F27: =COUNTIFS(Results!G:G, C27, Results!I:I, B27, Results!C:C, 1) -> 14 | G27: =COUNTIFS(Results!G:G, C27, Results!I:I, B27, Results!D:D, 1) -> 15 | H27: =COUNTIFS(Results!G:G, C27, Results!I:I, B27, Results!B:B, 1) -> 14 | I27: =IFERROR(E27/$D$27, 0) -> 0.00045320644 | J27: =IFERROR(F27/$D$27, 0) -> 0.003172445 | K27: =IFERROR(G27/$D$27, 0) -> 0.0033990483 | L27: =IFERROR(H27/$D$27, 0) -> 0.003172445 | M27: 0 | N27: =COUNTIFS(Results!I:I,B27,Results!G:G,C27,Results!C:C, 1, Results!A:A,"LOC") -> 0 | O27: =COUNTIFS(Results!I:I,B27,Results!G:G,C27,Results!C:C, 1, Results!A:A,"ORG") -> 0 | P27: =IFERROR(M27/F27, 0) -> 0 | Q27: =IFERROR(N27/G27, 0) -> 0 | R27: =IFERROR(O27/H27, 0) -> 0
B28: spaCy | C28: LOC | D28: =COUNTIFS(Results!G:G, C28, Results!I:I, B28) -> 5476 | E28: =COUNTIFS(Results!G:G, C28, Results!I:I, B28, Results!B:B, 0) -> 1 | F28: =COUNTIFS(Results!G:G, C28, Results!I:I, B28, Results!C:C, 1) -> 0 | G28: =COUNTIFS(Results!G:G, C28, Results!I:I, B28, Results!D:D, 1) -> 0 | H28: =COUNTIFS(Results!G:G, C28, Results!I:I, B28, Results!B:B, 1) -> 0 | I28: =IFERROR(E28/$D$28, 0) -> 0.00018261505 | J28: =IFERROR(F28/$D$28, 0) -> 0 | K28: =IFERROR(G28/$D$28, 0) -> 0 | L28: =IFERROR(H28/$D$28, 0) -> 0 | M28: =COUNTIFS(Results!I:I,$B$28,Results!G:G,$C$28,Results!C:C, 1, Results!A:A,"PER") -> 0 | N28: 0 | O28: =COUNTIFS(Results!I:I,B28,Results!G:G,C28,Results!C:C, 1, Results!A:A,"ORG") -> 0 | P28: =IFERROR(M28/F28, 0) -> 0 | Q28: =IFERROR(N28/G28, 0) -> 0 | R28: =IFERROR(O28/H28, 0) -> 0
B29: spaCy | C29: ORG | D29: =COUNTIFS(Results!G:G, C29, Results!I:I, B29) -> 921 | E29: =COUNTIFS(Results!G:G, C29, Results!I:I, B29, Results!B:B, 0) -> 0 | F29: =COUNTIFS(Results!G:G, C29, Results!I:I, B29, Results!C:C, 1) -> 0 | G29: =COUNTIFS(Results!G:G, C29, Results!I:I, B29, Results!D:D, 1) -> 0 | H29: =COUNTIFS(Results!G:G, C29, Results!I:I, B29, Results!B:B, 1) -> 0 | I29: =IFERROR(E29/$D$29, 0) -> 0 | J29: =IFERROR(F29/$D$29, 0) -> 0 | K29: =IFERROR(G29/$D$29, 0) -> 0 | L29: =IFERROR(H29/$D$29, 0) -> 0 | M29: =COUNTIFS(Results!I:I,$B$29,Results!G:G,$C$29,Results!C:C, 1, Results!A:A,"PER") -> 0 | N29: =COUNTIFS(Results!I:I,B29,Results!G:G,C29,Results!C:C, 1, Results!A:A,"LOC") -> 0 | O29: 0 | P29: =IFERROR(M29/F29, 0) -> 0 | Q29: =IFERROR(N29/G29, 0) -> 0 | R29: =IFERROR(O29/H29, 0) -> 0
B30: spaCy | C30: MISC | D30: =COUNTIFS(Results!G:G, C30, Results!I:I, B30) -> 4317 | E30: =COUNTIFS(Results!G:G, C30, Results!I:I, B30, Results!B:B, 0) -> 0 | F30: =COUNTIFS(Results!G:G, C30, Results!I:I, B30, Results!C:C, 1) -> 0 | G30: =COUNTIFS(Results!G:G, C30, Results!I:I, B30, Results!D:D, 1) -> 0 | H30: =COUNTIFS(Results!G:G, C30, Results!I:I, B30, Results!B:B, 1) -> 0 | I30: =IFERROR(E30/$D$30, 0) -> 0 | J30: =IFERROR(F30/$D$30, 0) -> 0 | K30: =IFERROR(G30/$D$30, 0) -> 0 | L30: =IFERROR(H30/$D$30, 0) -> 0 | M30: =COUNTIFS(Results!I:I,$B$30,Results!G:G,$C$30,Results!C:C, 1, Results!A:A,"PER") -> 0 | N30: =COUNTIFS(Results!I:I,B30,Results!G:G,C30,Results!C:C, 1, Results!A:A,"LOC") -> 0 | O30: =COUNTIFS(Results!I:I,B30,Results!G:G,C30,Results!C:C, 1, Results!A:A,"ORG") -> 0 | P30: =IFERROR(M30/F30, 0) -> 0 | Q30: =IFERROR(N30/G30, 0) -> 0 | R30: =IFERROR(O30/H30, 0) -> 0
